Workbook

Sheet README
A1: Faceprint Atlas: facial privacy protection literature workbook
A2: 225 entries from 1999 to 2026, densest coverage from 2018. Last updated September 2026. Interactive version: https://atulkr05.github.io/atlas.html
A4: How to use this workbook
A5: "All papers" holds every entry with the full record. Year tabs (Before 2018, then 2018 onward) and family tabs hold the same columns filtered. "Summary" counts entries by year and family with live COUNTIFS formulas over "All papers". "Attacks vs defenses" pairs defense papers with the papers that tested them. "Datasets index" and "Models index" count how often common datasets and backbones appear.
A7: Families
A8: Blur, pixelation & obfuscation | B8: Blur, pixelate, scramble, warp, average k faces, or capture less in the first place. The oldest family, and the one most often shown not to stop machines. Examples: k-Same, Street View blur, privacy optics.
A9: Differential privacy | B9: Calibrated noise with a formal privacy budget, applied to pixels, features, templates, gradients or generative models. Examples: DP-SGD, IdentityDP, DP diffusion.
A10: De-identification (generative) | B10: Synthesise a new face that keeps pose, expression and attributes but not identity. GANs from 2017, diffusion from 2023, often reversible with a key. Examples: DeepPrivacy, CIAGAN, RiDDLE, G2Face.
A11: Adversarial privacy | B11: Perturb photos, makeup or accessories so recognisers fail while humans see the same face. Cloaks poison training; masks and makeup evade matching. Examples: Fawkes, LowKey, CLIP2Protect, DiffAM.
A12: Unlearnable images & anti-customisation | B12: Make images useless as training data: unlearnable examples against classifiers, and anti-DreamBooth protections against personalised diffusion models. Examples: Unlearnable Examples, Anti-DreamBooth, PhotoGuard.
A13: Identity protection: templates & encrypted matching | B13: Protect the faceprint itself: cancelable transforms, fuzzy vaults, homomorphic encryption, and recognition on representations that hide the image. Examples: PolyProtect, HERS, IronMask, PartialFace.
A14: Soft-biometric privacy | B14: Keep a face usable for matching while suppressing what else it reveals: gender, age, ethnicity, health. Examples: PrivacyNet, SensitiveNets, PASS.
A15: Training-data privacy & synthetic data | B15: Train recognisers without hoarding faces: federated learning, synthetic identities, consented datasets, instance encoding. Examples: FedFace, DCFace, DigiFace-1M.
A16: Machine unlearning & auditing | B16: Remove a person from a trained model, erase an identity from a generator, or prove that a face was used in training. Examples: SalUn, GUIDE, Face-Auditor.
A17: Attacks & evaluations | B17: Papers that invert templates, defeat obfuscation, break cloaks and unlearnable examples, or measure whether anonymisation really removes identity. Examples: NbNet, Data Poisoning Won't Save You, GrIDPure.
A18: Surveys, audits & society | B18: Surveys that organise the field, audits that exposed bias, investigations and standards that changed what is deployed. Examples: Meden et al. 2021, Gender Shades, Exposing.ai.
A20: Caveats
B21: Curated catalogue, not a systematic review. Venues and years were checked against arXiv metadata and proceedings; preprints may since have been published. Findings are summaries, so read the paper before citing a number. Code links point only to repositories that could be confirmed.

Sheet All papers
A1: All papers
A2: Every entry, newest first. Use the filter arrows on the header row.
A4: # | B4: ID | C4: Paper title | D4: Authors | E4: Year | F4: Venue | G4: Venue type | H4: Family | I4: Chart group | J4: Datasets | K4: Models / backbones | L4: Approach | M4: Key findings | N4: Threat model / protects against | O4: Utility preserved | P4: Limitations & known attacks | Q4: Tags | R4: Code available | S4: GitHub / code link | T4: Paper link | U4: Google Scholar
A5: 1 | B5: hahn2026 | C5: A Deeper Dive into the Irreversibility of PolyProtect: Making Protected Face Templates Harder to Invert | D5: Vedrana Krivokuća Hahn, Jérémy Maceiras, Sébastien Marcel | E5: 2026 | F5: Under review (submitted to IEEE TIFS) | G5: Preprint | H5: Attacks & evaluations | I5: Attacks & evaluations | J5: MOBIO, LFW | K5: PolyProtect templates | L5: Analyses inversion of PolyProtect templates and proposes a key-selection algorithm that raises inversion difficulty consistently across parameters. | M5: Showed prior parameter choices left some templates invertible and fixed it with principled key selection. | N5: Attacker with protected templates. | O5: Verification accuracy retained. | P5: Under review. | Q5: PolyProtect, inversion, key selection | R5: No | T5: https://arxiv.org/abs/2605.03857 | U5: Search
A6: 2 | B6: zhang2026 | C6: Adversarial Attacks for Good: A Survey of Proactive Protection across the Visual Content Lifecycle | D6: Jiaming Zhang, Boyang Chen, Zherui Li, Fuyao Zhang, Xinyu Yan, Hong Xi Tae, Wenwen He, Xuan Wang, Siqi Guo, Junhao Dong, Kun Wang, Hanxun Huang, Yige Li, Xingjun Ma, Yang Cao, Lingjuan Lyu, Wei Yang Bryan Lim | E6: 2026 | F6: arXiv preprint | G6: Preprint | H6: Surveys, audits & society | I6: Surveys & society | J6: Survey | K6: Survey | L6: Surveys the use of adversarial perturbation as protection across creation, sharing and training of visual content, including face cloaks and anti-deepfake immunisation. | M6: Frames cloaking, watermarking and immunisation as one family with shared robustness problems. | N6: Not applicable. | O6: Not applicable. | P6: Preprint. | Q6: survey, proactive protection, adversarial for good | R6: No | T6: https://arxiv.org/abs/2608.04314 | U6: Search
A7: 3 | B7: wang2026diffmi | C7: DiffMI: Breaking Face Recognition Privacy via Diffusion-Driven Training-Free Model Inversion | D7: Hanrui Wang, Shuo Wang, Chun-Shien Lu, Isao Echizen | E7: 2026 | F7: IEEE TIFS | G7: Journal | H7: Attacks & evaluations | I7: Attacks & evaluations | J7: LFW, CelebA-HQ | K7: Diffusion prior; privacy-resistant recognisers | L7: Training-free diffusion-guided inversion that reconstructs faces from embeddings without a model-specific inverter. | M7: Attack success of 84.42% to 92.87% against privacy-resistant recognisers, including some designed to resist inversion. | N7: Attacker with embeddings from protected systems. | O7: Not applicable. | P7: Compute-heavy sampling. | Q7: model inversion, diffusion, training-free | R7: No | T7: https://arxiv.org/abs/2504.18015 | U7: Search
A8: 4 | B8: wei2026toolbox | C8: FDeID-Toolbox: Face De-Identification Toolbox | D8: Hui Wei, Hao Yu, Guoying Zhao | E8: 2026 | F8: Technical report (arXiv) | G8: Preprint | H8: Surveys, audits & society | I8: Surveys & society | J8: CelebA-HQ, FFHQ, LFW | K8: Many de-identification methods (toolbox) | L8: Open toolbox implementing many de-identification methods with shared evaluation for privacy, utility and quality. | M8: A step toward the unified evaluation every survey since 2016 has asked for. | N8: Not applicable. | O8: Not applicable. | P8: Coverage still growing. | Q8: toolbox, benchmark, open source | R8: Yes | S8: https://arxiv.org/abs/2603.13121 | T8: https://arxiv.org/abs/2603.13121 | U8: Search
A9: 5 | B9: wei2026survey | C9: Face De-Identification: A Domain-Centric Survey from Capture to Processing | D9: Hui Wei, Hao Yu, Guoying Zhao | E9: 2026 | F9: arXiv preprint | G9: Preprint | H9: Surveys, audits & society | I9: Surveys & society | J9: Survey | K9: Survey | L9: Taxonomy by where the privacy transformation happens: before capture (physical), at the sensor, or after capture (digital). | M9: First survey to treat camera-side and optics-based protection alongside image processing. | N9: Not applicable. | O9: Not applicable. | P9: Preprint. | Q9: survey, physical/sensor/digital domains | R9: No | T9: https://arxiv.org/abs/2607.25926 | U9: Search
A10: 6 | B10: guo2026 | C10: FaceLinkGen: A Re-evaluation of Identity Leakage in Privacy-Preserving Face Recognition and Face Anonymization Systems Using Simple Distillation | D10: Wenqi Guo, Mohamed Shehata, Shan Du | E10: 2026 | F10: arXiv preprint | G10: Preprint | H10: Attacks & evaluations | I10: Attacks & evaluations | J10: LFW, CelebA | K10: Distilled linking model | L10: Distils a linking model that connects protected representations or anonymised faces back to identities. | M10: Recovered identities at rates above 74% across tested privacy-preserving recognition and de-identification systems. | N10: Attacker with access to protected outputs and public face data. | O10: Not applicable. | P10: Preprint; systems tested are academic. | Q10: distillation, leakage, PPFR, anonymisation | R10: No | T10: https://arxiv.org/abs/2602.02914 | U10: Search
A11: 7 | B11: wang2026flux | C11: Flux-Guard: Facial Identity Protection using Diffusion Models | D11: Jie Wang, Tao Wang, Ru Zhang, Jianyi Liu | E11: 2026 | F11: arXiv preprint | G11: Preprint | H11: Adversarial privacy | I11: Adversarial & unlearnable | J11: CelebA-HQ | K11: FLUX diffusion backbone | L11: Uses a large diffusion backbone to generate identity-protected faces guided against recognisers. | M11: Reported strong black-box protection with high image quality. | N11: Black-box recognisers. | O11: Natural appearance. | P11: Preprint; untested against adaptive attackers. | Q11: diffusion, identity protection | R11: No | T11: https://arxiv.org/abs/2606.17606 | U11: Search
A12: 8 | B12: wen2026 | C12: Image Privacy Protection: A Survey | D12: Wenying Wen, Ziye Yuan, Yushu Zhang, Tao Wang, Xiangli Xiao, Ruoyu Zhao, Yuming Fang | E12: 2026 | F12: ACM Computing Surveys | G12: Journal | H12: Surveys, audits & society | I12: Surveys & society | J12: Survey | K12: Survey | L12: Survey of image privacy protection spanning encryption, perturbation, anonymisation and access control. | M12: Places face-specific methods in the wider image privacy landscape. | N12: Not applicable. | O12: Not applicable. | P12: Breadth over depth. | Q12: survey, image privacy | R12: No | T12: https://arxiv.org/abs/2412.15228 | U12: Search
A13: 9 | B13: honig2025 | C13: Adversarial Perturbations Cannot Reliably Protect Artists From Generative AI | D13: Robert Hönig, Javier Rando, Nicholas Carlini, Florian Tramèr | E13: 2025 | F13: ICLR (arXiv 2024) | G13: ML | H13: Attacks & evaluations | I13: Attacks & evaluations | J13: Artists' styles (WikiArt and contemporary), face sets | K13: Stable Diffusion fine-tuning; Glaze, Mist, Anti-DreamBooth | L13: Shows that low-effort, off-the-shelf techniques (noisy upscaling, Gaussian noise, IMPRESS-style purification) let a forger fine-tune on protected art or photos anyway; includes a user study. | M13: Every tested protection, including Glaze, Mist and Anti-DreamBooth, was bypassed; the authors argue perturbation-based protection gives a false sense of security, echoing the Fawkes result. | N13: Images protected against fine-tuning. | O13: Not applicable. | P13: Focused on style mimicry; identity-customisation findings transfer. | Q13: Glaze, Mist, Anti-DreamBooth, robust mimicry | R13: Yes | S13: https://github.com/ethz-spylab/robust-style-mimicry | T13: https://arxiv.org/abs/2406.12027 | U13: Search
A14: 10 | B14: mustu2025 | C14: Assessing the Use of Face Swapping Methods as Face Anonymizers in Videos | D14: Mustafa İzzet Muştu, Hazım Kemal Ekenel | E14: 2025 | F14: IEEE DSP | G14: Other | H14: Attacks & evaluations | I14: Attacks & evaluations | J14: Video face benchmarks | K14: SimSwap, FaceShifter and other swappers | L14: Evaluates general-purpose face swappers as anonymisers on video for identity removal, temporal consistency and quality. | M14: Face swappers anonymised effectively but with identity leakage and consistency issues that vary by method. | N14: Not a threat paper: measures anonymisation quality. | O14: Video quality and consistency. | P14: Limited set of swappers. | Q14: evaluation, face swapping, video | R14: No | T14: https://arxiv.org/abs/2505.20985 | U14: Search
A15: 11 | B15: kwon2025 | C15: Controllable Adversarial Makeup for Privacy via Text-Guided Diffusion | D15: Youngjin Kwon, Xiao Zhang | E15: 2025 | F15: arXiv preprint | G15: Preprint | H15: Adversarial privacy | I15: Adversarial & unlearnable | J15: CelebA-HQ | K15: Stable Diffusion, CLIP | L15: MASQUE generates localised adversarial makeup from text prompts with a diffusion model, targeting dodging rather than impersonation. | M15: Robust dodging with higher perceptual fidelity and adaptability across prompts. | N15: Recognisers matching shared photos. | O15: User-chosen makeup style. | P15: Preprint. | Q15: MASQUE, diffusion, text-guided | R15: No | T15: https://arxiv.org/abs/2503.10549 | U15: Search
A16: 12 | B16: liu2023diffprotect | C16: DiffProtect: Generate Adversarial Examples with Diffusion Models for Facial Privacy Protection | D16: Jiang Liu, Chun Pong Lau, Zhongliang Guo, Yuxiang Guo, Zhaoyang Wang, Rama Chellappa | E16: 2025 | F16: Pattern Recognition (arXiv 2023) | G16: Journal | H16: Adversarial privacy | I16: Adversarial & unlearnable | J16: CelebA-HQ, LADN | K16: Diffusion autoencoder; IR152, IRSE50, FaceNet, MobileFace | L16: Uses a diffusion autoencoder to produce semantically meaningful, natural perturbations rather than pixel noise. | M16: Higher attack success and naturalness than pixel-space methods on face verification. | N16: Black-box recognisers. | O16: Natural-looking edits. | P16: Sampling cost; static protection. | Q16: diffusion, semantic perturbation | R16: Yes | S16: https://github.com/joellliu/DiffProtect | T16: https://arxiv.org/abs/2305.13625 | U16: Search
A17: 13 | B17: wang2025mm | C17: Diffusion-based Adversarial Identity Manipulation for Facial Privacy Protection | D17: Liqin Wang, Qianyue Hu, Wei Lu, Xiangyang Luo | E17: 2025 | F17: ACM Multimedia | G17: Vision | H17: Adversarial privacy | I17: Adversarial & unlearnable | J17: CelebA-HQ, LADN | K17: Diffusion sampling with identity guidance | L17: Manipulates identity-relevant components during diffusion sampling to produce protected faces. | M17: Improved transfer to black-box recognisers with natural results. | N17: Black-box recognisers. | O17: Natural appearance. | P17: Static protection. | Q17: diffusion, identity manipulation | R17: No | T17: https://arxiv.org/abs/2504.21646 | U17: Search
A18: 14 | B18: salar2025 | C18: Enhancing Facial Privacy Protection via Weakening Diffusion Purification | D18: Ali Salar, Qing Liu, Yingli Tian, Guoying Zhao | E18: 2025 | F18: CVPR | G18: Vision | H18: Adversarial privacy | I18: Adversarial & unlearnable | J18: CelebA-HQ, LADN | K18: Diffusion latent optimisation; IR152, IRSE50, FaceNet, MobileFace | L18: Learns unconditional embeddings to steer adversarial latent codes so that diffusion purification, a defense that washes out adversarial noise, no longer removes the protection; adds an identity-preserving structure. | M18: Protection survived purification-based recognisers where earlier methods failed. | N18: Recognisers that purify inputs before matching. | O18: Structural consistency with the original. | P18: Addresses one adaptive defense; others remain. | Q18: diffusion purification, adaptive attacker, latent | R18: Yes | S18: https://github.com/parham1998/Facial-Privacy-Protection | T18: https://openaccess.thecvf.com/content/CVPR2025/html/Salar_Enhancing_Facial_Privacy_Protection_via_Weakening_Diffusion_Purification_CVPR_2025_paper.html | U18: Search
A19: 15 | B19: kung2025 | C19: Face Anonymization Made Simple | D19: Han-Wei Kung, Tuomas Varanka, Sanjay Saha, Terence Sim, Nicu Sebe | E19: 2025 | F19: WACV (oral) | G19: Vision | H19: De-identification (generative) | I19: Generative de-identification | J19: CelebA-HQ, FFHQ | K19: Stable Diffusion fine-tuned for anonymisation and swapping | L19: A diffusion model trained with reconstruction losses only, needing no landmarks or masks; the same model performs anonymisation and face swapping. | M19: Preserved expression, head pose, gaze and background while changing identity; simpler pipeline than prior GAN methods. | N19: Automated face recognition on images. | O19: Expression, pose, gaze, background. | P19: Identity leakage not evaluated against adaptive attackers. | Q19: diffusion, no landmarks, face swapping | R19: Yes | S19: https://github.com/hanweikung/face_anon_simple | T19: https://arxiv.org/abs/2411.00762 | U19: Search
A20: 16 | B20: shahreza2025 | C20: Face Reconstruction from Face Embeddings using Adapter to a Face Foundation Model | D20: Hatef Otroshi Shahreza, Anjith George, Sébastien Marcel | E20: 2025 | F20: CVPR Workshops | G20: Vision | H20: Attacks & evaluations | I20: Attacks & evaluations | J20: FFHQ, LFW, MOBIO, AgeDB | K20: Arc2Face foundation model + adapters; ArcFace, AdaFace | L20: Trains a small adapter that maps embeddings from any recogniser into a face foundation model's conditioning space. | M20: High-fidelity reconstructions from many different recognisers with one foundation model and cheap adapters. | N20: Attacker with embeddings from arbitrary systems. | O20: Not applicable. | P20: Inherits the foundation model's biases. | Q20: template inversion, foundation model, adapter | R20: No | T20: https://arxiv.org/abs/2411.03960 | U20: Search
A21: 17 | B21: wang2025survey | C21: Facial Privacy in the Digital Era: A Comprehensive Survey on Methods, Evaluation, and Future Directions | D21: Miaomiao Wang et al. | E21: 2025 | F21: Computer Science Review | G21: Journal | H21: Surveys, audits & society | I21: Surveys & society | J21: Survey | K21: Survey | L21: Organises facial privacy methods into appearance-guided, identity-guided, reversible and modular paradigms with an evaluation review. | M21: Argues for unified benchmarks jointly measuring privacy, utility and visual quality. | N21: Not applicable. | O21: Not applicable. | P21: Author list abbreviated here; see DOI. | Q21: survey, four paradigms | R21: No | T21: https://doi.org/10.1016/j.cosrev.2025.100785 | U21: Search
A22: 18 | B22: song2025idprotector | C22: IDProtector: An Adversarial Noise Encoder to Protect Against ID-Preserving Image Generation | D22: Yiren Song, Pei Yang, Hai Ci, Mike Zheng Shou | E22: 2025 | F22: CVPR | G22: Vision | H22: Unlearnable images & anti-customisation | I22: Adversarial & unlearnable | J22: CelebA-HQ, FFHQ | K22: InstantID, IP-Adapter, PhotoMaker, PuLID | L22: A single feed-forward encoder adds noise that defeats encoder-based, zero-shot identity customisation (InstantID, IP-Adapter, PhotoMaker) rather than fine-tuning-based DreamBooth. | M22: One-pass protection generalised across identity-preserving generators and survived common transformations. | N22: Zero-shot face personalisation from one photo. | O22: Imperceptible noise. | P22: Targets the current family of encoders; new encoders need retraining. | Q22: encoder-based customisation, InstantID, IP-Adapter | R22: No | T22: https://arxiv.org/abs/2412.11638 | U22: Search
A23: 19 | B23: razzhigaev2025 | C23: Inverting Black-Box Face Recognition Systems via Zero-Order Optimization in Eigenface Space | D23: Anton Razzhigaev, Matvey Mikhalchuk, Klim Kireev, Igor Udovichenko, Andrey Kuznetsov, Aleksandr Petiushko | E23: 2025 | F23: arXiv preprint | G23: Preprint | H23: Attacks & evaluations | I23: Attacks & evaluations | J23: LFW, CelebA | K23: Black-box recognisers returning scores | L23: DarkerBB reconstructs a face using only similarity scores returned by a black-box system, optimising in a PCA face space with zero-order methods. | M23: Competitive reconstructions with no embedding access at all, only scores. | N23: Any system that returns similarity scores. | O23: Not applicable. | P23: Query-hungry; rate limiting is a mitigation. | Q23: black-box, similarity scores, inversion | R23: No | T23: https://arxiv.org/abs/2506.09777 | U23: Search
A24: 20 | B24: wang2025percept | C24: Make Identity Unextractable yet Perceptible: Synthesis-Based Privacy Protection for Subject Faces in Photos | D24: Tao Wang, Yushu Zhang, Xiangli Xiao, Kun Xu, Lin Yuan, Wenying Wen, Yuming Fang | E24: 2025 | F24: arXiv preprint | G24: Preprint | H24: De-identification (generative) | I24: Generative de-identification | J24: CelebA-HQ, LFW | K24: GAN synthesis with perceptual loss; ArcFace for evaluation | L24: PerceptFace synthesises a face that automated recognisers cannot match but that friends still recognise, via a perceptual similarity loss on human-sensitive regions. | M24: Reversed the usual trade-off: machine recognition removed, human recognition kept. | N24: Automated recognition of shared photos. | O24: Human recognisability and photo aesthetics. | P24: Preprint; robustness to adaptive recognisers untested. | Q24: perceptual, synthesis, human recognisability | R24: No | T24: https://arxiv.org/abs/2509.11249 | U24: Search
A25: 21 | B25: egin2025 | C25: Now You See Me, Now You Don't: A Unified Framework for Expression Consistent Anonymization in Talking Head Videos | D25: Anil Egin, Andrea Tangherloni, Antitza Dantcheva | E25: 2025 | F25: ICCV Workshops | G25: Vision | H25: De-identification (generative) | I25: Generative de-identification | J25: Talking-head video sets (VoxCeleb, HDTF) | K25: Diffusion-based anonymiser with expression consistency | L25: AnonNET anonymises talking-head video while enforcing expression consistency over time. | M25: Kept expression dynamics stable across frames while identity changed, addressing flicker in per-frame methods. | N25: Identity recognition in video. | O25: Expression and lip movement. | P25: Workshop paper; evaluation on talking-head data only. | Q25: video, expression, talking head | R25: Yes | S25: https://github.com/anilegin/AnonNET | T25: https://arxiv.org/abs/2601.11635 | U25: Search
A26: 22 | B26: wang2025protego | C26: Protego: User-Centric Pose-Invariant Privacy Protection Against Face Recognition-Induced Digital Footprint Exposure | D26: Ziling Wang, Shuya Yang, Jialin Lu, Ka-Ho Chow | E26: 2025 | F26: arXiv preprint | G26: Preprint | H26: Adversarial privacy | I26: Adversarial & unlearnable | J26: CelebA-HQ; multi-pose sets | K26: 3D-aware perturbation template | L26: A 3D-aware, pose-invariant protection template per user applied across all their photos so recognisers cannot link them. | M26: Held protection across pose variation where per-image perturbations degrade. | N26: Linking a user's photos across the web. | O26: Photos remain natural. | P26: Preprint. | Q26: pose-invariant, 3D, digital footprint | R26: No | T26: https://arxiv.org/abs/2508.02034 | U26: Search
A27: 23 | B27: labarbarie2025 | C27: Secure and Reversible Face Anonymization with Diffusion Models | D27: Pol Labarbarie, Vincent Itier, William Puech | E27: 2025 | F27: arXiv preprint | G27: Preprint | H27: De-identification (generative) | I27: Generative de-identification | J27: CelebA-HQ | K27: Key-conditioned diffusion model | L27: Key-conditioned diffusion anonymisation whose inversion recovers the original only with the secret. | M27: Reversibility with a key and resistance to recovery without it, on standard face benchmarks. | N27: Unauthorised viewers of stored images. | O27: Exact recovery for key holder. | P27: Preprint; security argued empirically. | Q27: diffusion, reversible, key | R27: No | T27: https://arxiv.org/abs/2510.01031 | U27: Search
A28: 24 | B28: wu2025 | C28: Vec2Face: Scaling Face Dataset Generation with Loosely Constrained Vectors | D28: Haiyu Wu, Jaskirat Singh, Sicong Tian, Liang Zheng, Kevin W. Bowyer | E28: 2025 | F28: ICLR | G28: ML | H28: Training-data privacy & synthetic data | I28: Training data & unlearning | J28: WebFace4M (train); LFW, CFP-FP, AgeDB, CALFW, CPLFW, Hadrian, Eclipse | K28: Feature-to-image generator; ArcFace/ViT recognisers | L28: Generates faces from sampled feature vectors with loose constraints, scaling to hundreds of thousands of synthetic identities. | M28: Larger synthetic identity counts than prior work, approaching real-data accuracy on standard benchmarks. | N28: Training on real faces. | O28: Recognition accuracy. | P28: Leakage from the generator's training data unresolved. | Q28: synthetic data, scalable identities | R28: Yes | S28: https://github.com/HaiyuWu/vec2face | T28: https://arxiv.org/abs/2409.02979 | U28: Search
A29: 25 | B29: zhao2025 | C29: Visual Content Privacy Protection: A Survey | D29: Ruoyu Zhao, Yushu Zhang, Tao Wang, Wenying Wen, Yong Xiang, Xiaochun Cao | E29: 2025 | F29: ACM Computing Surveys | G29: Journal | H29: Surveys, audits & society | I29: Surveys & society | J29: Survey | K29: Survey | L29: Surveys protection of visual content across the lifecycle, framed by who the adversary is and what they see. | M29: Unifies face, scene and document privacy under one threat taxonomy. | N29: Not applicable. | O29: Not applicable. | P29: Broad rather than deep on faces. | Q29: survey, visual privacy | R29: No | T29: https://arxiv.org/abs/2303.16552 | U29: Search
A30: 26 | B30: papantoniou2024 | C30: Arc2Face: A Foundation Model for ID-Consistent Human Faces | D30: Foivos Paraperas Papantoniou, Alexandros Lattas, Stylianos Moschoglou, Jiankang Deng, Bernhard Kainz, Stefanos Zafeiriou | E30: 2024 | F30: ECCV | G30: Vision | H30: Training-data privacy & synthetic data | I30: Training data & unlearning | J30: WebFace42M (upsampled), FFHQ; LFW, CFP-FP, AgeDB | K30: Stable Diffusion conditioned on ArcFace | L30: Diffusion model conditioned directly on ArcFace embeddings to generate identity-consistent faces at scale. | M30: Enabled high-quality synthetic datasets; also demonstrated how easily an embedding becomes a face, sharpening template-inversion concerns. | N30: Real-data training (and, inversely, template exposure). | O30: Recognition accuracy from synthetic data. | P30: Dual use: a generator for privacy and a tool for inversion. | Q30: foundation model, ArcFace conditioning, synthetic data | R30: Yes | S30: https://github.com/foivospar/Arc2Face | T30: https://arxiv.org/abs/2403.11641 | U30: Search
A31: 27 | B31: zhao2024gridpure | C31: Can Protective Perturbation Safeguard Personal Data from Being Exploited by Stable Diffusion? | D31: Zhengyue Zhao, Jinhao Duan, Kaidi Xu, Chenan Wang, Rui Zhang, Zidong Du, Qi Guo, Xing Hu | E31: 2024 | F31: CVPR | G31: Vision | H31: Attacks & evaluations | I31: Attacks & evaluations | J31: CelebA-HQ, VGGFace2, WikiArt | K31: Stable Diffusion, DreamBooth; DDPM purifier | L31: GrIDPure: grid-based iterative diffusion purification that removes anti-customisation perturbations while preserving image structure. | M31: Anti-DreamBooth, Mist and PhotoGuard protections were largely undone; personalised models trained on purified images worked again. | N31: Photos protected against diffusion personalisation. | O31: Not applicable. | P31: Purification is compute-heavy and can soften fine detail. | Q31: GrIDPure, purification, anti-DreamBooth | R31: Yes | S31: https://github.com/ZhengyueZhao/GrIDPure | T31: https://arxiv.org/abs/2312.00084 | U31: Search
A32: 28 | B32: sun2024 | C32: DiffAM: Diffusion-based Adversarial Makeup Transfer for Facial Privacy Protection | D32: Yuhao Sun, Lingyun Yu, Hongtao Xie, Jiaming Li, Yongdong Zhang | E32: 2024 | F32: CVPR | G32: Vision | H32: Adversarial privacy | I32: Adversarial & unlearnable | J32: CelebA-HQ, LADN, MT | K32: Fine-tuned diffusion with CLIP loss; IR152, IRSE50, FaceNet, MobileFace; commercial APIs | L32: Fine-tuned diffusion model transfers makeup from a reference with a CLIP-based makeup loss and an ensemble attack strategy. | M32: Gain of 12.98% attack success under black-box settings over the previous state of the art, with natural makeup. | N32: Black-box recognisers. | O32: Natural makeup. | P32: Heavy generation cost; static. | Q32: diffusion, makeup, CLIP | R32: Yes | S32: https://github.com/HansSunY/DiffAM | T32: https://arxiv.org/abs/2405.09882 | U32: Search
A33: 29 | B33: cai2024 | C33: Disguise without Disruption: Utility-Preserving Face De-Identification | D33: Zikui Cai, Zhongpai Gao, Benjamin Planche, Meng Zheng, Terrence Chen, M. Salman Asif, Ziyan Wu | E33: 2024 | F33: AAAI | G33: ML | H33: De-identification (generative) | I33: Generative de-identification | J33: Face and clinical benchmarks (see paper) | K33: Generative disguise network constrained by downstream models | L33: Generates a disguised face constrained so that downstream analysis models (e.g., clinical or expression models) produce the same outputs as on the original. | M33: Kept task outputs stable while recognition failed, including on medical images where utility is critical. | N33: Identity recognition on shared analytic data. | O33: Downstream task outputs, by constraint. | P33: Utility tied to chosen tasks; identity leakage through preserved features untested. | Q33: utility, medical, generative | R33: No | T33: https://arxiv.org/abs/2303.13269 | U33: Search
A34: 30 | B34: wang2024facelock | C34: Edit Away and My Face Will Not Stay: Personal Biometric Defense against Malicious Generative Editing | D34: Hanhui Wang, Yihua Zhang, Ruizheng Bai, Yue Zhao, Sijia Liu, Zhengzhong Tu | E34: 2024 | F34: arXiv preprint | G34: Preprint | H34: Unlearnable images & anti-customisation | I34: Adversarial & unlearnable | J34: CelebA-HQ | K34: Stable Diffusion, InstructPix2Pix, ArcFace | L34: FaceLock optimises perturbations so that any diffusion edit of the image destroys the face's biometric identity rather than just image quality. | M34: Edited outputs lost identity by recogniser measures where PhotoGuard-style protection left faces intact. | N34: Malicious editing of personal photos. | O34: Imperceptible noise. | P34: Preprint; purification not fully addressed. | Q34: FaceLock, generative editing, biometric loss | R34: No | T34: https://arxiv.org/abs/2411.16832 | U34: Search
A35: 31 | B35: melzi2024frcsyn | C35: FRCSyn Challenge at WACV 2024: Face Recognition Challenge in the Era of Synthetic Data | D35: Pietro Melzi, Ruben Tolosana, Ruben Vera-Rodriguez, Minchul Kim, Christian Rathgeb, Xiaoming Liu, Ivan DeAndres-Tame, Aythami Morales, Julian Fierrez, Javier Ortega-Garcia, et al. | E35: 2024 | F35: WACV Workshops | G35: Vision | H35: Training-data privacy & synthetic data | I35: Training data & unlearning | J35: DCFace, GANDiffFace (synthetic); CASIA-WebFace; BUPT-BalancedFace, AgeDB, CFP-FP, ROF, IJB-C | K35: Participants' ResNet and ViT recognisers | L35: Community challenge comparing recognisers trained only on synthetic data (DCFace, GANDiffFace) against real-data training, with bias analysis. | M35: Synthetic-only training approached but did not match real data; mixing synthetic and real reduced demographic bias. | N35: Real-data collection for training. | O35: Recognition accuracy. | P35: Fixed generators and protocols. | Q35: challenge, synthetic data, benchmark | R35: No | T35: https://arxiv.org/abs/2311.10476 | U35: Search
A36: 32 | B36: cao2024survey | C36: Face De-identification: State-of-the-art Methods and Comparative Studies | D36: Jingyi Cao, Xiangyi Chen, Bo Liu, Ming Ding, Rong Xie, Li Song, Zhu Li, Wenjun Zhang | E36: 2024 | F36: arXiv preprint (IEEE journal version 2026) | G36: Preprint | H36: Surveys, audits & society | I36: Surveys & society | J36: CelebA-HQ, FFHQ, LFW (comparisons) | K36: Many de-identification methods | L36: Surveys de-identification at pixel, representation and semantic levels and runs quantitative comparisons of leading methods. | M36: GAN and diffusion methods dominate the privacy-utility trade-off; evaluation protocols remain inconsistent. | N36: Not applicable. | O36: Not applicable. | P36: Comparisons on a limited set of benchmarks. | Q36: survey, comparative study, pixel/representation/semantic | R36: No | T36: https://arxiv.org/abs/2411.09863 | U36: Search
A37: 33 | B37: kuang2024 | C37: Facial Identity Anonymization via Intrinsic and Extrinsic Attention Distraction | D37: Zhenzhong Kuang, Xiaochen Yang, Yingjie Shen, Chao Hu, Jun Yu | E37: 2024 | F37: CVPR | G37: Vision | H37: De-identification (generative) | I37: Generative de-identification | J37: CelebA-HQ, FFHQ | K37: Attention-guided generator; ArcFace for evaluation | L37: Distracts a recogniser's attention both inside the face (intrinsic) and via context (extrinsic) while a generator keeps non-identity attributes. | M37: Improved the anonymity-utility balance over GAN baselines on standard benchmarks. | N37: Automated face recognition. | O37: Attributes, background. | P37: Evaluated against a fixed set of recognisers. | Q37: attention, diffusion, attribute preservation | R37: No | T37: https://arxiv.org/abs/2406.17219 | U37: Search
A38: 34 | B38: todt2024 | C38: Fantômas: Understanding Face Anonymization Reversibility | D38: Julian Todt, Simon Hanisch, Thorsten Strufe | E38: 2024 | F38: PoPETs | G38: Security | H38: Attacks & evaluations | I38: Attacks & evaluations | J38: CelebA, LFW | K38: 15 anonymisers; FaceNet/ArcFace matchers | L38: Systematically trains reconstruction and inversion attacks against fifteen face anonymisation methods. | M38: Eleven of fifteen anonymisations were at least partially reversible; visual unrecognisability was a poor proxy for irreversibility. | N38: Attacker with anonymised images and knowledge of the method. | O38: Not applicable. | P38: Attacks assume method knowledge. | Q38: reversibility, anonymisation, evaluation | R38: No | T38: https://arxiv.org/abs/2210.10651 | U38: Search
A39: 35 | B39: zhang2024fmn | C39: Forget-Me-Not: Learning to Forget in Text-to-Image Diffusion Models | D39: Eric Zhang, Kai Wang, Xingqian Xu, Zhangyang Wang, Humphrey Shi | E39: 2024 | F39: CVPR Workshops | G39: Vision | H39: Machine unlearning & auditing | I39: Training data & unlearning | J39: Custom identity and concept prompt sets | K39: Stable Diffusion | L39: Attention re-steering minimises cross-attention to the target concept's tokens so the model forgets identities, objects or styles in seconds. | M39: Forgot celebrity identities and custom concepts with minimal impact on other prompts; released as a lightweight tool. | N39: Generative models reproducing a real person. | O39: Other concepts preserved. | P39: Forgetting can be shallow against paraphrased prompts. | Q39: concept forgetting, attention re-steering, identity | R39: Yes | S39: https://github.com/SHI-Labs/Forget-Me-Not | T39: https://arxiv.org/abs/2303.17591 | U39: Search
A40: 36 | B40: yang2024g2face | C40: G2Face: High-Fidelity Reversible Face Anonymization via Generative and Geometric Priors | D40: Haoxin Yang, Xuemiao Xu, Cheng Xu, Huaidong Zhang, Jing Qin, Yi Wang, Pheng-Ann Heng, Shengfeng He | E40: 2024 | F40: IEEE TIFS | G40: Journal | H40: De-identification (generative) | I40: Generative de-identification | J40: CelebA-HQ, FFHQ, LFW | K40: StyleGAN2, 3DMM; ArcFace | L40: Combines a 3D geometric prior with StyleGAN generative priors and a secret to produce reversible anonymisation at high fidelity. | M40: Better identity removal and recovery quality than RiDDLE-class methods on standard face sets. | N40: Unauthorised recognition of stored or shared images. | O40: Recovery for key holder; pose and expression. | P40: Empirical security of the reversal path. | Q40: reversible, 3D prior, StyleGAN | R40: Yes | S40: https://github.com/Harxis/G2Face | T40: https://arxiv.org/abs/2408.09458 | U40: Search
A41: 37 | B41: hellmann2023 | C41: GANonymization: A GAN-based Face Anonymization Framework for Preserving Emotional Expressions | D41: Fabio Hellmann, Silvan Mertes, Mohamed Benouis, Alexander Hustinx, Tzung-Chien Hsieh, Cristina Conati, Peter Krawitz, Elisabeth André | E41: 2024 | F41: ACM TOMM | G41: Journal | H41: De-identification (generative) | I41: Generative de-identification | J41: CelebA, FFHQ, AffectNet, CK+ | K41: Landmark-to-image GAN | L41: Reduces a face to landmarks and regenerates a new face from them with a GAN, so identity is discarded while expression geometry survives. | M41: Expression recognition on anonymised faces stayed close to the original across several datasets. | N41: Identity recognition in affective-computing datasets. | O41: Emotional expression. | P41: Landmark-only conditioning loses skin, age and gaze cues. | Q41: expression, landmarks, GAN | R41: Yes | S41: https://github.com/hcmlab/GANonymization | T41: https://arxiv.org/abs/2305.02143 | U41: Search
A42: 38 | B42: seo2024guide | C42: Generative Unlearning for Any Identity | D42: Juwon Seo, Sung-Hoon Lee, Tae-Young Lee, Seungjun Moon, Gyeong-Moon Park | E42: 2024 | F42: CVPR | G42: Vision | H42: Machine unlearning & auditing | I42: Training data & unlearning | J42: CelebA-HQ, FFHQ | K42: StyleGAN2 | L42: GUIDE unlearns a specific identity from a pretrained GAN using a single image by erasing its latent neighbourhood with a boundary-based loss. | M42: Removed identities from StyleGAN2 while keeping generation quality, needing only one photo of the person. | N42: Generative models that can reproduce a real person. | O42: Generation quality for other identities. | P42: GAN-specific; extension to diffusion separate. | Q42: GUIDE, GAN unlearning, identity | R42: Yes | S42: https://github.com/JJuOn/GUIDE | T42: https://arxiv.org/abs/2405.09879 | U42: Search
A43: 39 | B43: dealcala2024 | C43: Is My Data in Your AI Model? Membership Inference Test with Application to Face Images | D43: Daniel DeAlcala, Aythami Morales, Gonzalo Mancera, Julian Fierrez, Ruben Tolosana, Javier Ortega-Garcia | E43: 2024 | F43: arXiv preprint | G43: Preprint | H43: Machine unlearning & auditing | I43: Training data & unlearning | J43: CASIA-WebFace, VGGFace2, MS1M, LFW | K43: ResNet-based ArcFace models | L43: Membership Inference Test: trained auditors over activation patterns to detect whether specific face images were used to train a recogniser. | M43: Detected training membership of face images with high accuracy across recognisers and datasets. | N43: Unauthorised use of a person's images for training. | O43: Not applicable. | P43: Needs access to activations; preprint. | Q43: MINT, membership inference, face recognition | R43: No | T43: https://arxiv.org/abs/2402.09225 | U43: Search
A44: 40 | B44: piano2024 | C44: Latent Diffusion Models for Attribute-Preserving Image Anonymization | D44: Luca Piano, Pietro Basci, Fabrizio Lamberti, Lia Morra | E44: 2024 | F44: arXiv preprint | G44: Preprint | H44: De-identification (generative) | I44: Generative de-identification | J44: CelebA-HQ, FFHQ | K44: Stable Diffusion with ControlNet and adapter | L44: CAMOUFLaGE: latent diffusion with ControlNets that push the anonymised image away from the original while an adapter encodes attributes to keep. | M44: Reported better attribute preservation and anonymity than GAN methods on most metrics. | N44: Identity recognition in shared images. | O44: Scene and facial attributes. | P44: Preprint; slow sampling. | Q44: diffusion, ControlNet, attributes | R44: No | T44: https://arxiv.org/abs/2403.14790 | U44: Search
A45: 41 | B45: wang2024canfg | C45: Make Privacy Renewable! Generating Privacy-Preserving Faces Supporting Cancelable Biometric Recognition | D45: Tao Wang, Yushu Zhang, Xiangli Xiao, Lin Yuan, Zhihua Xia, Jian Weng | E45: 2024 | F45: ACM Multimedia | G45: Vision | H45: De-identification (generative) | I45: Generative de-identification | J45: CelebA-HQ, LFW | K45: Cancelable face generator; ArcFace for evaluation | L45: CanFG removes the physical identity and embeds a revocable virtual identity into a generated face, so the face can still be enrolled and matched. | M45: Faces remained usable for recognition under the virtual identity; a leaked identity can be revoked and reissued. | N45: Re-identification after a database leak. | O45: Recognition on the virtual identity. | P45: Security of the virtual identity mapping is empirical. | Q45: cancelable, virtual identity, generative | R45: Yes | S45: https://github.com/daizigege/CanFG | T45: https://doi.org/10.1145/3664647.3680704 | U45: Search
A46: 42 | B46: liu2024metacloak | C46: MetaCloak: Preventing Unauthorized Subject-Driven Text-to-Image Diffusion-Based Synthesis via Meta-Learning | D46: Yixin Liu, Chenrui Fan, Yutong Dai, Xun Chen, Pan Zhou, Lichao Sun | E46: 2024 | F46: CVPR (oral) | G46: Vision | H46: Unlearnable images & anti-customisation | I46: Adversarial & unlearnable | J46: CelebA-HQ, VGGFace2 | K46: Stable Diffusion 2.1 with DreamBooth | L46: Meta-learns perturbations over a pool of surrogate models with transformation sampling so protection survives Gaussian filtering, JPEG and resizing. | M46: Outperformed Anti-DreamBooth under data transformations and remained effective on online services. | N46: Personalised diffusion fine-tuning with preprocessing. | O46: Small perturbations. | P46: Still purifiable with stronger diffusion purification. | Q46: anti-customisation, meta-learning, robust | R46: Yes | S46: https://github.com/liuyixin-louis/MetaCloak | T46: https://arxiv.org/abs/2311.13127 | U46: Search
A47: 43 | B47: shan2024nightshade | C47: Nightshade: Prompt-Specific Poisoning Attacks on Text-to-Image Generative Models | D47: Shawn Shan, Wenxin Ding, Josephine Passananti, Stanley Wu, Haitao Zheng, Ben Y. Zhao | E47: 2024 | F47: IEEE Symposium on Security and Privacy | G47: Security | H47: Unlearnable images & anti-customisation | I47: Adversarial & unlearnable | J47: LAION subsets | K47: Stable Diffusion XL, SD 2.1 | L47: Optimised poison samples that corrupt a specific concept in a text-to-image model trained on them, with fewer than a hundred samples. | M47: Concept corruption bled into related prompts; positioned as a deterrent against scraping. | N47: Scraping for text-to-image training. | O47: Images look normal. | P47: Detectable in principle; effect on very large models unclear. | Q47: poisoning, text-to-image, deterrent | R47: No | T47: https://arxiv.org/abs/2310.13828 | U47: Search
A48: 44 | B48: chow2024 | C48: Personalized Privacy Protection Mask Against Unauthorized Facial Recognition | D48: Ka-Ho Chow, Sihao Hu, Tiansheng Huang, Ling Liu | E48: 2024 | F48: ECCV | G48: Vision | H48: Adversarial privacy | I48: Adversarial & unlearnable | J48: CelebA-HQ, LFW | K48: ArcFace, FaceNet and unseen recognisers | L48: Cross-image optimisation yields one user-specific mask that generalises across the user's photos and unknown recognisers. | M48: Improved robustness to unseen models over per-image perturbations while keeping image quality. | N48: Unknown recognisers on a user's photos. | O48: Image quality preserved. | P48: Same arms-race exposure as other static masks. | Q48: personalised mask, cross-image, robustness | R48: No | T48: https://arxiv.org/abs/2407.13975 | U48: Search
A49: 45 | B49: xu2024caat | C49: Perturbing Attention Gives You More Bang for the Buck: Subtle Imaging Perturbations That Efficiently Fool Customized Diffusion Models | D49: Jingyao Xu, Yuetong Lu, Yandong Li, Siyang Lu, Dongdong Wang, Xiang Wei | E49: 2024 | F49: CVPR | G49: Vision | H49: Unlearnable images & anti-customisation | I49: Adversarial & unlearnable | J49: CelebA-HQ, VGGFace2 | K49: Stable Diffusion v1.4/2.1 with DreamBooth, LoRA | L49: CAAT targets cross-attention layers, which change most during fine-tuning, so small perturbations derail customisation cheaply. | M49: Matched or beat prior anti-customisation at a fraction of the compute. | N49: Diffusion personalisation on a face. | O49: Subtle perturbations. | P49: Purification-based bypass. | Q49: anti-customisation, cross-attention, efficiency | R49: No | T49: https://arxiv.org/abs/2404.15081 | U49: Search
A50: 46 | B50: mi2024 | C50: Privacy-Preserving Face Recognition Using Trainable Feature Subtraction | D50: Yuxi Mi, Zhizhou Zhong, Yuge Huang, Jiazhen Ji, Jianqing Xu, Jun Wang, Shaoming Wang, Shouhong Ding, Shuigeng Zhou | E50: 2024 | F50: CVPR | G50: Vision | H50: Identity protection: templates & encrypted matching | I50: Template protection | J50: CASIA-WebFace, MS1M (train); LFW, CFP-FP, AgeDB, IJB-B, IJB-C | K50: Generative + recognition pair (MinusFace) | L50: MinusFace represents a face by the residue between the image and its regeneration, then shuffles it, giving a visually uninformative but recognisable representation. | M50: Strong resistance to reconstruction with accuracy near baseline. | N50: Server or eavesdropper reconstructing faces. | O50: Recognition accuracy. | P50: Empirical privacy; adaptive attacks continue. | Q50: MinusFace, feature subtraction, shuffle | R50: Yes | S50: https://github.com/Tencent/TFace | T50: https://openaccess.thecvf.com/content/CVPR2024/html/Mi_Privacy-Preserving_Face_Recognition_Using_Trainable_Feature_Subtraction_CVPR_2024_paper.html | U50: Search
A51: 47 | B51: fan2024salun | C51: SalUn: Empowering Machine Unlearning via Gradient-Based Weight Saliency in Both Image Classification and Generation | D51: Chongyu Fan, Jiancheng Liu, Yihua Zhang, Eric Wong, Dennis Wei, Sijia Liu | E51: 2024 | F51: ICLR (spotlight) | G51: ML | H51: Machine unlearning & auditing | I51: Training data & unlearning | J51: CIFAR-10, CIFAR-100, SVHN, ImageNette, CelebA-HQ | K51: ResNet-18, VGG-16, DDPM, Stable Diffusion | L51: Computes gradient-based weight saliency to restrict unlearning updates to the weights that matter, then applies random labelling. | M51: Near-retrain forgetting on classifiers and the first effective unlearning for conditional diffusion, including identity removal on CelebA-HQ. | N51: Deletion of identities or concepts from discriminative and generative models. | O51: Retained accuracy and generation quality. | P51: Approximate; hyperparameter sensitive. | Q51: weight saliency, classification and generation, faces | R51: Yes | S51: https://github.com/OPTML-Group/Unlearn-Saliency | T51: https://arxiv.org/abs/2310.12508 | U51: Search
A52: 48 | B52: wang2024simac | C52: SimAC: A Simple Anti-Customization Method for Protecting Face Privacy against Text-to-Image Synthesis of Diffusion Models | D52: Feifei Wang, Zhentao Tan, Tianyi Wei, Yue Wu, Qidong Huang | E52: 2024 | F52: CVPR | G52: Vision | H52: Unlearnable images & anti-customisation | I52: Adversarial & unlearnable | J52: CelebA-HQ, VGGFace2 | K52: Stable Diffusion with DreamBooth | L52: Adaptive greedy timestep selection plus feature-interference loss at intermediate layers, a simpler and stronger anti-customisation objective. | M52: Improved identity disruption over Anti-DreamBooth with less computation. | N52: DreamBooth-style personalisation of a face. | O52: Small perturbations. | P52: Purification remains effective against it. | Q52: anti-customisation, timestep selection, feature interference | R52: Yes | S52: https://github.com/somuchtome/SimAC | T52: https://arxiv.org/abs/2312.07865 | U52: Search
A53: 49 | B53: dolatabadi2024 | C53: The Devil's Advocate: Shattering the Illusion of Unexploitable Data using Diffusion Models | D53: Hadi M. Dolatabadi, Sarah Erfani, Christopher Leckie | E53: 2024 | F53: IEEE SaTML | G53: Security | H53: Attacks & evaluations | I53: Attacks & evaluations | J53: CIFAR-10, CIFAR-100, ImageNet subset | K53: DDPM purification | L53: Uses diffusion models to purify protective perturbations from training data before learning. | M53: Removed availability-poisoning protections, making 'unexploitable' data exploitable again; the same purification idea threatens cloaks. | N53: Attacker training on protected data. | O53: Not applicable. | P53: Purification can also degrade fine details. | Q53: diffusion purification, unlearnable data, poisoning | R53: No | T53: https://arxiv.org/abs/2303.08500 | U53: Search
A54: 50 | B54: shahreza2024 | C54: Vulnerability of State-of-the-Art Face Recognition Models to Template Inversion Attack | D54: Hatef Otroshi Shahreza, Vedrana Krivokuća Hahn, Sébastien Marcel | E54: 2024 | F54: IEEE TIFS | G54: Journal | H54: Attacks & evaluations | I54: Attacks & evaluations | J54: FFHQ, MOBIO, LFW, AgeDB | K54: Many state-of-the-art recognisers | L54: Benchmarks inversion attacks across many modern recognisers and both white-box and black-box settings. | M54: Every tested state-of-the-art model was vulnerable; concluded templates must be protected, not merely kept secret. | N54: Attacker with templates. | O54: Not applicable. | P54: Academic models; commercial systems inferred. | Q54: template inversion, benchmark | R54: No | T54: https://doi.org/10.1109/TIFS.2024.3381820 | U54: Search
A55: 51 | B55: rigaki2023 | C55: A Survey of Privacy Attacks in Machine Learning | D55: Maria Rigaki, Sebastian Garcia | E55: 2023 | F55: ACM Computing Surveys | G55: Journal | H55: Surveys, audits & society | I55: Surveys & society | J55: Survey | K55: Survey | L55: Taxonomy of privacy attacks on models: membership inference, reconstruction, property inference and model extraction, with defenses. | M55: Places face template inversion and membership inference in the general attack landscape. | N55: Not applicable. | O55: Not applicable. | P55: General ML rather than face-specific. | Q55: survey, membership inference, model inversion | R55: No | T55: https://arxiv.org/abs/2007.07646 | U55: Search
A56: 52 | B56: kumari2023 | C56: Ablating Concepts in Text-to-Image Diffusion Models | D56: Nupur Kumari, Bingliang Zhang, Sheng-Yu Wang, Eli Shechtman, Richard Zhang, Jun-Yan Zhu | E56: 2023 | F56: ICCV | G56: Vision | H56: Machine unlearning & auditing | I56: Training data & unlearning | J56: Custom concept prompt sets | K56: Stable Diffusion v1.4 | L56: Maps a target concept's distribution onto an anchor concept so the model generates the anchor when asked for the target. | M56: Ablated specific instances, styles and memorised images in minutes with little collateral damage. | N56: Generative models reproducing specific people or works. | O56: Related concepts preserved. | P56: Anchor choice matters; adversarial recovery possible. | Q56: concept ablation, diffusion, copyright | R56: Yes | S56: https://github.com/nupurkmr9/concept-ablation | T56: https://arxiv.org/abs/2303.13516 | U56: Search
A57: 53 | B57: liang2023 | C57: Adversarial Example Does Good: Preventing Painting Imitation from Diffusion Models via Adversarial Examples | D57: Chumeng Liang, Xiaoyu Wu, Yang Hua, Jiaru Zhang, Yiming Xue, Tao Song, Zhengui Xue, Ruhui Ma, Haibing Guan | E57: 2023 | F57: ICML | G57: ML | H57: Unlearnable images & anti-customisation | I57: Adversarial & unlearnable | J57: WikiArt, LSUN, own artwork | K57: Stable Diffusion v1.4/1.5 | L57: AdvDM: adversarial examples for latent diffusion models via Monte Carlo estimation of the diffusion loss gradient; basis of the Mist tool. | M57: Textual-inversion and DreamBooth mimicry of protected artworks degraded sharply. | N57: Style and subject mimicry by fine-tuned diffusion models. | O57: Perturbations visible at strong settings. | P57: Broken by GrIDPure and by Hönig et al.'s robust mimicry pipelines. | Q57: AdvDM, Mist, artwork, diffusion | R57: Yes | S57: https://github.com/mist-project/mist | T57: https://arxiv.org/abs/2302.04578 | U57: Search
A58: 54 | B58: vanle2023 | C58: Anti-DreamBooth: Protecting Users from Personalized Text-to-Image Synthesis | D58: Thanh Van Le, Hao Phung, Thuan Hoang Nguyen, Quan Dao, Ngoc N. Tran, Anh Tran | E58: 2023 | F58: ICCV | G58: Vision | H58: Unlearnable images & anti-customisation | I58: Adversarial & unlearnable | J58: CelebA-HQ, VGGFace2 | K58: Stable Diffusion v1.4, v1.5, v2.1 with DreamBooth | L58: ASPL: alternating surrogate and perturbation learning produces noise that makes DreamBooth fine-tuning on a person's photos yield distorted, unusable faces. | M58: Personalised models trained on protected photos produced low-quality faces across Stable Diffusion versions and prompts; introduced FDFR and ISM metrics. | N58: Deepfake personalisation of a user's face from a few photos. | O58: Photos usable by people; visible noise at high budgets. | P58: GrIDPure and other purification remove the protection; robustness to JPEG and resizing limited (MetaCloak addresses). | Q58: anti-customisation, DreamBooth, faces | R58: Yes | S58: https://github.com/VinAIResearch/Anti-DreamBooth | T58: https://arxiv.org/abs/2303.15433 | U58: Search
A59: 55 | B59: barattin2023 | C59: Attribute-Preserving Face Dataset Anonymization via Latent Code Optimization | D59: Simone Barattin, Christos Tzelepis, Ioannis Patras, Nicu Sebe | E59: 2023 | F59: CVPR | G59: Vision | H59: De-identification (generative) | I59: Generative de-identification | J59: CelebA-HQ, LFW | K59: StyleGAN2, FaRL features; ArcFace for evaluation | L59: Optimises each image's latent code in a pretrained GAN with an identity-distance loss and a feature-matching loss in FaRL space to keep facial attributes. | M59: Anonymised whole datasets while preserving attributes better than prior work, enabling training on anonymised data. | N59: Re-identification of people in released datasets. | O59: Facial attributes for downstream training. | P59: Slow per-image optimisation; dependent on GAN inversion. | Q59: FALCO, StyleGAN, dataset anonymization | R59: Yes | S59: https://github.com/chi0tzp/FALCO | T59: https://arxiv.org/abs/2303.11296 | U59: Search
A60: 56 | B60: hahn2023 | C60: Biometric Template Protection for Neural-Network-Based Face Recognition Systems: A Survey of Methods and Evaluation Techniques | D60: Vedrana Krivokuća Hahn, Sébastien Marcel | E60: 2023 | F60: IEEE TIFS | G60: Journal | H60: Identity protection: templates & encrypted matching | I60: Template protection | J60: Survey (many) | K60: Survey | L60: Survey of template protection for deep face embeddings and a critique of how recognition accuracy, irreversibility and unlinkability are evaluated. | M60: Found inconsistent threat models and evaluation across the literature and proposed a common protocol. | N60: Template compromise. | O60: Not applicable. | P60: Focused on face embeddings only. | Q60: survey, evaluation | R60: No | T60: https://arxiv.org/abs/2110.05044 | U60: Search
A61: 57 | B61: chen2023boundary | C61: Boundary Unlearning: Rapid Forgetting of Deep Networks via Shifting the Decision Boundary | D61: Min Chen, Weizhuo Gao, Gaoyang Liu, Kai Peng, Chen Wang | E61: 2023 | F61: CVPR | G61: Vision | H61: Machine unlearning & auditing | I61: Training data & unlearning | J61: CIFAR-10, VGGFace2 subset | K61: ResNet-18 | L61: Shifts or expands the decision boundary of the forgotten class rather than editing parameters globally. | M61: Removed an identity from a face recognition model on VGGFace2 with a 17× speed-up over retraining, near-retrain accuracy. | N61: Removing a person from a trained face recogniser. | O61: Retained-class accuracy. | P61: Class-level, not sample-level, unlearning. | Q61: decision boundary, class unlearning, faces | R61: No | T61: https://arxiv.org/abs/2303.11570 | U61: Search
A62: 58 | B62: shamshad2023 | C62: CLIP2Protect: Protecting Facial Privacy using Text-Guided Makeup via Adversarial Latent Search | D62: Fahad Shamshad, Muzammal Naseer, Karthik Nandakumar | E62: 2023 | F62: CVPR | G62: Vision | H62: Adversarial privacy | I62: Adversarial & unlearnable | J62: CelebA-HQ, LADN | K62: StyleGAN2, CLIP; IR152, IRSE50, FaceNet, MobileFace | L62: Searches adversarial codes in a generative model's latent space, guided by a text makeup prompt and an identity-preserving regulariser. | M62: Absolute gain of 12.06% in black-box transferability over prior facial privacy methods on verification. | N62: Black-box recognisers. | O62: Text-controllable natural makeup. | P62: Per-image optimisation cost; relies on GAN inversion. | Q62: CLIP, latent search, makeup | R62: Yes | S62: https://github.com/fahadshamshad/Clip2Protect | T62: https://arxiv.org/abs/2306.10008 | U62: Search
A63: 59 | B63: sadasivan2023 | C63: CUDA: Convolution-based Unlearnable Datasets | D63: Vinu Sankar Sadasivan, Mahdi Soltanolkotabi, Soheil Feizi | E63: 2023 | F63: CVPR | G63: Vision | H63: Unlearnable images & anti-customisation | I63: Adversarial & unlearnable | J63: CIFAR-10, CIFAR-100, ImageNet-100 | K63: ResNet-18, VGG, DenseNet, ViT | L63: Applies class-wise randomly generated blur filters, a model-free convolutional shortcut. | M63: Fast to generate, and more robust than additive noise to adversarial training and to some augmentations. | N63: Unauthorised training. | O63: Slight blur visible. | P63: Filters can be estimated and inverted. | Q63: unlearnable datasets, convolution, class-wise filters | R63: Yes | S63: https://github.com/vinusankars/Convolution-based-Unlearnability | T63: https://arxiv.org/abs/2303.04278 | U63: Search
A64: 60 | B64: chundawat2023a | C64: Can Bad Teaching Induce Forgetting? Unlearning in Deep Networks Using an Incompetent Teacher | D64: Vikram S. Chundawat, Ayush K. Tarun, Murari Mandal, Mohan Kankanhalli | E64: 2023 | F64: AAAI | G64: ML | H64: Machine unlearning & auditing | I64: Training data & unlearning | J64: CIFAR-10, CIFAR-100, MNIST | K64: ResNet-18, AllCNN | L64: Distils the forget set toward a randomly initialised incompetent teacher and the retain set toward the original model. | M64: Fast approximate unlearning with a new ZRF metric for how much a model still knows. | N64: Deletion requests. | O64: Retain-set accuracy. | P64: Approximate; no formal guarantee. | Q64: teacher-student, approximate unlearning | R64: Yes | S64: https://github.com/vikram2000b/bad-teaching-unlearning | T64: https://arxiv.org/abs/2205.08096 | U64: Search
A65: 61 | B65: shahreza2023tpami | C65: Comprehensive Vulnerability Evaluation of Face Recognition Systems to Template Inversion Attacks via 3D Face Reconstruction | D65: Hatef Otroshi Shahreza, Sébastien Marcel | E65: 2023 | F65: IEEE TPAMI | G65: Journal | H65: Attacks & evaluations | I65: Attacks & evaluations | J65: MOBIO, LFW, AgeDB, FFHQ | K65: ArcFace, ElasticFace and other recognisers | L65: Reconstructs 3D faces from templates and uses them for digital and physical presentation attacks. | M65: Reconstructed faces passed several state-of-the-art recognisers and transferred across systems. | N65: Attacker with leaked templates. | O65: Not applicable. | P65: Evaluation on academic systems. | Q65: template inversion, 3D, presentation attack | R65: No | T65: https://doi.org/10.1109/TPAMI.2023.3312123 | U65: Search
A66: 62 | B66: kim2023 | C66: DCFace: Synthetic Face Generation with Dual Condition Diffusion Model | D66: Minchul Kim, Feng Liu, Anil K. Jain, Xiaoming Liu | E66: 2023 | F66: CVPR | G66: Vision | H66: Training-data privacy & synthetic data | I66: Training data & unlearning | J66: CASIA-WebFace (train); DCFace 0.5M/1.2M; LFW, CFP-FP, CPLFW, AgeDB, CALFW | K66: Dual-condition DDPM; IR-50/IR-101 AdaFace | L66: Diffusion model conditioned on an identity image and a style image to generate many consistent images per synthetic subject. | M66: Set the 2023 state of the art for synthetic-trained recognition and controlled intra-class variation explicitly. | N66: Training on real scraped faces. | O66: Recognition accuracy. | P66: Identity generator seeded from real images. | Q66: synthetic data, diffusion, dual condition | R66: Yes | S66: https://github.com/mk-minchul/dcface | T66: https://arxiv.org/abs/2304.07060 | U66: Search
A67: 63 | B67: hukkelas2023 | C67: DeepPrivacy2: Towards Realistic Full-Body Anonymization | D67: Håkon Hukkelås, Frank Lindseth | E67: 2023 | F67: WACV | G67: Vision | H67: De-identification (generative) | I67: Generative de-identification | J67: FDF256, FDH (Flickr Diverse Humans) | K67: Style-based GAN with surface guidance | L67: Detects faces and bodies and generates full-body replacements with a style-based GAN conditioned on surface and keypoint maps. | M67: Extended anonymisation from faces to bodies at higher resolution; released as a usable toolkit. | N67: Recognition by face or body in datasets and footage. | O67: Pose, scene; suitable for training data. | P67: Generated bodies can be inconsistent across frames; heavy compute. | Q67: full body, GAN, high resolution | R67: Yes | S67: https://github.com/hukkelas/deep_privacy2 | T67: https://arxiv.org/abs/2211.09454 | U67: Search
A68: 64 | B68: dockhorn2023 | C68: Differentially Private Diffusion Models | D68: Tim Dockhorn, Tianshi Cao, Arash Vahdat, Karsten Kreis | E68: 2023 | F68: TMLR | G68: Journal | H68: Differential privacy | I68: Obfuscation & differential privacy | J68: MNIST, Fashion-MNIST, CelebA (32×32) | K68: Diffusion (DDPM-style) | L68: Trains diffusion models with DP-SGD and noise multiplicity to reduce gradient variance. | M68: State-of-the-art DP image synthesis including 32×32 CelebA faces; DP-trained synthetic data trained useful downstream classifiers. | N68: Training-sample leakage from generative models. | O68: Synthetic data utility. | P68: Low resolution; large compute. | Q68: DP diffusion, synthetic faces | R68: Yes | S68: https://github.com/nv-tlabs/DP-Diffusion | T68: https://arxiv.org/abs/2210.09929 | U68: Search
A69: 65 | B69: ghalebikesabi2023 | C69: Differentially Private Diffusion Models Generate Useful Synthetic Images | D69: Sahra Ghalebikesabi, Leonard Berrada, Sven Gowal, Ira Ktena, Robert Stanforth, Jamie Hayes, Soham De, Samuel L. Smith, Olivia Wiles, Borja Balle | E69: 2023 | F69: arXiv preprint | G69: Preprint | H69: Differential privacy | I69: Obfuscation & differential privacy | J69: CIFAR-10, Camelyon17 | K69: Diffusion models | L69: Fine-tunes ImageNet-pretrained diffusion models with DP-SGD to generate synthetic training sets. | M69: Classifiers trained on DP synthetic data approached the accuracy of DP training on real data at epsilon 10. | N69: Training-sample leakage. | O69: Downstream classifier accuracy. | P69: Relies on public pretraining data. | Q69: DP diffusion, pretraining, utility | R69: No | T69: https://arxiv.org/abs/2302.13861 | U69: Search
A70: 66 | B70: bae2023 | C70: DigiFace-1M: 1 Million Digital Face Images for Face Recognition | D70: Gwangbin Bae, Martin de La Gorce, Tadas Baltrušaitis, Charlie Hewitt, Dong Chen, Julien Valentin, Roberto Cipolla, Jingjing Shen | E70: 2023 | F70: WACV | G70: Vision | H70: Training-data privacy & synthetic data | I70: Training data & unlearning | J70: DigiFace-1M (released); LFW, CFP-FP, AgeDB, CALFW, CPLFW | K70: Rendered 3D faces; ResNet-50 | L70: Renders 1.22 million images of 110,000 synthetic identities from a 3D face model built with consented scans. | M70: Recognisers trained on rendered faces approached real-data accuracy with no scraped identities at all. | N70: Consent and copyright issues of scraped datasets. | O70: Recognition accuracy (gap to real data remains). | P70: Domain gap of rendered faces; expensive pipeline. | Q70: synthetic data, 3D rendering, consent | R70: Yes | S70: https://github.com/microsoft/DigiFace1M | T70: https://arxiv.org/abs/2210.02579 | U70: Search
A71: 67 | B71: wen2023 | C71: Divide and Conquer: a Two-Step Method for High Quality Face De-Identification with Model Explainability | D71: Yunqian Wen, Bo Liu, Jingyi Cao, Rong Xie, Li Song | E71: 2023 | F71: ICCV | G71: Vision | H71: De-identification (generative) | I71: Generative de-identification | J71: CelebA-HQ, FFHQ | K71: EG3D/NeRF generator, StyleGAN refinement; ArcFace | L71: IDeudemon: first protects identity in a 3D-aware (NeRF-based) generator's identity code, then restores utility with a GAN refinement, with explainable identity steps. | M71: High-quality de-identification with controllable identity distance and pose consistency. | N71: Automated recognition on shared images. | O71: Pose, expression, background. | P71: Heavy two-stage pipeline. | Q71: IDeudemon, NeRF, explainability | R71: No | T71: https://openaccess.thecvf.com/content/ICCV2023/html/Wen_Divide_and_Conquer_a_Two-Step_Method_for_High_Quality_Face_ICCV_2023_paper.html | U71: Search
A72: 68 | B72: hukkelas2023eval | C72: Does Image Anonymization Impact Computer Vision Training? | D72: Håkon Hukkelås, Frank Lindseth | E72: 2023 | F72: CVPR Workshops | G72: Vision | H72: Attacks & evaluations | I72: Attacks & evaluations | J72: COCO, Cityscapes, BDD100K | K72: Mask R-CNN and other detectors/segmenters | L72: Trains detection, segmentation and pose models on datasets anonymised by blur, mask and realistic generation, and measures the drop. | M72: Traditional anonymisation degraded training noticeably; realistic generative anonymisation reduced but did not eliminate the gap. | N72: Not a threat paper: measures utility cost. | O72: Quantified per task. | P72: Face and body only; a few datasets. | Q72: evaluation, utility, training data | R72: Yes | S72: https://github.com/hukkelas/deep_privacy2 | T72: https://arxiv.org/abs/2306.05135 | U72: Search
A73: 69 | B73: gandikota2023 | C73: Erasing Concepts from Diffusion Models | D73: Rohit Gandikota, Joanna Materzyńska, Jaden Fiotto-Kaufman, David Bau | E73: 2023 | F73: ICCV | G73: Vision | H73: Machine unlearning & auditing | I73: Training data & unlearning | J73: COCO prompts, artist styles, I2P | K73: Stable Diffusion v1.4 | L73: ESD fine-tunes a diffusion model with negative guidance from its own knowledge to erase a concept, style or identity without retraining. | M73: Erased artistic styles, objects and nudity while leaving other generation intact; used for removing people from models. | N73: A generative model that can render a real person on request. | O73: Other concepts preserved. | P73: Erased concepts can sometimes be recovered with adversarial prompts. | Q73: concept erasure, diffusion, ESD | R73: Yes | S73: https://github.com/rohitgandikota/erasing | T73: https://arxiv.org/abs/2303.07345 | U73: Search
A74: 70 | B74: chen2023auditor | C74: FACE-AUDITOR: Data Auditing in Facial Recognition Systems | D74: Min Chen, Zhikun Zhang, Tianhao Wang, Michael Backes, Yang Zhang | E74: 2023 | F74: USENIX Security | G74: Security | H74: Machine unlearning & auditing | I74: Training data & unlearning | J74: UMDFaces, WebFace, VGGFace2, CelebA | K74: SiameseNet, ProtoNet, RelationNet | L74: Lets a user test whether their face images were used to train a few-shot face recognition system, using auxiliary information and probing. | M74: High auditing accuracy across few-shot recognisers; a tool for enforcing deletion and consent. | N74: Unauthorised use of a person's photos to train recognisers. | O74: Not applicable. | P74: Targets few-shot systems; adaptive training can evade. | Q74: auditing, membership inference, few-shot FR | R74: Yes | S74: https://github.com/MinChen00/Face-Auditor | T74: https://arxiv.org/abs/2304.02782 | U74: Search
A75: 71 | B75: rosberg2023 | C75: FIVA: Facial Image and Video Anonymization and Anonymization Defense | D75: Felix Rosberg, Eren Erdal Aksoy, Cristofer Englund, Fernando Alonso-Fernandez | E75: 2023 | F75: ICCV Workshops | G75: Vision | H75: De-identification (generative) | I75: Generative de-identification | J75: CelebA-HQ, VoxCeleb | K75: StyleGAN-based swapping; ArcFace | L75: Face-swap based anonymiser with temporal consistency and a defense that stops the anonymised face from being re-anonymised or reverted. | M75: Consistent video anonymisation and protection against re-swapping. | N75: Recognition in video and re-identification attacks on anonymised output. | O75: Expression, pose, video quality. | P75: Workshop-scale evaluation. | Q75: video, anonymisation defense, face swapping | R75: No | T75: https://arxiv.org/abs/2309.04228 | U75: Search
A76: 72 | B76: shahreza2023neurips | C76: Face Reconstruction from Facial Templates by Learning Latent Space of a Generator Network | D76: Hatef Otroshi Shahreza, Sébastien Marcel | E76: 2023 | F76: NeurIPS | G76: ML | H76: Attacks & evaluations | I76: Attacks & evaluations | J76: FFHQ, MOBIO, LFW, AgeDB | K76: StyleGAN3 generator; ArcFace, ElasticFace, AdaFace | L76: Learns a mapping from templates to the intermediate latent space of a pretrained face generator to produce high-resolution reconstructions. | M76: Realistic reconstructions in white-box and black-box settings that also impersonated the subject against other recognisers. | N76: Attacker with leaked templates. | O76: Not applicable. | P76: Generator domain limits pose and age range. | Q76: template inversion, StyleGAN, white-box, black-box | R76: No | T76: https://proceedings.neurips.cc/paper_files/paper/2023/hash/29e4b51d45dc8f534260adc45b587363-Abstract-Conference.html | U76: Search
A77: 73 | B77: shan2023glaze | C77: Glaze: Protecting Artists from Style Mimicry by Text-to-Image Models | D77: Shawn Shan, Jenna Cryan, Emily Wenger, Haitao Zheng, Rana Hanocka, Ben Y. Zhao | E77: 2023 | F77: USENIX Security | G77: Security | H77: Unlearnable images & anti-customisation | I77: Adversarial & unlearnable | J77: Artists' portfolios; WikiArt | K77: Stable Diffusion, DreamBooth | L77: Style cloaks: perturb artwork toward a target style in feature space so fine-tuned models learn the wrong style. From the Fawkes team. | M77: Artists in a user study rated mimicry of cloaked work as failed in over 90% of cases; deployed as a desktop app with over a million downloads. | N77: Style mimicry by fine-tuned text-to-image models. | O77: Small visible changes on some art. | P77: Hönig et al. (2024) showed simple robust mimicry bypasses it; the arms race from Fawkes repeats. | Q77: style cloak, artists, diffusion | R77: No | T77: https://arxiv.org/abs/2302.04222 | U77: Search
A78: 74 | B78: boutros2023idiff | C78: IDiff-Face: Synthetic-based Face Recognition through Fuzzy Identity-Conditioned Diffusion Models | D78: Fadi Boutros, Jonas Henry Grebe, Arjan Kuijper, Naser Damer | E78: 2023 | F78: ICCV | G78: Vision | H78: Training-data privacy & synthetic data | I78: Training data & unlearning | J78: FFHQ (train); LFW, AgeDB, CFP-FP, CALFW, CPLFW | K78: Latent diffusion; ResNet-50 | L78: Latent diffusion conditioned on identity embeddings with contextual partial dropout for intra-class diversity. | M78: Strong synthetic-only recognition with tunable diversity. | N78: Training on real faces. | O78: Recognition accuracy. | P78: Same generator-leakage caveat. | Q78: synthetic data, diffusion, fuzzy identity | R78: Yes | S78: https://github.com/fdbtrs/IDiff-Face | T78: https://arxiv.org/abs/2308.04995 | U78: Search
A79: 75 | B79: cao2023impress | C79: IMPRESS: Evaluating the Resilience of Imperceptible Perturbations Against Unauthorized Data Usage in Diffusion-Based Generative AI | D79: Bochuan Cao, Changjiang Li, Ting Wang, Jinyuan Jia, Bo Li, Jinghui Chen | E79: 2023 | F79: NeurIPS | G79: ML | H79: Attacks & evaluations | I79: Attacks & evaluations | J79: WikiArt, CelebA-HQ | K79: Stable Diffusion; Glaze, PhotoGuard | L79: Purifies protected images by enforcing consistency between an image and its diffusion reconstruction, removing imperceptible protective perturbations. | M79: Substantially weakened Glaze and PhotoGuard protections on art and faces. | N79: Images protected against diffusion misuse. | O79: Not applicable. | P79: Some visible quality loss after purification. | Q79: purification, Glaze, PhotoGuard, consistency | R79: No | T79: https://arxiv.org/abs/2310.19248 | U79: Search
A80: 76 | B80: liu2023iss | C80: Image Shortcut Squeezing: Countering Perturbative Availability Poisons with Compression | D80: Zhuoran Liu, Zhengyu Zhao, Martha Larson | E80: 2023 | F80: ICML | G80: ML | H80: Attacks & evaluations | I80: Attacks & evaluations | J80: CIFAR-10, CIFAR-100, ImageNet subset | K80: ResNet-18 with compression preprocessing | L80: Applies simple compression (JPEG, grayscale, bit-depth reduction) before training to squeeze out perturbative availability poisons. | M80: Restored accuracy against twelve poisoning methods, in several cases to within a few points of clean training. | N80: Data protected by unlearnable-example noise. | O80: Not applicable. | P80: Some robust poisons resist; compression costs a little accuracy. | Q80: unlearnable examples, compression, JPEG | R80: Yes | S80: https://github.com/liuzrcc/ImageShortcutSqueezing | T80: https://arxiv.org/abs/2301.13838 | U80: Search
A81: 77 | B81: klemp2023 | C81: LDFA: Latent Diffusion Face Anonymization for Self-Driving Applications | D81: Marvin Klemp, Kevin Rösch, Royden Wagner, Jannik Quehl, Martin Lauer | E81: 2023 | F81: CVPR Workshops | G81: Vision | H81: De-identification (generative) | I81: Generative de-identification | J81: Cityscapes | K81: Latent diffusion inpainting | L81: Inpaints detected faces in driving-scene images with a latent diffusion model. | M81: Anonymised training data with a smaller drop in downstream segmentation than blur or mask baselines. | N81: Re-identification of pedestrians in driving datasets. | O81: Segmentation and detection training. | P81: Small faces; diffusion cost per image. | Q81: diffusion, inpainting, autonomous driving | R81: No | T81: https://arxiv.org/abs/2302.08931 | U81: Search
A82: 78 | B82: melzi2023 | C82: Multi-IVE: Privacy Enhancement of Multiple Soft-Biometrics in Face Embeddings | D82: Pietro Melzi, Christian Rathgeb, Ruben Tolosana, Ruben Vera-Rodriguez, Aythami Morales, Dominik Lawatsch, Florian Domin, Maxim Schaub | E82: 2023 | F82: WACV Workshops | G82: Vision | H82: Soft-biometric privacy | I82: Soft-biometric privacy | J82: MAAD-Face, LFW | K82: ArcFace embeddings | L82: Extends incremental variable elimination to suppress several attributes at once from deep embeddings. | M82: Joint suppression of gender, age and ethnicity information with limited recognition loss. | N82: Attribute inference from stored embeddings. | O82: Recognition. | P82: Linear elimination; residual leakage. | Q82: IVE, multiple attributes, embeddings | R82: No | T82: https://arxiv.org/abs/2301.02516 | U82: Search
A83: 79 | B83: ciftci2023 | C83: My Face My Choice: Privacy Enhancing Deepfakes for Social Media Anonymization | D83: Umur Aybars Ciftci, Gokturk Yuksek, Ilke Demir | E83: 2023 | F83: WACV | G83: Vision | H83: De-identification (generative) | I83: Generative de-identification | J83: CelebA-HQ, LFW | K83: Face-swap generator; ArcFace and commercial APIs for evaluation | L83: Uses face swapping to replace non-consenting faces in shared photos with dissimilar synthetic identities, governed by user access permissions. | M83: Recognition accuracy on swapped faces dropped to near zero for the tested systems while photos stayed natural. | N83: Recognition of bystanders and friends in uploaded photos. | O83: Photo realism and social utility. | P83: Deepfake quality varies with pose; platform integration hypothetical. | Q83: deepfake, social media, access control | R83: No | T83: https://arxiv.org/abs/2211.01361 | U83: Search
A84: 80 | B84: wu2023ops | C84: One-Pixel Shortcut: On the Learning Preference of Deep Neural Networks | D84: Shutong Wu, Sizhe Chen, Cihang Xie, Xiaolin Huang | E84: 2023 | F84: ICLR (spotlight) | G84: ML | H84: Unlearnable images & anti-customisation | I84: Adversarial & unlearnable | J84: CIFAR-10, CIFAR-100, ImageNet subset | K84: ResNet-18, ViT | L84: Perturbs a single pixel per class to a fixed value, exploiting networks' preference for easy features. | M84: One pixel per image made CIFAR-10 unlearnable, and the shortcut survived adversarial training better than dense noise. | N84: Unauthorised training. | O84: Nearly invisible change. | P84: Detectable and removable by simple filters once known. | Q84: shortcut, one pixel, availability poisoning | R84: Yes | S84: https://github.com/cychomatica/One-Pixel-Shotcut | T84: https://arxiv.org/abs/2205.12141 | U84: Search
A85: 81 | B85: mi2023 | C85: Privacy-Preserving Face Recognition Using Random Frequency Components | D85: Yuxi Mi, Yuge Huang, Jiazhen Ji, Minyi Zhao, Jiaxiang Wu, Xingkun Xu, Shouhong Ding, Shuigeng Zhou | E85: 2023 | F85: ICCV | G85: Vision | H85: Identity protection: templates & encrypted matching | I85: Template protection | J85: CASIA-WebFace, MS1M (train); LFW, CFP-FP, AgeDB, IJB-B, IJB-C | K85: ResNet on random DCT components | L85: Prunes human-perceivable low frequencies and trains and infers on randomly selected high-frequency components so no fixed subset can be inverted. | M85: Maintained accuracy while making reconstruction from transmitted data markedly harder than fixed-channel schemes. | N85: Server reconstructing the query face. | O85: Recognition accuracy. | P85: Later distillation-based attacks (FaceLinkGen 2026) report identity leakage from such systems. | Q85: PartialFace, random frequencies, reconstruction resistance | R85: Yes | S85: https://github.com/Tencent/TFace | T85: https://arxiv.org/abs/2308.10461 | U85: Search
A86: 82 | B86: salman2023 | C86: Raising the Cost of Malicious AI-Powered Image Editing | D86: Hadi Salman, Alaa Khaddaj, Guillaume Leclerc, Andrew Ilyas, Aleksander Madry | E86: 2023 | F86: ICML | G86: ML | H86: Unlearnable images & anti-customisation | I86: Adversarial & unlearnable | J86: ImageNet and own photo sets | K86: Stable Diffusion v1.5 (latent encoder) | L86: PhotoGuard immunises a photo with an encoder attack or a full diffusion attack so that latent-diffusion editing of the image fails. | M86: Edited outputs of immunised images became grey or incoherent; argued for platform-level immunisation. | N86: Malicious editing of a person's photo with diffusion models. | O86: Imperceptible change. | P86: Circumvented by resizing, noise or purification; diffusion attack is expensive. | Q86: PhotoGuard, immunisation, diffusion editing | R86: Yes | S86: https://github.com/MadryLab/photoguard | T86: https://arxiv.org/abs/2302.06588 | U86: Search
A87: 83 | B87: li2023riddle | C87: RiDDLE: Reversible and Diversified De-identification with Latent Encryptor | D87: Dongze Li, Wei Wang, Kang Zhao, Jing Dong, Tieniu Tan | E87: 2023 | F87: CVPR | G87: Vision | H87: De-identification (generative) | I87: Generative de-identification | J87: CelebA-HQ, FFHQ | K87: StyleGAN2 + latent encryptor; ArcFace for evaluation | L87: A lightweight encryptor acting in StyleGAN2 latent space: passwords drive diverse anonymisations; only the right password decrypts, a wrong one gives another anonymous face. | M87: Diverse, high-quality de-identified faces with exact recovery; encryption and decryption share one efficient network. | N87: Unauthorised recognition of stored images. | O87: Attributes, pose; recovery for key holder. | P87: Relies on GAN inversion fidelity; security is empirical. | Q87: StyleGAN2, reversible, password | R87: Yes | S87: https://github.com/DongzeLi-CASIA/RiDDLE | T87: https://arxiv.org/abs/2303.05171 | U87: Search
A88: 84 | B88: heng2023 | C88: Selective Amnesia: A Continual Learning Approach to Forgetting in Deep Generative Models | D88: Alvin Heng, Harold Soh | E88: 2023 | F88: NeurIPS | G88: ML | H88: Machine unlearning & auditing | I88: Training data & unlearning | J88: MNIST, CIFAR-10, STL-10, CelebA; SD prompts | K88: VAE, DDPM, Stable Diffusion v1.4 | L88: Combines elastic weight consolidation and generative replay so a generative model forgets a class or a person while keeping the rest. | M88: Forgot celebrity identities in Stable Diffusion and classes in VAEs and DDPMs. | N88: Generative models that reproduce a specific person. | O88: Other generation quality. | P88: Requires access to model weights and a surrogate for the forgotten distribution. | Q88: generative unlearning, continual learning, celebrity identity | R88: Yes | S88: https://github.com/clear-nus/selective-amnesia | T88: https://arxiv.org/abs/2305.10120 | U88: Search
A89: 85 | B89: wenger2023 | C89: SoK: Anti-Facial Recognition Technology | D89: Emily Wenger, Shawn Shan, Haitao Zheng, Ben Y. Zhao | E89: 2023 | F89: IEEE Symposium on Security and Privacy | G89: Security | H89: Surveys, audits & society | I89: Surveys & society | J89: Survey | K89: Survey | L89: Systematises anti-facial recognition tools by which stage of the recognition pipeline they target: data collection, processing, training, or matching. | M89: Most tools target a single stage and are brittle to changes elsewhere; the authors, who built Fawkes, catalogue usability and durability problems frankly. | N89: Not applicable. | O89: Not applicable. | P89: Security-community perspective; less on template protection. | Q89: systematisation, anti-facial recognition, pipeline | R89: No | T89: https://arxiv.org/abs/2112.04558 | U89: Search
A90: 86 | B90: boutros2023survey | C90: Synthetic Data for Face Recognition: Current State and Future Prospects | D90: Fadi Boutros, Vitomir Štruc, Julian Fierrez, Naser Damer | E90: 2023 | F90: Image and Vision Computing | G90: Journal | H90: Training-data privacy & synthetic data | I90: Training data & unlearning | J90: Survey (many) | K90: Survey | L90: Survey of synthetic face data for training and evaluation, covering generators, protocols and privacy claims. | M90: Set out the open questions: identity leakage from generators, diversity, and legal status of synthetic identities. | N90: Not applicable. | O90: Not applicable. | P90: Fast-moving area. | Q90: survey, synthetic data | R90: No | T90: https://arxiv.org/abs/2305.01021 | U90: Search
A91: 87 | B91: kurmanji2023 | C91: Towards Unbounded Machine Unlearning | D91: Meghdad Kurmanji, Peter Triantafillou, Jamie Hayes, Eleni Triantafillou | E91: 2023 | F91: NeurIPS | G91: ML | H91: Machine unlearning & auditing | I91: Training data & unlearning | J91: CIFAR-10, Lacuna-10 (VGGFace2 faces) | K91: ResNet-18, All-CNN | L91: SCRUB: a student unlearns by moving away from the teacher on the forget set while staying close on the retain set, with a rewinding step for privacy-motivated deletion. | M91: Strong across removing bias, resolving confusion and user privacy, measured with membership inference on face data. | N91: Deletion requests with different goals. | O91: Retained accuracy. | P91: Heuristic; evaluation via MIA proxies. | Q91: SCRUB, teacher-student, evaluation | R91: Yes | S91: https://github.com/meghdadk/SCRUB | T91: https://arxiv.org/abs/2302.09880 | U91: Search
A92: 88 | B92: ren2023tue | C92: Transferable Unlearnable Examples | D92: Jie Ren, Han Xu, Yuxuan Wan, Xingjun Ma, Lichao Sun, Jiliang Tang | E92: 2023 | F92: ICLR | G92: ML | H92: Unlearnable images & anti-customisation | I92: Adversarial & unlearnable | J92: CIFAR-10, CIFAR-100, ImageNet subset | K92: ResNet-18, VGG | L92: Class-wise separability discriminant that makes unlearnable noise transfer across training settings and datasets. | M92: Protection held when the protected data was mixed with other data or used in different training pipelines. | N92: Unauthorised training under unknown settings. | O92: Small perturbations. | P92: Still a perturbation-based shortcut, vulnerable to squeezing. | Q92: unlearnable examples, transferability, class-wise separability | R92: No | T92: https://arxiv.org/abs/2210.10114 | U92: Search
A93: 89 | B93: zhang2023uc | C93: Unlearnable Clusters: Towards Label-Agnostic Unlearnable Examples | D93: Jiaming Zhang, Xingjun Ma, Qi Yi, Jitao Sang, Yu-Gang Jiang, Yaowei Wang, Changsheng Xu | E93: 2023 | F93: CVPR | G93: Vision | H93: Unlearnable images & anti-customisation | I93: Adversarial & unlearnable | J93: CIFAR-10, CIFAR-100, ImageNet subset, WebFace subset | K93: ResNet-18, VGG, DenseNet | L93: Generates cluster-wise perturbations without knowing the labels the exploiter will use, targeting the uniform-noise-to-cluster mapping. | M93: Worked when the attacker's label space differed from the protector's, unlike class-wise UEs. | N93: Unauthorised training with unknown labels. | O93: Small perturbations. | P93: Same purification weaknesses. | Q93: label-agnostic, clusters, unlearnable examples | R93: Yes | S93: https://github.com/jiamingzhang94/Unlearnable-Clusters | T93: https://arxiv.org/abs/2301.01217 | U93: Search
A94: 90 | B94: hill2023 | C94: Your Face Belongs to Us: A Secretive Startup's Quest to End Privacy as We Know It | D94: Kashmir Hill | E94: 2023 | F94: Random House (book) | G94: Other | H94: Surveys, audits & society | I94: Surveys & society | J94: None | K94: None | L94: Book-length account of Clearview AI and the history of face recognition from Bledsoe to the present. | M94: The most complete public record of how a scraped face database became a police tool and how regulators responded. | N94: Mass identification. | O94: Not applicable. | P94: Journalism. | Q94: Clearview AI, history, journalism | R94: No | T94: https://www.penguinrandomhouse.com/books/705578/your-face-belongs-to-us-by-kashmir-hill/ | U94: Search
A95: 91 | B95: chundawat2023b | C95: Zero-Shot Machine Unlearning | D95: Vikram S. Chundawat, Ayush K. Tarun, Murari Mandal, Mohan Kankanhalli | E95: 2023 | F95: IEEE TIFS | G95: Journal | H95: Machine unlearning & auditing | I95: Training data & unlearning | J95: MNIST, CIFAR-10, CIFAR-100 | K95: ResNet-18, AllCNN | L95: Unlearns without access to any original training data via error-minimising noise and gated knowledge transfer. | M95: Forgetting when the training data is gone, the realistic case for deployed face models. | N95: Deletion requests after data has been deleted. | O95: Retained accuracy. | P95: Weaker forgetting than data-available methods. | Q95: zero-shot, no training data | R95: No | T95: https://arxiv.org/abs/2201.05629 | U95: Search
A96: 92 | B96: nguyen2022 | C96: A Survey of Machine Unlearning | D96: Thanh Tam Nguyen, Thanh Trung Huynh, Phi Le Nguyen, Alan Wee-Chung Liew, Hongzhi Yin, Quoc Viet Hung Nguyen | E96: 2022 | F96: arXiv preprint | G96: Preprint | H96: Machine unlearning & auditing | I96: Training data & unlearning | J96: Survey | K96: Survey | L96: Survey of unlearning definitions, exact and approximate methods, verification and datasets. | M96: The most-cited map of the field; documents the lack of standard verification. | N96: Not applicable. | O96: Not applicable. | P96: Fast-moving field. | Q96: survey, machine unlearning | R96: Yes | S96: https://github.com/tamlhp/awesome-machine-unlearning | T96: https://arxiv.org/abs/2209.02299 | U96: Search
A97: 93 | B97: zolfi2022 | C97: Adversarial Mask: Real-World Universal Adversarial Attack on Face Recognition Models | D97: Alon Zolfi, Shai Avidan, Yuval Elovici, Asaf Shabtai | E97: 2022 | F97: ECML PKDD | G97: ML | H97: Adversarial privacy | I97: Adversarial & unlearnable | J97: Own collected videos; CASIA-WebFace | K97: ArcFace, CosFace, FaceNet, MagFace | L97: A single printed fabric mask pattern that makes many wearers unrecognisable to face recognition models. | M97: Universal dodging in physical tests; transferable to unseen models. | N97: Physical recognition in masked settings. | O97: A patterned face mask. | P97: Mask-aware retraining reduces effect. | Q97: universal, fabric mask, physical | R97: Yes | S97: https://github.com/AlonZolfi/AdversarialMask | T97: https://arxiv.org/abs/2111.10759 | U97: Search
A98: 94 | B98: wei2022 | C98: Adversarial Sticker: A Stealthy Attack Method in the Physical World | D98: Xingxing Wei, Ying Guo, Jie Yu | E98: 2022 | F98: IEEE TPAMI | G98: Journal | H98: Adversarial privacy | I98: Adversarial & unlearnable | J98: LFW, CelebA | K98: FaceNet, ArcFace, CosFace | L98: Places ordinary-looking stickers (cartoons, logos) on the face and optimises only their position and rotation for dodging or impersonation. | M98: Stealthy physical attacks without odd-looking patterns, transferable across recognisers. | N98: Physical recognition systems. | O98: Looks like a decorative sticker. | P98: Success depends on sticker inventory and camera geometry. | Q98: physical, sticker, meaningful patterns | R98: Yes | S98: https://github.com/jinyugy21/Adv-Stickers_RHDE | T98: https://arxiv.org/abs/2104.06728 | U98: Search
A99: 95 | B99: osorio2022 | C99: An Attack on Facial Soft-Biometric Privacy Enhancement | D99: Dailé Osorio-Roig, Christian Rathgeb, Pawel Drozdowski, Philipp Terhörst, Vitomir Štruc, Christoph Busch | E99: 2022 | F99: IEEE TBIOM | G99: Biometrics | H99: Attacks & evaluations | I99: Attacks & evaluations | J99: LFW, CelebA | K99: ArcFace; PE-MIU, IVE and other privacy enhancers | L99: Recovers suppressed attributes from privacy-enhanced templates by comparing them with a small annotated database, exploiting that similar templates share attributes. | M99: Attribute prediction well above chance against several soft-biometric privacy methods, using only black-box access. | N99: Attacker with privacy-enhanced templates. | O99: Not applicable. | P99: Needs an annotated reference set. | Q99: soft biometrics, attribute recovery, black-box | R99: No | T99: https://arxiv.org/abs/2111.12405 | U99: Search
A100: 96 | B100: sandoval2022 | C100: Autoregressive Perturbations for Data Poisoning | D100: Pedro Sandoval-Segura, Vasu Singla, Jonas Geiping, Micah Goldblum, Tom Goldstein, David W. Jacobs | E100: 2022 | F100: NeurIPS | G100: ML | H100: Unlearnable images & anti-customisation | I100: Adversarial & unlearnable | J100: CIFAR-10, CIFAR-100, SVHN, STL-10 | K100: ResNet-18, VGG, DenseNet | L100: Generates poisoning perturbations from autoregressive processes without access to any model or the rest of the dataset. | M100: Model-free noise transferred across architectures and matched optimisation-based poisons. | N100: Unauthorised training on released data. | O100: Small perturbations. | P100: Removed by the same squeezing and purification defenses. | Q100: availability poisoning, model-free, autoregressive | R100: Yes | S100: https://github.com/psandovalsegura/autoregressive-poisoning | T100: https://arxiv.org/abs/2206.03693 | U100: Search
A101: 97 | B101: yu2022 | C101: Availability Attacks Create Shortcuts | D101: Da Yu, Huishuai Zhang, Wei Chen, Jian Yin, Tie-Yan Liu | E101: 2022 | F101: ACM KDD | G101: ML | H101: Unlearnable images & anti-customisation | I101: Adversarial & unlearnable | J101: CIFAR-10, CIFAR-100, ImageNet subset | K101: ResNet-18, VGG | L101: Explains availability poisons as learnable shortcuts and shows that simple synthetic, linearly separable noise works as well as optimised noise. | M101: Random linearly separable perturbations made data unlearnable without any model in the loop, revealing why such attacks are also easy to remove. | N101: Unauthorised training on released data. | O101: Small perturbations. | P101: Shortcuts are removed by augmentation or compression. | Q101: shortcut learning, synthetic noise, analysis | R101: Yes | S101: https://github.com/dayu11/Availability-Attacks-Create-Shortcuts | T101: https://arxiv.org/abs/2111.00898 | U101: Search
...

Sheet Summary
A1: Entries by year and family
A2: Live COUNTIFS over the "All papers" tab.
A4: Family | B4: Before 2018 | C4: 2018 | D4: 2019 | E4: 2020 | F4: 2021 | G4: 2022 | H4: 2023 | I4: 2024 | J4: 2025 | K4: 2026 | L4: Total
A5: Blur, pixelation & obfuscation | B5: =COUNTIFS('All papers'!$H$5:$H$229,$A5,'All papers'!$E$5:$E$229,"<2018") -> 13 | C5: =COUNTIFS('All papers'!$H$5:$H$229,$A5,'All papers'!$E$5:$E$229,2018) -> 2 | D5: =COUNTIFS('All papers'!$H$5:$H$229,$A5,'All papers'!$E$5:$E$229,2019) -> 0 | E5: =COUNTIFS('All papers'!$H$5:$H$229,$A5,'All papers'!$E$5:$E$229,2020) -> 0 | F5: =COUNTIFS('All papers'!$H$5:$H$229,$A5,'All papers'!$E$5:$E$229,2021) -> 1 | G5: =COUNTIFS('All papers'!$H$5:$H$229,$A5,'All papers'!$E$5:$E$229,2022) -> 0 | H5: =COUNTIFS('All papers'!$H$5:$H$229,$A5,'All papers'!$E$5:$E$229,2023) -> 0 | I5: =COUNTIFS('All papers'!$H$5:$H$229,$A5,'All papers'!$E$5:$E$229,2024) -> 0 | J5: =COUNTIFS('All papers'!$H$5:$H$229,$A5,'All papers'!$E$5:$E$229,2025) -> 0 | K5: =COUNTIFS('All papers'!$H$5:$H$229,$A5,'All papers'!$E$5:$E$229,2026) -> 0 | L5: =SUM(B5:K5) -> 16
A6: Differential privacy | B6: =COUNTIFS('All papers'!$H$5:$H$229,$A6,'All papers'!$E$5:$E$229,"<2018") -> 2 | C6: =COUNTIFS('All papers'!$H$5:$H$229,$A6,'All papers'!$E$5:$E$229,2018) -> 2 | D6: =COUNTIFS('All papers'!$H$5:$H$229,$A6,'All papers'!$E$5:$E$229,2019) -> 3 | E6: =COUNTIFS('All papers'!$H$5:$H$229,$A6,'All papers'!$E$5:$E$229,2020) -> 1 | F6: =COUNTIFS('All papers'!$H$5:$H$229,$A6,'All papers'!$E$5:$E$229,2021) -> 2 | G6: =COUNTIFS('All papers'!$H$5:$H$229,$A6,'All papers'!$E$5:$E$229,2022) -> 2 | H6: =COUNTIFS('All papers'!$H$5:$H$229,$A6,'All papers'!$E$5:$E$229,2023) -> 2 | I6: =COUNTIFS('All papers'!$H$5:$H$229,$A6,'All papers'!$E$5:$E$229,2024) -> 0 | J6: =COUNTIFS('All papers'!$H$5:$H$229,$A6,'All papers'!$E$5:$E$229,2025) -> 0 | K6: =COUNTIFS('All papers'!$H$5:$H$229,$A6,'All papers'!$E$5:$E$229,2026) -> 0 | L6: =SUM(B6:K6) -> 14
A7: De-identification (generative) | B7: =COUNTIFS('All papers'!$H$5:$H$229,$A7,'All papers'!$E$5:$E$229,"<2018") -> 1 | C7: =COUNTIFS('All papers'!$H$5:$H$229,$A7,'All papers'!$E$5:$E$229,2018) -> 3 | D7: =COUNTIFS('All papers'!$H$5:$H$229,$A7,'All papers'!$E$5:$E$229,2019) -> 3 | E7: =COUNTIFS('All papers'!$H$5:$H$229,$A7,'All papers'!$E$5:$E$229,2020) -> 2 | F7: =COUNTIFS('All papers'!$H$5:$H$229,$A7,'All papers'!$E$5:$E$229,2021) -> 2 | G7: =COUNTIFS('All papers'!$H$5:$H$229,$A7,'All papers'!$E$5:$E$229,2022) -> 0 | H7: =COUNTIFS('All papers'!$H$5:$H$229,$A7,'All papers'!$E$5:$E$229,2023) -> 7 | I7: =COUNTIFS('All papers'!$H$5:$H$229,$A7,'All papers'!$E$5:$E$229,2024) -> 6 | J7: =COUNTIFS('All papers'!$H$5:$H$229,$A7,'All papers'!$E$5:$E$229,2025) -> 4 | K7: =COUNTIFS('All papers'!$H$5:$H$229,$A7,'All papers'!$E$5:$E$229,2026) -> 0 | L7: =SUM(B7:K7) -> 28
A8: Adversarial privacy | B8: =COUNTIFS('All papers'!$H$5:$H$229,$A8,'All papers'!$E$5:$E$229,"<2018") -> 4 | C8: =COUNTIFS('All papers'!$H$5:$H$229,$A8,'All papers'!$E$5:$E$229,2018) -> 1 | D8: =COUNTIFS('All papers'!$H$5:$H$229,$A8,'All papers'!$E$5:$E$229,2019) -> 1 | E8: =COUNTIFS('All papers'!$H$5:$H$229,$A8,'All papers'!$E$5:$E$229,2020) -> 3 | F8: =COUNTIFS('All papers'!$H$5:$H$229,$A8,'All papers'!$E$5:$E$229,2021) -> 7 | G8: =COUNTIFS('All papers'!$H$5:$H$229,$A8,'All papers'!$E$5:$E$229,2022) -> 5 | H8: =COUNTIFS('All papers'!$H$5:$H$229,$A8,'All papers'!$E$5:$E$229,2023) -> 1 | I8: =COUNTIFS('All papers'!$H$5:$H$229,$A8,'All papers'!$E$5:$E$229,2024) -> 2 | J8: =COUNTIFS('All papers'!$H$5:$H$229,$A8,'All papers'!$E$5:$E$229,2025) -> 5 | K8: =COUNTIFS('All papers'!$H$5:$H$229,$A8,'All papers'!$E$5:$E$229,2026) -> 1 | L8: =SUM(B8:K8) -> 30
A9: Unlearnable images & anti-customisation | B9: =COUNTIFS('All papers'!$H$5:$H$229,$A9,'All papers'!$E$5:$E$229,"<2018") -> 0 | C9: =COUNTIFS('All papers'!$H$5:$H$229,$A9,'All papers'!$E$5:$E$229,2018) -> 0 | D9: =COUNTIFS('All papers'!$H$5:$H$229,$A9,'All papers'!$E$5:$E$229,2019) -> 0 | E9: =COUNTIFS('All papers'!$H$5:$H$229,$A9,'All papers'!$E$5:$E$229,2020) -> 0 | F9: =COUNTIFS('All papers'!$H$5:$H$229,$A9,'All papers'!$E$5:$E$229,2021) -> 2 | G9: =COUNTIFS('All papers'!$H$5:$H$229,$A9,'All papers'!$E$5:$E$229,2022) -> 3 | H9: =COUNTIFS('All papers'!$H$5:$H$229,$A9,'All papers'!$E$5:$E$229,2023) -> 8 | I9: =COUNTIFS('All papers'!$H$5:$H$229,$A9,'All papers'!$E$5:$E$229,2024) -> 5 | J9: =COUNTIFS('All papers'!$H$5:$H$229,$A9,'All papers'!$E$5:$E$229,2025) -> 1 | K9: =COUNTIFS('All papers'!$H$5:$H$229,$A9,'All papers'!$E$5:$E$229,2026) -> 0 | L9: =SUM(B9:K9) -> 19
A10: Identity protection: templates & encrypted matching | B10: =COUNTIFS('All papers'!$H$5:$H$229,$A10,'All papers'!$E$5:$E$229,"<2018") -> 9 | C10: =COUNTIFS('All papers'!$H$5:$H$229,$A10,'All papers'!$E$5:$E$229,2018) -> 3 | D10: =COUNTIFS('All papers'!$H$5:$H$229,$A10,'All papers'!$E$5:$E$229,2019) -> 0 | E10: =COUNTIFS('All papers'!$H$5:$H$229,$A10,'All papers'!$E$5:$E$229,2020) -> 1 | F10: =COUNTIFS('All papers'!$H$5:$H$229,$A10,'All papers'!$E$5:$E$229,2021) -> 1 | G10: =COUNTIFS('All papers'!$H$5:$H$229,$A10,'All papers'!$E$5:$E$229,2022) -> 8 | H10: =COUNTIFS('All papers'!$H$5:$H$229,$A10,'All papers'!$E$5:$E$229,2023) -> 2 | I10: =COUNTIFS('All papers'!$H$5:$H$229,$A10,'All papers'!$E$5:$E$229,2024) -> 1 | J10: =COUNTIFS('All papers'!$H$5:$H$229,$A10,'All papers'!$E$5:$E$229,2025) -> 0 | K10: =COUNTIFS('All papers'!$H$5:$H$229,$A10,'All papers'!$E$5:$E$229,2026) -> 0 | L10: =SUM(B10:K10) -> 25
A11: Soft-biometric privacy | B11: =COUNTIFS('All papers'!$H$5:$H$229,$A11,'All papers'!$E$5:$E$229,"<2018") -> 1 | C11: =COUNTIFS('All papers'!$H$5:$H$229,$A11,'All papers'!$E$5:$E$229,2018) -> 1 | D11: =COUNTIFS('All papers'!$H$5:$H$229,$A11,'All papers'!$E$5:$E$229,2019) -> 2 | E11: =COUNTIFS('All papers'!$H$5:$H$229,$A11,'All papers'!$E$5:$E$229,2020) -> 5 | F11: =COUNTIFS('All papers'!$H$5:$H$229,$A11,'All papers'!$E$5:$E$229,2021) -> 2 | G11: =COUNTIFS('All papers'!$H$5:$H$229,$A11,'All papers'!$E$5:$E$229,2022) -> 0 | H11: =COUNTIFS('All papers'!$H$5:$H$229,$A11,'All papers'!$E$5:$E$229,2023) -> 1 | I11: =COUNTIFS('All papers'!$H$5:$H$229,$A11,'All papers'!$E$5:$E$229,2024) -> 0 | J11: =COUNTIFS('All papers'!$H$5:$H$229,$A11,'All papers'!$E$5:$E$229,2025) -> 0 | K11: =COUNTIFS('All papers'!$H$5:$H$229,$A11,'All papers'!$E$5:$E$229,2026) -> 0 | L11: =SUM(B11:K11) -> 12
A12: Training-data privacy & synthetic data | B12: =COUNTIFS('All papers'!$H$5:$H$229,$A12,'All papers'!$E$5:$E$229,"<2018") -> 1 | C12: =COUNTIFS('All papers'!$H$5:$H$229,$A12,'All papers'!$E$5:$E$229,2018) -> 0 | D12: =COUNTIFS('All papers'!$H$5:$H$229,$A12,'All papers'!$E$5:$E$229,2019) -> 0 | E12: =COUNTIFS('All papers'!$H$5:$H$229,$A12,'All papers'!$E$5:$E$229,2020) -> 1 | F12: =COUNTIFS('All papers'!$H$5:$H$229,$A12,'All papers'!$E$5:$E$229,2021) -> 3 | G12: =COUNTIFS('All papers'!$H$5:$H$229,$A12,'All papers'!$E$5:$E$229,2022) -> 3 | H12: =COUNTIFS('All papers'!$H$5:$H$229,$A12,'All papers'!$E$5:$E$229,2023) -> 4 | I12: =COUNTIFS('All papers'!$H$5:$H$229,$A12,'All papers'!$E$5:$E$229,2024) -> 2 | J12: =COUNTIFS('All papers'!$H$5:$H$229,$A12,'All papers'!$E$5:$E$229,2025) -> 1 | K12: =COUNTIFS('All papers'!$H$5:$H$229,$A12,'All papers'!$E$5:$E$229,2026) -> 0 | L12: =SUM(B12:K12) -> 15
A13: Machine unlearning & auditing | B13: =COUNTIFS('All papers'!$H$5:$H$229,$A13,'All papers'!$E$5:$E$229,"<2018") -> 2 | C13: =COUNTIFS('All papers'!$H$5:$H$229,$A13,'All papers'!$E$5:$E$229,2018) -> 0 | D13: =COUNTIFS('All papers'!$H$5:$H$229,$A13,'All papers'!$E$5:$E$229,2019) -> 0 | E13: =COUNTIFS('All papers'!$H$5:$H$229,$A13,'All papers'!$E$5:$E$229,2020) -> 2 | F13: =COUNTIFS('All papers'!$H$5:$H$229,$A13,'All papers'!$E$5:$E$229,2021) -> 1 | G13: =COUNTIFS('All papers'!$H$5:$H$229,$A13,'All papers'!$E$5:$E$229,2022) -> 1 | H13: =COUNTIFS('All papers'!$H$5:$H$229,$A13,'All papers'!$E$5:$E$229,2023) -> 8 | I13: =COUNTIFS('All papers'!$H$5:$H$229,$A13,'All papers'!$E$5:$E$229,2024) -> 4 | J13: =COUNTIFS('All papers'!$H$5:$H$229,$A13,'All papers'!$E$5:$E$229,2025) -> 0 | K13: =COUNTIFS('All papers'!$H$5:$H$229,$A13,'All papers'!$E$5:$E$229,2026) -> 0 | L13: =SUM(B13:K13) -> 18
A14: Attacks & evaluations | B14: =COUNTIFS('All papers'!$H$5:$H$229,$A14,'All papers'!$E$5:$E$229,"<2018") -> 3 | C14: =COUNTIFS('All papers'!$H$5:$H$229,$A14,'All papers'!$E$5:$E$229,2018) -> 0 | D14: =COUNTIFS('All papers'!$H$5:$H$229,$A14,'All papers'!$E$5:$E$229,2019) -> 1 | E14: =COUNTIFS('All papers'!$H$5:$H$229,$A14,'All papers'!$E$5:$E$229,2020) -> 1 | F14: =COUNTIFS('All papers'!$H$5:$H$229,$A14,'All papers'!$E$5:$E$229,2021) -> 2 | G14: =COUNTIFS('All papers'!$H$5:$H$229,$A14,'All papers'!$E$5:$E$229,2022) -> 2 | H14: =COUNTIFS('All papers'!$H$5:$H$229,$A14,'All papers'!$E$5:$E$229,2023) -> 5 | I14: =COUNTIFS('All papers'!$H$5:$H$229,$A14,'All papers'!$E$5:$E$229,2024) -> 4 | J14: =COUNTIFS('All papers'!$H$5:$H$229,$A14,'All papers'!$E$5:$E$229,2025) -> 4 | K14: =COUNTIFS('All papers'!$H$5:$H$229,$A14,'All papers'!$E$5:$E$229,2026) -> 3 | L14: =SUM(B14:K14) -> 25
A15: Surveys, audits & society | B15: =COUNTIFS('All papers'!$H$5:$H$229,$A15,'All papers'!$E$5:$E$229,"<2018") -> 3 | C15: =COUNTIFS('All papers'!$H$5:$H$229,$A15,'All papers'!$E$5:$E$229,2018) -> 1 | D15: =COUNTIFS('All papers'!$H$5:$H$229,$A15,'All papers'!$E$5:$E$229,2019) -> 2 | E15: =COUNTIFS('All papers'!$H$5:$H$229,$A15,'All papers'!$E$5:$E$229,2020) -> 3 | F15: =COUNTIFS('All papers'!$H$5:$H$229,$A15,'All papers'!$E$5:$E$229,2021) -> 4 | G15: =COUNTIFS('All papers'!$H$5:$H$229,$A15,'All papers'!$E$5:$E$229,2022) -> 0 | H15: =COUNTIFS('All papers'!$H$5:$H$229,$A15,'All papers'!$E$5:$E$229,2023) -> 3 | I15: =COUNTIFS('All papers'!$H$5:$H$229,$A15,'All papers'!$E$5:$E$229,2024) -> 1 | J15: =COUNTIFS('All papers'!$H$5:$H$229,$A15,'All papers'!$E$5:$E$229,2025) -> 2 | K15: =COUNTIFS('All papers'!$H$5:$H$229,$A15,'All papers'!$E$5:$E$229,2026) -> 4 | L15: =SUM(B15:K15) -> 23
A16: Total | B16: =SUM(B5:B15) -> 39 | C16: =SUM(C5:C15) -> 13 | D16: =SUM(D5:D15) -> 12 | E16: =SUM(E5:E15) -> 19 | F16: =SUM(F5:F15) -> 27 | G16: =SUM(G5:G15) -> 24 | H16: =SUM(H5:H15) -> 41 | I16: =SUM(I5:I15) -> 25 | ... L16: =SUM(L5:L15) -> 225
A19: Other counts
A20: Entries with public code | B20: =COUNTIF('All papers'!$R$5:$R$229,"Yes") -> 77
A21: Entries from 2018 onward | B21: =COUNTIF('All papers'!$E$5:$E$229,">=2018") -> 186
A22: Preprints or under review | B22: =COUNTIF('All papers'!$G$5:$G$229,"Preprint") -> 24
A23: Grey literature (Other) | B23: =COUNTIF('All papers'!$G$5:$G$229,"Other") -> 14
A24: All entries | B24: =COUNTA('All papers'!$H$5:$H$229) -> 225

Sheet Before 2018
A1: Before 2018
A2: 39 entries before 2018: the foundations.
A4: # | B4: ID | C4: Paper title | D4: Authors | E4: Year | F4: Venue | G4: Venue type | H4: Family | I4: Chart group | J4: Datasets | K4: Models / backbones | L4: Approach | M4: Key findings | N4: Threat model / protects against | O4: Utility preserved | P4: Limitations & known attacks | Q4: Tags | R4: Code available | S4: GitHub / code link | T4: Paper link | U4: Google Scholar
A5: 1 | B5: oh2017 | C5: Adversarial Image Perturbation for Privacy Protection: A Game Theory Perspective | D5: Seong Joon Oh, Mario Fritz, Bernt Schiele | E5: 2017 | F5: ICCV | G5: Vision | H5: Adversarial privacy | I5: Adversarial & unlearnable | J5: PIPA | K5: ResNet person recogniser (head and body cues) | L5: Models user and recogniser as players: the user perturbs, the recogniser may adapt (e.g., train on perturbed data). Studies equilibria. | M5: Showed that a recogniser who knows the perturbation strategy recovers much accuracy; users must randomise to keep any advantage. An early warning of the arms race. | N5: Adaptive person recognisers on social media. | O5: Perturbations kept small. | P5: Analysis limited to 2017 architectures. | Q5: game theory, perturbation, recogniser adaptation | R5: No | T5: https://arxiv.org/abs/1703.09471 | U5: Search
A6: 2 | B6: brkic2017 | C6: I Know That Person: Generative Full Body and Face De-identification of People in Images | D6: Karla Brkić, Ivan Sikirić, Tomislav Hrkać, Zoran Kalafatić | E6: 2017 | F6: CVPR Workshops | G6: Vision | H6: De-identification (generative) | I6: Generative de-identification | J6: Own surveillance-style images; ClothingAttributes | K6: Segmentation + generative replacement | L6: Segments people and replaces face and body with generated appearance, keeping pose. | M6: Early demonstration that generative replacement can de-identify the whole person, not just the face. | N6: Recognition by face and by clothing or body. | O6: Pose and scene. | P6: Low resolution; identity leakage through unreplaced cues. | Q6: GAN, full body, de-identification | R6: No | T6: https://doi.org/10.1109/CVPRW.2017.173 | U6: Search
A7: 3 | B7: shokri2017 | C7: Membership Inference Attacks Against Machine Learning Models | D7: Reza Shokri, Marco Stronati, Congzheng Song, Vitaly Shmatikov | E7: 2017 | F7: IEEE Symposium on Security and Privacy | G7: Security | H7: Machine unlearning & auditing | I7: Training data & unlearning | J7: CIFAR, Purchase, Texas hospital, MNIST, UCI Adult | K7: Google Prediction API, Amazon ML, CNNs | L7: Shadow models trained to mimic a target let an attacker tell whether a record was in the target's training set from its outputs. | M7: Black-box membership inference against commercial ML-as-a-service models; overfitting drives leakage. | N7: Proving a person's data was used to train a model. | O7: Not applicable. | P7: Later work shows weaker attacks on well-generalised models; face-specific variants followed. | Q7: membership inference, auditing, foundational | R7: No | T7: https://arxiv.org/abs/1610.05820 | U7: Search
A8: 4 | B8: ryoo2017 | C8: Privacy-Preserving Human Activity Recognition from Extreme Low Resolution | D8: Michael S. Ryoo, Brandon Rothrock, Charles Fleming, Hyun Jong Yang | E8: 2017 | F8: AAAI | G8: ML | H8: Blur, pixelation & obfuscation | I8: Obfuscation & differential privacy | J8: HMDB, DogCentric at 16×12 | K8: Two-stream CNN with inverse super-resolution | L8: Recognises human activities from 16×12 pixel video using inverse super-resolution to learn from multiple low-resolution transforms. | M8: Activity recognition stayed useful at resolutions where faces are unrecognisable, motivating low-resolution cameras as privacy by design. | N8: Identification from in-home or workplace cameras. | O8: Activity recognition. | P8: Fine-grained tasks impossible; gait and body shape can still identify. | Q8: extreme low resolution, activity recognition, inverse super-resolution | R8: No | T8: https://ojs.aaai.org/index.php/AAAI/article/view/11233 | U8: Search
A9: 5 | B9: mirjalili2017 | C9: Soft Biometric Privacy: Retaining Biometric Utility of Face Images While Perturbing Gender | D9: Vahid Mirjalili, Arun Ross | E9: 2017 | F9: IJCB | G9: Biometrics | H9: Soft-biometric privacy | I9: Soft-biometric privacy | J9: MUCT, LFW, CelebA | K9: Commercial face matcher; IntraFace gender classifier | L9: Perturbs face images so gender classifiers fail while a face matcher still verifies identity. | M9: Gender prediction dropped toward chance with small loss in matching accuracy. | N9: Automated attribute inference from stored face images. | O9: Identity matching. | P9: Classifier-specific perturbations; later shown recoverable. | Q9: gender, perturbation, matching utility | R9: No | T9: https://doi.org/10.1109/BTAS.2017.8272743 | U9: Search
A10: 6 | B10: sharif2016 | C10: Accessorize to a Crime: Real and Stealthy Attacks on State-of-the-Art Face Recognition | D10: Mahmood Sharif, Sruti Bhagavatula, Lujo Bauer, Michael K. Reiter | E10: 2016 | F10: ACM CCS | G10: Security | H10: Adversarial privacy | I10: Adversarial & unlearnable | J10: PubFig; own photographs | K10: VGG-Face based DNNs | L10: Prints adversarial patterns onto eyeglass frames so a wearer either evades recognition (dodging) or is recognised as a chosen target (impersonation). | M10: Physically realised attacks on a deep recogniser; high dodging success and impersonation success above 80% for some target pairs. | N10: White-box and, in follow-ups, black-box deep face recognition. | O10: Wearer looks like a person in glasses. | P10: Needed model access originally; patterns are visibly odd; later systems retrained. | Q10: physical, eyeglasses, dodging, impersonation | R10: No | T10: https://doi.org/10.1145/2976749.2978392 | U10: Search
A11: 7 | B11: ribaric2016 | C11: De-identification for Privacy Protection in Multimedia Content: A Survey | D11: Slobodan Ribaric, Aladdin Ariyaeeinia, Nikola Pavesic | E11: 2016 | F11: Signal Processing: Image Communication | G11: Journal | H11: Surveys, audits & society | I11: Surveys & society | J11: Survey (many) | K11: Survey | L11: Survey covering de-identification of face, gait, voice, text and soft biometrics across images, video and audio. | M11: Framed de-identification as a multimodal problem and set out evaluation criteria (naturalness, reversibility, utility) later surveys reuse. | N11: Identification from any biometric or non-biometric identifier in media. | O11: Discussed as a design criterion. | P11: Written just before deep generative de-identification took over. | Q11: survey, de-identification, multimodal | R11: No | T11: https://doi.org/10.1016/j.image.2016.05.020 | U11: Search
A12: 8 | B12: abadi2016 | C12: Deep Learning with Differential Privacy | D12: Martín Abadi, Andy Chu, Ian Goodfellow, H. Brendan McMahan, Ilya Mironov, Kunal Talwar, Li Zhang | E12: 2016 | F12: ACM CCS | G12: Security | H12: Differential privacy | I12: Obfuscation & differential privacy | J12: MNIST, CIFAR-10 | K12: CNNs | L12: DP-SGD: clip per-example gradients and add Gaussian noise, with a moments accountant to track the privacy budget. | M12: Trained image classifiers with formal DP at modest accuracy cost; the standard for DP training of face and other models. | N12: Membership and reconstruction attacks on trained models. | O12: Model accuracy (reduced). | P12: Accuracy gap widens on large models and fine-grained tasks such as face recognition. | Q12: DP-SGD, moments accountant, training | R12: Yes | S12: https://github.com/tensorflow/privacy | T12: https://arxiv.org/abs/1607.00133 | U12: Search
A13: 9 | B13: pandey2016 | C13: Deep Secure Encoding for Face Template Protection | D13: Rohit Kumar Pandey, Yingbo Zhou, Bhargava Urala Kota, Venu Govindaraju | E13: 2016 | F13: CVPR Workshops | G13: Vision | H13: Identity protection: templates & encrypted matching | I13: Template protection | J13: CMU-PIE, Extended Yale B, Multi-PIE | K13: CNN + SHA-512 | L13: Trains a CNN to map a user's face images to a random binary code that is then cryptographically hashed, so only the hash is stored. | M13: High matching accuracy with a stored template that is a one-way hash. | N13: Template database theft. | O13: Verification accuracy. | P13: Per-user training; small closed datasets. | Q13: binary codes, hashing, CNN | R13: No | T13: https://doi.org/10.1109/CVPRW.2016.17 | U13: Search
A14: 10 | B14: mcpherson2016 | C14: Defeating Image Obfuscation with Deep Learning | D14: Richard McPherson, Reza Shokri, Vitaly Shmatikov | E14: 2016 | F14: arXiv preprint | G14: Preprint | H14: Attacks & evaluations | I14: Attacks & evaluations | J14: MNIST, CIFAR-10, AT&T faces, FaceScrub | K14: CNN classifiers trained on obfuscated data | L14: Trains recognisers directly on obfuscated images (mosaicing, YouTube-style blur, P3 encryption) to identify faces, digits and objects. | M14: Identification far above chance on all three obfuscations, including heavy pixelation; showed obfuscation designed for human eyes does not stop machines. | N14: Anyone with obfuscated images and a labelled reference set. | O14: Not applicable. | P14: Closed-set recognition; still the standard citation against blur and pixelation. | Q14: pixelation, blur, P3, recognition | R14: No | T14: https://arxiv.org/abs/1609.00408 | U14: Search
A15: 11 | B15: oh2016 | C15: Faceless Person Recognition: Privacy Implications in Social Media | D15: Seong Joon Oh, Rodrigo Benenson, Mario Fritz, Bernt Schiele | E15: 2016 | F15: ECCV | G15: Vision | H15: Attacks & evaluations | I15: Attacks & evaluations | J15: PIPA | K15: AlexNet-based person recogniser | L15: Recognises people in social-media photos from body, clothing and scene even when faces are blurred or blacked out. | M15: Substantial recognition with only a handful of tagged examples and no visible face; obfuscating the face alone protects less than assumed. | N15: Recognition from non-face cues. | O15: Not applicable. | P15: Studied a single album domain; motivated full-body anonymisation. | Q15: person recognition, context, blur | R15: No | T15: https://arxiv.org/abs/1607.08438 | U15: Search
A16: 12 | B16: zhmoginov2016 | C16: Inverting Face Embeddings with Convolutional Neural Networks | D16: Andrey Zhmoginov, Mark Sandler | E16: 2016 | F16: arXiv preprint | G16: Preprint | H16: Attacks & evaluations | I16: Attacks & evaluations | J16: LFW-scale face sets | K16: FaceNet embeddings; CNN inverter | L16: Trains a network to reconstruct a face image from a FaceNet embedding. | M16: Recognisable reconstructions from 128 numbers, the first public demonstration that deep templates leak appearance. | N16: Attacker holding stolen embeddings. | O16: Not applicable. | P16: Low resolution; white-box embedding model. | Q16: template inversion, FaceNet | R16: No | T16: https://arxiv.org/abs/1606.04189 | U16: Search
A17: 13 | B17: guo2016 | C17: MS-Celeb-1M: A Dataset and Benchmark for Large-Scale Face Recognition | D17: Yandong Guo, Lei Zhang, Yuxiao Hu, Xiaodong He, Jianfeng Gao | E17: 2016 | F17: ECCV | G17: Vision | H17: Training-data privacy & synthetic data | I17: Training data & unlearning | J17: MS-Celeb-1M | K17: Benchmark for deep recognisers | L17: Ten million web-scraped images of about 100,000 celebrities as a training benchmark. | M17: Powered a generation of recognisers; withdrawn by Microsoft in 2019 after the Exposing.ai investigation showed it included non-celebrities and had been used by surveillance vendors. Copies still circulate as MS1M variants. | N17: Not a protection paper: the canonical example of the consent problem. | O17: Not applicable. | P17: Noisy labels; withdrawn. | Q17: dataset, scraping, withdrawn | R17: No | T17: https://arxiv.org/abs/1607.08221 | U17: Search
A18: 14 | B18: garvie2016 | C18: The Perpetual Line-Up: Unregulated Police Face Recognition in America | D18: Clare Garvie, Alvaro Bedoya, Jonathan Frankle | E18: 2016 | F18: Georgetown Law Center on Privacy & Technology | G18: Other | H18: Surveys, audits & society | I18: Surveys & society | J18: Records from 100+ US agencies | K18: None | L18: Records requests to over 100 US police agencies on face recognition use, databases and safeguards. | M18: Estimated half of American adults were in a law-enforcement face network; found almost no accuracy testing, bias audits or legal limits. | N18: State use of driver's licence photos for identification. | O18: Not applicable. | P18: US only; snapshot of 2016. | Q18: policy, police, audit | R18: No | T18: https://www.perpetuallineup.org | U18: Search
A19: 15 | B19: nandakumar2015 | C19: Biometric Template Protection: Bridging the Performance Gap Between Theory and Practice | D19: Karthik Nandakumar, Anil K. Jain | E19: 2015 | F19: IEEE Signal Processing Magazine | G19: Journal | H19: Identity protection: templates & encrypted matching | I19: Template protection | J19: Survey (many) | K19: Survey | L19: Survey of feature transformation and biometric cryptosystem approaches with the requirements of irreversibility, unlinkability and revocability. | M19: Identified the accuracy loss and representation mismatch that kept template protection out of deployment. | N19: Template database compromise. | O19: Discussed per scheme. | P19: Pre-deep-features; the gap it describes narrowed after 2018. | Q19: survey, template protection | R19: No | T19: https://doi.org/10.1109/MSP.2015.2427849 | U19: Search
A20: 16 | B20: ilia2015 | C20: Face/Off: Preventing Privacy Leakage From Photos in Social Networks | D20: Panagiotis Ilia, Iasonas Polakis, Elias Athanasopoulos, Federico Maggi, Sotiris Ioannidis | E20: 2015 | F20: ACM CCS | G20: Security | H20: Blur, pixelation & obfuscation | I20: Obfuscation & differential privacy | J20: Facebook photos in user study | K20: Face recognition for detection; blur | L20: Blurs the faces of users who have not consented to a photo when it is shown to viewers outside their permitted audience, using face recognition to find them. | M20: Prototype on a social network with a user study showing acceptance; reframed tagging as an access-control problem. | N20: Bystanders and friends exposed in others' uploads. | O20: Photo intact for permitted viewers. | P20: Relies on recognition to protect against recognition; blur remains weak. | Q20: social networks, per-user blur, access control | R20: No | T20: https://doi.org/10.1145/2810103.2813603 | U20: Search
A21: 17 | B21: pittaluga2015 | C21: Privacy Preserving Optics for Miniature Vision Sensors | D21: Francesco Pittaluga, Sanjeev J. Koppal | E21: 2015 | F21: CVPR | G21: Vision | H21: Blur, pixelation & obfuscation | I21: Obfuscation & differential privacy | J21: Own captured scenes | K21: Custom optics and sensors | L21: Designs optical elements and sensors that never capture an identifiable image yet support tasks such as motion or blob detection. | M21: Demonstrated task-specific optics that defocus or aggregate light so identity is destroyed before digitisation. | N21: Any leak of captured imagery, including compromised sensors. | O21: Coarse tasks only. | P21: Task-specific hardware; low information. | Q21: optics, pre-capture, sensor-level | R21: No | T21: https://doi.org/10.1109/CVPR.2015.7298658 | U21: Search
A22: 18 | B22: reflectacles2015 | C22: Reflectacles: IR-blocking and reflective privacy eyewear | D22: Scott Urban (Reflectacles) | E22: 2015 | F22: Commercial product | G22: Other | H22: Adversarial privacy | I22: Adversarial & unlearnable | J22: None | K22: Infrared CCTV and structured-light sensors | L22: Eyewear with frames that reflect infrared and lenses that absorb near-infrared, aimed at IR-illuminated CCTV and 3D IR face mapping. | M22: Blocks the eye region for infrared systems including structured-light phone unlock; no effect on visible-light cameras. | N22: Near-infrared cameras and IR depth sensors. | O22: Ordinary glasses to a human. | P22: Useless against the visible-light cameras that dominate public CCTV and social media. | Q22: physical, infrared, eyewear | R22: No | T22: https://www.reflectacles.com | U22: Search
A23: 19 | B23: cao2015 | C23: Towards Making Systems Forget with Machine Unlearning | D23: Yinzhi Cao, Junfeng Yang | E23: 2015 | F23: IEEE Symposium on Security and Privacy | G23: Security | H23: Machine unlearning & auditing | I23: Training data & unlearning | J23: LensKit, Zozzle, OSN spam, PJScan | K23: Statistical query learners | L23: Coins machine unlearning: restructure learning into summations so a training sample's contribution can be subtracted without retraining. | M23: Exact forgetting for a class of models at a fraction of retraining cost. | N23: Data whose deletion a user requests but a trained model still encodes. | O23: Model accuracy retained. | P23: Does not cover deep networks. | Q23: machine unlearning, summation form, foundational | R23: No | T23: https://doi.org/10.1109/SP.2015.35 | U23: Search
A24: 20 | B24: padilla2015 | C24: Visual Privacy Protection Methods: A Survey | D24: José Ramón Padilla-López, Alexandros Andre Chaaraoui, Francisco Flórez-Revuelta | E24: 2015 | F24: Expert Systems with Applications | G24: Journal | H24: Surveys, audits & society | I24: Surveys & society | J24: Survey (many) | K24: Survey | L24: Survey of visual privacy protection in video: intervention, blind vision, secure processing, redaction (blur, pixelation, masking, encryption, k-Same) and data hiding. | M24: Organised the pre-deep-learning field into five categories and catalogued the utility loss of each redaction method. | N24: Human and automated observers of video. | O24: Discussed per method. | P24: Pre-dates GAN-based and adversarial methods entirely. | Q24: survey, visual privacy, video | R24: No | T24: https://doi.org/10.1016/j.eswa.2015.01.041 | U24: Search
... A43: 39 | B43: juels1999 | C43: A Fuzzy Commitment Scheme | D43: Ari Juels, Martin Wattenberg | E43: 1999 | F43: ACM CCS | G43: Security | H43: Identity protection: templates & encrypted matching | I43: Template protection | J43: None (theory) | K43: Error-correcting codes | L43: Commits to a codeword with the biometric as witness; a noisy but close biometric decommits via error correction. | M43: Founded biometric cryptosystems: a template that can be verified against a noisy reading without storing it. | N43: Template database theft. | O43: Verification only. | P43: Assumes a fixed-length, ordered binary representation; linkability across enrolments. | Q43: biometric cryptosystem, error-correcting codes | R43: No | T43: https://doi.org/10.1145/319709.319714 | U43: Search

Sheet 2018
A1: 2018
A2: 13 entries published or first released in 2018.
A4: # | B4: ID | C4: Paper title | D4: Authors | E4: Year | F4: Venue | G4: Venue type | H4: Family | I4: Chart group | J4: Datasets | K4: Models / backbones | L4: Approach | M4: Key findings | N4: Threat model / protects against | O4: Utility preserved | P4: Limitations & known attacks | Q4: Tags | R4: Code available | S4: GitHub / code link | T4: Paper link | U4: Google Scholar
A5: 1 | B5: sun2018b | C5: A Hybrid Model for Identity Obfuscation by Face Replacement | D5: Qianru Sun, Ayush Tewari, Weipeng Xu, Mario Fritz, Christian Theobalt, Bernt Schiele | E5: 2018 | F5: ECCV | G5: Vision | H5: De-identification (generative) | I5: Generative de-identification | J5: PIPA, CelebA | K5: 3D morphable model + refinement GAN | L5: Fits a parametric 3D face model, alters identity parameters, renders and then refines with a GAN. | M5: Explicit control of how far the new identity is from the original while keeping expression and pose. | N5: Automated face recognition. | O5: Expression, pose, lighting. | P5: Depends on 3DMM fitting quality; artefacts at extreme poses. | Q5: 3D morphable model, face replacement, GAN | R5: No | T5: https://arxiv.org/abs/1804.04779 | U5: Search
A6: 2 | B6: xie2018 | C6: Differentially Private Generative Adversarial Network | D6: Liyang Xie, Kaixiang Lin, Shu Wang, Fei Wang, Jiayu Zhou | E6: 2018 | F6: arXiv preprint | G6: Preprint | H6: Differential privacy | I6: Obfuscation & differential privacy | J6: MNIST, MIMIC-III | K6: GAN | L6: Adds calibrated noise to discriminator gradients during GAN training so generated samples carry a DP guarantee. | M6: Synthetic images and health records with formal privacy at reduced fidelity. | N6: Leakage of training samples through a generator. | O6: Synthetic data utility (reduced). | P6: Poor image quality at strong budgets. | Q6: DPGAN, synthetic data | R6: No | T6: https://arxiv.org/abs/1802.06739 | U6: Search
A7: 3 | B7: jindal2018 | C7: Face Template Protection Using Deep Convolutional Neural Network | D7: Arun Kumar Jindal, Srinivas Chalamala, Santosh Kumar Jami | E7: 2018 | F7: CVPR Workshops | G7: Vision | H7: Identity protection: templates & encrypted matching | I7: Template protection | J7: CMU-PIE, FEI, Color FERET | K7: VGG-Face features + CNN | L7: Random projection of deep features to binary codes followed by hashing, with a CNN trained to be robust to intra-class variation. | M7: Improved robustness over deep secure encoding on standard face sets. | N7: Template theft. | O7: Verification accuracy. | P7: Stolen-token scenario weakens security. | Q7: binary codes, random projection, hashing | R7: No | T7: https://doi.org/10.1109/CVPRW.2018.00087 | U7: Search
A8: 4 | B8: buolamwini2018 | C8: Gender Shades: Intersectional Accuracy Disparities in Commercial Gender Classification | D8: Joy Buolamwini, Timnit Gebru | E8: 2018 | F8: FAT* (ACM FAccT) | G8: ML | H8: Surveys, audits & society | I8: Surveys & society | J8: Pilot Parliaments Benchmark (PPB) | K8: Microsoft, IBM, Face++ gender classifiers | L8: Audits three commercial gender classifiers on a balanced dataset stratified by skin type and gender. | M8: Error rates up to 34.7% for darker-skinned women versus at most 0.8% for lighter-skinned men. | N8: Disparate harm from face analysis. | O8: Not applicable. | P8: Gender classification, not identification; vendors updated afterwards. | Q8: audit, bias, commercial systems | R8: No | T8: https://proceedings.mlr.press/v81/buolamwini18a.html | U8: Search
A9: 5 | B9: gomez2018 | C9: General Framework to Evaluate Unlinkability in Biometric Template Protection Systems | D9: Marta Gomez-Barrero, Javier Galbally, Christian Rathgeb, Christoph Busch | E9: 2018 | F9: IEEE TIFS | G9: Journal | H9: Identity protection: templates & encrypted matching | I9: Template protection | J9: Face, iris and fingerprint benchmarks | K9: Bloom-filter and other protected templates | L9: Defines local and global unlinkability measures from mated and non-mated score distributions of protected templates. | M9: Became the standard way to report unlinkability in template protection papers. | N9: Cross-matching templates across databases. | O9: Not applicable; an evaluation method. | P9: Score-based; does not capture all inversion risks. | Q9: unlinkability, evaluation, metric | R9: No | T9: https://doi.org/10.1109/TIFS.2017.2788000 | U9: Search
A10: 6 | B10: fan2018 | C10: Image Pixelization with Differential Privacy | D10: Liyue Fan | E10: 2018 | F10: IFIP DBSec | G10: Security | H10: Differential privacy | I10: Obfuscation & differential privacy | J10: AT&T (ORL) faces and other image sets | K10: Pixelization with Laplace noise | L10: Extends pixelization with Laplace noise under an m-neighbourhood notion of differential privacy over images. | M10: First formal DP guarantee for image obfuscation; at useful privacy budgets the images are heavily degraded. | N10: Any inference from the released image, with a formal bound. | O10: Low at strong privacy levels. | P10: The neighbourhood definition is small; guarantees do not translate into recognition rates that users can interpret. | Q10: differential privacy, pixelization | R10: No | T10: https://doi.org/10.1007/978-3-319-95729-6_10 | U10: Search
A11: 7 | B11: zhou2018 | C11: Invisible Mask: Practical Attacks on Face Recognition with Infrared | D11: Zhe Zhou, Di Tang, Xiaofeng Wang, Weili Han, Xiangyu Liu, Kehuan Zhang | E11: 2018 | F11: arXiv preprint | G11: Preprint | H11: Adversarial privacy | I11: Adversarial & unlearnable | J11: LFW | K11: FaceNet | L11: Infrared LEDs hidden in a cap project adversarial light patterns invisible to people but captured by cameras. | M11: Over 70% success in finding infrared-realisable adversarial examples; demonstrated impersonation against a commercial recogniser. | N11: Camera-based recognition, especially authentication. | O11: Wearer looks normal. | P11: Requires a target model to optimise against; IR-filtered cameras defeat it. | Q11: physical, infrared, LED, impersonation | R11: No | T11: https://arxiv.org/abs/1803.04683 | U11: Search
A12: 8 | B12: ren2018 | C12: Learning to Anonymize Faces for Privacy Preserving Action Detection | D12: Zhongzheng Ren, Yong Jae Lee, Michael S. Ryoo | E12: 2018 | F12: ECCV | G12: Vision | H12: De-identification (generative) | I12: Generative de-identification | J12: DALY, JHMDB (action detection) | K12: Face modifier GAN; face classifier; action detector in the loop | L12: Trains a face modifier and a face recogniser adversarially while a downstream action detector is trained on the modified video. | M12: Anonymised video retained action-detection accuracy while recognition on the modified faces dropped sharply. | N12: Identity recognition in video used for analytics. | O12: Action detection, by construction. | P12: Utility is task-specific; the recogniser in the loop bounds what the anonymiser learns to defeat. | Q12: adversarial training, action recognition, video | R12: No | T12: https://arxiv.org/abs/1803.11556 | U12: Search
A13: 9 | B13: sun2018a | C13: Natural and Effective Obfuscation by Head Inpainting | D13: Qianru Sun, Liqian Ma, Seong Joon Oh, Luc Van Gool, Bernt Schiele, Mario Fritz | E13: 2018 | F13: CVPR | G13: Vision | H13: De-identification (generative) | I13: Generative de-identification | J13: PIPA (People In Photo Albums) | K13: Landmark generator + inpainting GAN; person recogniser for evaluation | L13: Two-stage network: generate facial landmarks conditioned on context, then inpaint a new head consistent with the scene. | M13: Reduced recognition far more than blur while producing natural images; landmark stage allowed control over pose. | N13: Person recognition on social-media photos. | O13: Scene realism and pose. | P13: Resolution and identity control limited; evaluated against 2018 recognisers. | Q13: inpainting, landmarks, GAN | R13: No | T13: https://arxiv.org/abs/1711.09001 | U13: Search
A14: 10 | B14: boddeti2018 | C14: Secure Face Matching Using Fully Homomorphic Encryption | D14: Vishnu Naresh Boddeti | E14: 2018 | F14: IEEE BTAS | G14: Biometrics | H14: Identity protection: templates & encrypted matching | I14: Template protection | J14: LFW, IJB-A | K14: Deep face features; Fan-Vercauteren FHE | L14: Quantises deep face features and computes match scores under fully homomorphic encryption. | M14: Encrypted matching of 512-dimensional deep templates with negligible accuracy loss and practical latency for 1:1. | N14: Server or database learning the templates. | O14: Verification accuracy preserved. | P14: 1:N search too slow without further work (see HERS). | Q14: FHE, deep features, matching | R14: Yes | S14: https://github.com/human-analysis/secure-face-matching | T14: https://arxiv.org/abs/1805.00577 | U14: Search
A15: 11 | B15: mirjalili2018 | C15: Semi-Adversarial Networks: Convolutional Autoencoders for Imparting Privacy to Face Images | D15: Vahid Mirjalili, Sebastian Raschka, Anoop Namboodiri, Arun Ross | E15: 2018 | F15: ICB | G15: Biometrics | H15: Soft-biometric privacy | I15: Soft-biometric privacy | J15: CelebA, MORPH, MUCT, LFW | K15: Convolutional autoencoder; VGG-Face matcher; gender CNNs | L15: Autoencoder trained with an auxiliary matcher (to preserve) and gender classifier (to confuse). | M15: Generalised to unseen gender classifiers better than per-classifier perturbation. | N15: Unseen attribute classifiers. | O15: Identity matching. | P15: Single attribute; image-level artefacts. | Q15: SAN, autoencoder, gender | R15: No | T15: https://arxiv.org/abs/1712.00321 | U15: Search
A16: 12 | B16: wu2018 | C16: Towards Privacy-Preserving Visual Recognition via Adversarial Training: A Pilot Study | D16: Zhenyu Wu, Zhangyang Wang, Zhaowen Wang, Hailin Jin | E16: 2018 | F16: ECCV | G16: Vision | H16: Blur, pixelation & obfuscation | I16: Obfuscation & differential privacy | J16: SBU Kinship, UCF101, VISPR | K16: Degradation network; C3D/ResNet utility; identity CNN adversary | L16: Learns an image degradation jointly with a utility model and an adversarial privacy model so the degraded video supports action recognition but defeats identity and attribute inference. | M16: Learned degradations beat downsampling and blur on the utility-privacy frontier. | N16: Identity and attribute inference from shared video. | O16: Action recognition. | P16: Privacy measured against the attackers in the loop only. | Q16: learned degradation, adversarial training, utility-privacy | R16: No | T16: https://arxiv.org/abs/1807.08379 | U16: Search
A17: 13 | B17: meden2018 | C17: k-Same-Net: k-Anonymity with Generative Deep Neural Networks for Face Deidentification | D17: Blaž Meden, Žiga Emeršič, Vitomir Štruc, Peter Peer | E17: 2018 | F17: Entropy | G17: Journal | H17: Blur, pixelation & obfuscation | I17: Obfuscation & differential privacy | J17: XM2VTS | K17: Generative neural network (k-Same-Net); VGG-Face for evaluation | L17: Combines k-Same's k-anonymity with a generative network that synthesises the surrogate face, avoiding pixel averaging artefacts. | M17: Natural-looking surrogates that keep the k-anonymity guarantee; retained expression better than k-Same. | N17: Face recognition on released data. | O17: Expression and attribute utility measured; better than pixel k-Same. | P17: Generator limited to low resolution; still set-based. | Q17: k-Same, GAN, k-anonymity | R17: No | T17: https://doi.org/10.3390/e20010060 | U17: Search

Sheet 2019
A1: 2019
A2: 12 entries published or first released in 2019.
A4: # | B4: ID | C4: Paper title | D4: Authors | E4: Year | F4: Venue | G4: Venue type | H4: Family | I4: Chart group | J4: Datasets | K4: Models / backbones | L4: Approach | M4: Key findings | N4: Threat model / protects against | O4: Utility preserved | P4: Limitations & known attacks | Q4: Tags | R4: Code available | S4: GitHub / code link | T4: Paper link | U4: Google Scholar
A5: 1 | B5: sharif2019 | C5: A General Framework for Adversarial Examples with Objectives | D5: Mahmood Sharif, Sruti Bhagavatula, Lujo Bauer, Michael K. Reiter | E5: 2019 | F5: ACM TOPS | G5: Security | H5: Adversarial privacy | I5: Adversarial & unlearnable | J5: PubFig, VGGFace2; own photographs | K5: VGG-Face, OpenFace | L5: Adversarial Generative Nets: a GAN produces eyeglass patterns that are simultaneously inconspicuous, robust to pose and lighting, and adversarial. | M5: Inconspicuous physical attacks that transferred across recognisers and survived real-world capture. | N5: Deep face recognition, black-box in part. | O5: Frames look like fashion eyewear. | P5: Still requires substitute models; defended by adversarial training. | Q5: AGN, GAN, eyeglasses, physical | R5: No | T5: https://arxiv.org/abs/1801.00349 | U5: Search
A6: 2 | B6: raji2019 | C6: Actionable Auditing: Investigating the Impact of Publicly Naming Biased Performance Results of Commercial AI Products | D6: Inioluwa Deborah Raji, Joy Buolamwini | E6: 2019 | F6: AAAI/ACM AIES | G6: ML | H6: Surveys, audits & society | I6: Surveys & society | J6: PPB | K6: Microsoft, IBM, Face++, Amazon, Kairos | L6: Re-audits the Gender Shades vendors and others a year after publication. | M6: Named vendors reduced disparities substantially; unnamed ones had not. Public audits change products. | N6: Not applicable. | O6: Not applicable. | P6: Correlational evidence. | Q6: audit, accountability | R6: No | T6: https://doi.org/10.1145/3306618.3314244 | U6: Search
A7: 3 | B7: li2019 | C7: AnonymousNet: Natural Face De-Identification with Measurable Privacy | D7: Tao Li, Lei Lin | E7: 2019 | F7: CVPR Workshops | G7: Vision | H7: De-identification (generative) | I7: Generative de-identification | J7: CelebA | K7: Attribute predictor + StarGAN-style generator | L7: Four-stage pipeline: predict attributes, obfuscate them under a privacy metric, synthesise with a GAN, then add adversarial perturbation. | M7: Introduced measurable privacy for generative de-identification by tying attribute changes to a k-anonymity-style metric. | N7: Face recognition and attribute inference. | O7: Selected attributes preserved. | P7: Complex pipeline; evaluation on limited datasets. | Q7: attribute, GAN, measurable privacy | R7: No | T7: https://arxiv.org/abs/1904.12620 | U7: Search
A8: 4 | B8: hukkelas2019 | C8: DeepPrivacy: A Generative Adversarial Network for Face Anonymization | D8: Håkon Hukkelås, Rudolf Mester, Frank Lindseth | E8: 2019 | F8: ISVC | G8: Vision | H8: De-identification (generative) | I8: Generative de-identification | J8: FDF (Flickr Diverse Faces, 1.47M faces) | K8: Progressive-growing conditional GAN | L8: Conditional GAN that never sees the original face: it generates a new face from seven sparse keypoints and the surrounding background. | M8: By design no identity information reaches the generator; produced realistic 128×128 faces with a small drop in detection performance on anonymised data. | N8: Any identity inference from the face region. | O8: Pose via keypoints, scene context. | P8: Low resolution; keypoints and background can leak a little identity; expression not preserved. | Q8: GAN, keypoints, inpainting | R8: Yes | S8: https://github.com/hukkelas/DeepPrivacy | T8: https://arxiv.org/abs/1909.04538 | U8: Search
A9: 5 | B9: croft2019 | C9: Differentially Private Obfuscation of Facial Images | D9: William Croft, Jörg-Rüdiger Sack, Wei Shi | E9: 2019 | F9: CD-MAKE (Springer LNCS) | G9: Security | H9: Differential privacy | I9: Obfuscation & differential privacy | J9: LFW | K9: Metric-DP mechanism | L9: Applies a metric-privacy variant of DP to face images so that faces within a distance are indistinguishable. | M9: Formal indistinguishability with more visual utility than pixel-level DP. | N9: Re-identification from released face images. | O9: Moderate. | P9: Distance metric choice defines the guarantee. | Q9: metric privacy, facial obfuscation | R9: No | T9: https://doi.org/10.1007/978-3-030-29726-8_15 | U9: Search
A10: 6 | B10: grother2019 | C10: Face Recognition Vendor Test Part 3: Demographic Effects | D10: Patrick Grother, Mei Ngan, Kayee Hanaoka | E10: 2019 | F10: NIST Interagency Report 8280 | G10: Other | H10: Surveys, audits & society | I10: Surveys & society | J10: US government mugshot, visa and border image sets | K10: 189 submitted algorithms | L10: Evaluates 189 algorithms for false-positive and false-negative differentials across sex, age and race using government image sets. | M10: False-positive rates 10 to 100 times higher for some demographic groups in many algorithms; the most accurate algorithms showed the smallest differentials. | N10: Misidentification harm from deployed systems. | O10: Not applicable. | P10: Image sets are US government collections. | Q10: NIST, demographics, false positives | R10: No | T10: https://doi.org/10.6028/NIST.IR.8280 | U10: Search
A11: 7 | B11: mirjalili2019 | C11: FlowSAN: Privacy-Enhancing Semi-Adversarial Networks to Confound Arbitrary Face-Based Gender Classifiers | D11: Vahid Mirjalili, Sebastian Raschka, Arun Ross | E11: 2019 | F11: IEEE Access | G11: Journal | H11: Soft-biometric privacy | I11: Soft-biometric privacy | J11: CelebA, MORPH, LFW, MUCT, RaFD | K11: Autoencoder ensemble; VGG-Face matcher; gender CNNs | L11: Stacks several semi-adversarial networks trained against diverse gender classifiers so the perturbation generalises to unseen ones. | M11: Confounded arbitrary gender classifiers better than a single SAN while keeping matching. | N11: Unknown gender classifiers on shared images. | O11: Identity matching. | P11: Perturbations accumulate visible artefacts. | Q11: SAN, ensemble, generalisation | R11: No | T11: https://doi.org/10.1109/ACCESS.2019.2924619 | U11: Search
A12: 8 | B12: gafni2019 | C12: Live Face De-Identification in Video | D12: Oran Gafni, Lior Wolf, Yaniv Taigman | E12: 2019 | F12: ICCV | G12: Vision | H12: De-identification (generative) | I12: Generative de-identification | J12: LFW, VGGFace2 videos, FaceForensics | K12: Encoder-decoder with identity network; ArcFace and FaceNet for evaluation | L12: Feed-forward encoder-decoder that pushes the identity embedding away from the original while preserving pose, expression and lighting, frame by frame in real time. | M12: Real-time de-identified video judged natural by humans; recognition rates fell to near chance for the tested networks. | N12: Automated face recognition on video. | O12: Expression, pose, lip movement. | P12: No formal guarantee; trained against specific recognisers. | Q12: video, feed-forward, expression | R12: No | T12: https://arxiv.org/abs/1911.08348 | U12: Search
A13: 9 | B13: mai2019 | C13: On the Reconstruction of Face Images from Deep Face Templates | D13: Guangcan Mai, Kai Cao, Pong C. Yuen, Anil K. Jain | E13: 2019 | F13: IEEE TPAMI | G13: Journal | H13: Attacks & evaluations | I13: Attacks & evaluations | J13: VGG-Face, Multi-PIE (train); LFW, FRGCv2, color-FERET | K13: FaceNet templates; NbNet inverter | L13: Neighbourly de-convolutional network (NbNet) trained on real and synthesised faces to invert deep templates. | M13: Reconstructions accepted as the genuine user 95.20% of the time at FAR 0.1% on LFW (type-I attack); templates are not safe to store in the clear. | N13: Attacker with stolen templates and black-box matcher access. | O13: Not applicable. | P13: Trained against specific feature extractors; later GAN and diffusion inverters are stronger. | Q13: NbNet, template inversion, type-I attack | R13: No | T13: https://arxiv.org/abs/1703.00832 | U13: Search
A14: 10 | B14: jordon2019 | C14: PATE-GAN: Generating Synthetic Data with Differential Privacy Guarantees | D14: James Jordon, Jinsung Yoon, Mihaela van der Schaar | E14: 2019 | F14: ICLR | G14: ML | H14: Differential privacy | I14: Obfuscation & differential privacy | J14: Kaggle credit, MAGGIC, UCI, MNIST | K14: GAN with PATE discriminator | L14: Uses the PATE teacher-ensemble mechanism as the GAN discriminator so the generator's training is differentially private. | M14: Better utility than DPGAN at the same budget on tabular and image data. | N14: Leakage of training samples through a generator. | O14: Synthetic data utility. | P14: Teacher ensemble cost; limited image quality. | Q14: PATE, synthetic data, teacher ensemble | R14: No | T14: https://openreview.net/forum?id=S1zk9iRqF7 | U14: Search
A15: 11 | B15: fan2019 | C15: Practical Image Obfuscation with Provable Privacy | D15: Liyue Fan | E15: 2019 | F15: IEEE ICME | G15: Vision | H15: Differential privacy | I15: Obfuscation & differential privacy | J15: AT&T faces and other image sets | K15: SVD perturbation | L15: Extends DP pixelization with SVD-based perturbation to keep more structure under the same privacy budget. | M15: Better utility than DP-Pix at matched epsilon on face and other images. | N15: Inference from released images with a formal bound. | O15: Moderate visual utility. | P15: Guarantee still tied to a small pixel neighbourhood. | Q15: DP-SVD, pixelization, provable | R15: No | T15: https://doi.org/10.1109/ICME.2019.00140 | U15: Search
A16: 12 | B16: terhorst2019 | C16: Suppressing Gender and Age in Face Templates Using Incremental Variable Elimination | D16: Philipp Terhörst, Naser Damer, Florian Kirchbuchner, Arjan Kuijper | E16: 2019 | F16: ICB | G16: Biometrics | H16: Soft-biometric privacy | I16: Soft-biometric privacy | J16: ColorFeret, Adience, LFW | K16: FaceNet templates | L16: Iteratively removes template dimensions most predictive of gender and age while monitoring recognition. | M16: Attribute prediction reduced substantially at small recognition cost, working on the template rather than the image. | N16: Attribute inference from stored templates. | O16: Recognition accuracy. | P16: Linear view of attributes; later attacks recover them. | Q16: template level, feature elimination | R16: No | T16: https://doi.org/10.1109/ICB45695.2019.8987331 | U16: Search

Sheet 2020
A1: 2020
A2: 19 entries published or first released in 2020.
A4: # | B4: ID | C4: Paper title | D4: Authors | E4: Year | F4: Venue | G4: Venue type | H4: Family | I4: Chart group | J4: Datasets | K4: Models / backbones | L4: Approach | M4: Key findings | N4: Threat model / protects against | O4: Utility preserved | P4: Limitations & known attacks | Q4: Tags | R4: Code available | S4: GitHub / code link | T4: Paper link | U4: Google Scholar
A5: 1 | B5: deb2020 | C5: AdvFaces: Adversarial Face Synthesis | D5: Debayan Deb, Jianbang Zhang, Anil K. Jain | E5: 2020 | F5: IJCB | G5: Biometrics | H5: Adversarial privacy | I5: Adversarial & unlearnable | J5: CASIA-WebFace (train); LFW | K5: FaceNet, SphereFace, ArcFace, COTS matcher | L5: A GAN learns to synthesise minimal, image-specific perturbations in salient facial regions for obfuscation or impersonation. | M5: Reported 97.22% obfuscation success on LFW against a black-box matcher with high visual quality. | N5: Black-box recognisers, including COTS. | O5: Natural-looking images. | P5: Static perturbations; same future-model exposure. | Q5: GAN, minimal perturbation, obfuscation and impersonation | R5: No | T5: https://arxiv.org/abs/1908.05008 | U5: Search
A6: 2 | B6: komkov2020 | C6: AdvHat: Real-World Adversarial Attack on ArcFace Face ID System | D6: Stepan Komkov, Aleksandr Petiushko | E6: 2020 | F6: ICPR | G6: Vision | H6: Adversarial privacy | I6: Adversarial & unlearnable | J6: CASIA-WebFace; own photographs | K6: ArcFace (LResNet100E-IR) | L6: A printed rectangular sticker on a hat, optimised with off-plane transformations to remain adversarial when photographed. | M6: Reduced ArcFace similarity to the wearer's gallery image below the matching threshold in physical tests, and transferred partly to other models. | N6: Deep recognisers in the physical world. | O6: A hat with a patterned sticker. | P6: Single model targeted; conspicuous pattern. | Q6: physical, sticker, ArcFace | R6: Yes | S6: https://github.com/papermsucode/advhat | T6: https://arxiv.org/abs/1908.08705 | U6: Search
A7: 3 | B7: maximov2020 | C7: CIAGAN: Conditional Identity Anonymization Generative Adversarial Networks | D7: Maxim Maximov, Ismail Elezi, Laura Leal-Taixé | E7: 2020 | F7: CVPR | G7: Vision | H7: De-identification (generative) | I7: Generative de-identification | J7: CelebA, MOTS, LFW | K7: Landmark-conditioned GAN; FaceNet for evaluation | L7: Conditions a GAN on landmarks, a masked face and a one-hot identity code so the new identity is chosen, not random, and stays consistent across video frames. | M7: Removed identity from images and video while keeping pose and detectability; identity control allowed consistent anonymisation across frames. | N7: Face recognition in images and video. | O7: Detection, tracking, pose. | P7: Landmark leakage; limited resolution; expression fidelity modest. | Q7: GAN, landmarks, controllable identity | R7: Yes | S7: https://github.com/dvl-tum/ciagan | T7: https://arxiv.org/abs/2005.09544 | U7: Search
A8: 4 | B8: kolberg2020 | C8: Efficiency Analysis of Post-Quantum-Secure Face Template Protection Schemes Based on Homomorphic Encryption | D8: Jascha Kolberg, Pawel Drozdowski, Marta Gomez-Barrero, Christian Rathgeb, Christoph Busch | E8: 2020 | F8: BIOSIG | G8: Biometrics | H8: Identity protection: templates & encrypted matching | I8: Template protection | J8: FERET, FRGCv2 | K8: ArcFace; BFV/CKKS-style HE | L8: Compares lattice-based HE schemes for protecting deep face templates in verification and identification. | M8: Post-quantum HE feasible for verification; identification remains costly. | N8: Template theft, including by quantum-capable adversaries. | O8: Verification accuracy unchanged. | P8: Latency for large galleries. | Q8: homomorphic encryption, post-quantum, efficiency | R8: No | T8: https://ieeexplore.ieee.org/document/9210976 | U8: Search
A9: 5 | B9: golatkar2020a | C9: Eternal Sunshine of the Spotless Net: Selective Forgetting in Deep Networks | D9: Aditya Golatkar, Alessandro Achille, Stefano Soatto | E9: 2020 | F9: CVPR | G9: Vision | H9: Machine unlearning & auditing | I9: Training data & unlearning | J9: MNIST, CIFAR-10, Lacuna-10/100 (VGGFace2 faces) | K9: ResNet-18, All-CNN | L9: Scrubs information about a subset of training data from network weights using a Fisher-information-based noise, with an information-theoretic bound on what remains. | M9: Forgot classes of faces (Lacuna, from VGGFace2) with residual information bounded, without full retraining. | N9: Identities that must be removed from a trained recogniser. | O9: Accuracy on retained classes. | P9: Approximate; bounds are loose for large forget sets. | Q9: selective forgetting, Fisher noise, faces | R9: Yes | S9: https://github.com/AdityaGolatkar/SelectiveForgetting | T9: https://arxiv.org/abs/1911.04933 | U9: Search
A10: 6 | B10: learnedmiller2020 | C10: Facial Recognition Technologies in the Wild: A Call for a Federal Office | D10: Erik Learned-Miller, Vicente Ordóñez, Jamie Morgenstern, Joy Buolamwini | E10: 2020 | F10: Algorithmic Justice League white paper | G10: Other | H10: Surveys, audits & society | I10: Surveys & society | J10: None | K10: None | L10: Proposes an FDA-style federal office to approve and audit face recognition deployments, with an accompanying primer on the technology. | M10: Framed regulation as pre-market approval rather than after-the-fact litigation; widely cited in US policy debates. | N10: Unregulated deployment. | O10: Not applicable. | P10: US-centric proposal. | Q10: policy, regulation, primer | R10: No | T10: https://www.ajl.org/federal-office-call | U10: Search
A11: 7 | B11: shan2020 | C11: Fawkes: Protecting Privacy against Unauthorized Deep Learning Models | D11: Shawn Shan, Emily Wenger, Jiayun Zhang, Huiying Li, Haitao Zheng, Ben Y. Zhao | E11: 2020 | F11: USENIX Security | G11: Security | H11: Adversarial privacy | I11: Adversarial & unlearnable | J11: PubFig, FaceScrub, WebFace | K11: VGG2-Dense and WebFace-Dense feature extractors; Microsoft Azure Face, Amazon Rekognition, Face++ | L11: Cloaking: add imperceptible perturbations to photos before posting so that a model trained on them learns a wrong feature representation of the user. | M11: Reported over 95% protection against models including Microsoft Azure Face, Amazon Rekognition and Face++ trained on cloaked images; the tool was downloaded more than 500,000 times. | N11: Unauthorised recognisers trained by scraping the user's photos. | O11: Photos look unchanged to people. | P11: Broken as a durable defense by Radiya-Dixit et al. (ICLR 2022): protection fails against future or adaptive models. Does nothing against cameras. | Q11: cloaking, data poisoning, Clearview | R11: Yes | S11: https://github.com/Shawn-Shan/fawkes | T11: https://arxiv.org/abs/2002.08327 | U11: Search
A12: 8 | B12: golatkar2020b | C12: Forgetting Outside the Box: Scrubbing Deep Networks of Information Accessible from Input-Output Observations | D12: Aditya Golatkar, Alessandro Achille, Stefano Soatto | E12: 2020 | F12: ECCV | G12: Vision | H12: Machine unlearning & auditing | I12: Training data & unlearning | J12: Lacuna-10/100, CIFAR-10 | K12: ResNet-18, All-CNN | L12: Extends scrubbing to information recoverable from input-output behaviour using a linearised (NTK) approximation of training. | M12: Forgetting measured on the function, not just weights, on face and object benchmarks. | N12: Identity leakage through model outputs after deletion requests. | O12: Retained accuracy. | P12: Linearisation assumptions. | Q12: black-box forgetting, NTK, faces | R12: Yes | S12: https://github.com/AdityaGolatkar/SelectiveForgetting | T12: https://arxiv.org/abs/2003.02960 | U12: Search
A13: 9 | B13: huang2020 | C13: InstaHide: Instance-hiding Schemes for Private Distributed Learning | D13: Yangsibo Huang, Zhao Song, Kai Li, Sanjeev Arora | E13: 2020 | F13: ICML | G13: ML | H13: Training-data privacy & synthetic data | I13: Training data & unlearning | J13: CIFAR-10, CIFAR-100, ImageNet | K13: ResNet-18 | L13: Encodes each training image by mixing it with random public images and flipping pixel signs before training. | M13: Claimed practical privacy at little accuracy cost; a public challenge was broken within months. | N13: Anyone seeing encoded training data. | O13: Training accuracy. | P13: Broken by Carlini et al. (S&P 2021), who recovered the challenge images. | Q13: instance encoding, mixup, broken | R13: Yes | S13: https://github.com/Hazelsuko07/InstaHide | T13: https://arxiv.org/abs/2010.02772 | U13: Search
A14: 10 | B14: bortolato2020 | C14: Learning Privacy-Enhancing Face Representations Through Feature Disentanglement | D14: Blaž Bortolato, Marija Ivanovska, Peter Rot, Janez Križaj, Philipp Terhörst, Naser Damer, Peter Peer, Vitomir Štruc | E14: 2020 | F14: IEEE FG | G14: Biometrics | H14: Soft-biometric privacy | I14: Soft-biometric privacy | J14: CelebA, LFW | K14: ArcFace/VGGFace2 representations | L14: Autoencoder that splits a representation into identity and attribute parts and discards the attribute part. | M14: Reduced gender predictability from representations with limited recognition impact. | N14: Attribute inference from representations. | O14: Recognition. | P14: Disentanglement is imperfect; residual leakage. | Q14: disentanglement, representation | R14: No | T14: https://doi.org/10.1109/FG47880.2020.00007 | U14: Search
A15: 11 | B15: ngan2020 | C15: Ongoing Face Recognition Vendor Test Part 6B: Face Recognition Accuracy with Face Masks Using Post-COVID-19 Algorithms | D15: Mei Ngan, Patrick Grother, Kayee Hanaoka | E15: 2020 | F15: NIST Interagency Report 8331 | G15: Other | H15: Surveys, audits & society | I15: Surveys & society | J15: Digitally masked government image sets | K15: Post-pandemic submitted algorithms | L15: Tests algorithms submitted after the pandemic began on digitally masked faces. | M15: Error rates for masked faces fell sharply compared with pre-pandemic algorithms as vendors retrained, though masks still raised errors. | N15: Not applicable. | O15: Not applicable. | P15: Digital masks rather than real ones. | Q15: masks, NIST, occlusion | R15: No | T15: https://doi.org/10.6028/NIST.IR.8331 | U15: Search
A16: 12 | B16: terhorst2020 | C16: PE-MIU: A Training-Free Privacy-Enhancing Face Recognition Approach Based on Minimum Information Units | D16: Philipp Terhörst, Kevin Riehl, Naser Damer, Peter Rot, Blaz Bortolato, Florian Kirchbuchner, Vitomir Štruc, Arjan Kuijper | E16: 2020 | F16: IEEE Access | G16: Journal | H16: Soft-biometric privacy | I16: Soft-biometric privacy | J16: ColorFeret, Adience, LFW | K16: FaceNet templates | L16: Splits templates into minimum information units and shuffles them so attribute classifiers lose structure while matching uses block-wise comparison. | M16: Training-free suppression of several attributes with little recognition loss. | N16: Attribute inference from templates. | O16: Recognition accuracy. | P16: Vulnerable to the black-box attribute attack of Osorio-Roig et al. | Q16: training-free, template, shuffling | R16: No | T16: https://doi.org/10.1109/ACCESS.2020.2994960 | U16: Search
A17: 13 | B17: gu2020 | C17: Password-Conditioned Anonymization and Deanonymization with Face Identity Transformers | D17: Xiuye Gu, Weixin Luo, Michael S. Ryoo, Yong Jae Lee | E17: 2020 | F17: ECCV | G17: Vision | H17: De-identification (generative) | I17: Generative de-identification | J17: CASIA-WebFace, LFW, FFHQ | K17: Face identity transformer (GAN); FaceNet for evaluation | L17: A face identity transformer conditioned on a password: the correct password recovers the original, any wrong password yields a different, still anonymous face. | M17: First reversible generative de-identification with a secret; wrong passwords do not reveal the original. | N17: Unauthorised viewers of stored images. | O17: Full recovery for the key holder. | P17: Security rests on the network, not on cryptography; not analysed against inversion attacks. | Q17: reversible, password, GAN | R17: Yes | S17: https://github.com/laoreja/face-identity-transformer | T17: https://arxiv.org/abs/1911.11759 | U17: Search
A18: 14 | B18: terhorst2020proto | C18: Privacy Evaluation Protocols for the Evaluation of Soft-Biometric Privacy-Enhancing Technologies | D18: Philipp Terhörst, Marco Huber, Naser Damer, Peter Rot, Florian Kirchbuchner, Vitomir Štruc, Arjan Kuijper | E18: 2020 | F18: BIOSIG | G18: Biometrics | H18: Soft-biometric privacy | I18: Soft-biometric privacy | J18: ColorFeret, Adience, LFW | K18: Several privacy enhancers and attribute classifiers | L18: Proposes evaluation protocols that test privacy against unknown attribute classifiers, not the ones used in training. | M18: Showed that many soft-biometric privacy methods overstated protection when tested only on training-time classifiers. | N18: Not applicable: evaluation. | O18: Not applicable. | P18: Protocol paper. | Q18: evaluation protocol, soft biometrics | R18: No | T18: https://ieeexplore.ieee.org/document/9211021 | U18: Search
A19: 15 | B19: chamikara2020 | C19: Privacy Preserving Face Recognition Utilizing Differential Privacy | D19: M.A.P. Chamikara, P. Bertok, I. Khalil, D. Liu, S. Camtepe | E19: 2020 | F19: Computers & Security | G19: Journal | H19: Differential privacy | I19: Obfuscation & differential privacy | J19: LFW, ORL, Yale | K19: Eigenfaces with local DP | L19: PEEP applies local differential privacy to Eigenface projections before they leave the device. | M19: Formal privacy with modest recognition loss on classic benchmarks. | N19: Server or eavesdropper inferring faces from transmitted features. | O19: Recognition accuracy (Eigenface-level). | P19: Eigenfaces are weak; DP noise costs accuracy on deep features. | Q19: PEEP, local differential privacy, Eigenfaces | R19: No | T19: https://doi.org/10.1016/j.cose.2020.101951 | U19: Search
A20: 16 | B20: mirjalili2020 | C20: PrivacyNet: Semi-Adversarial Networks for Multi-Attribute Face Privacy | D20: Vahid Mirjalili, Sebastian Raschka, Arun Ross | E20: 2020 | F20: IEEE TIP | G20: Journal | H20: Soft-biometric privacy | I20: Soft-biometric privacy | J20: CelebA, MORPH, MUCT, RaFD, UTKFace | K20: GAN; commercial matcher; attribute CNNs | L20: GAN-based semi-adversarial network that lets the user choose which attributes (age, race, gender) to obfuscate while keeping others and identity. | M20: Selective, multi-attribute obfuscation with preserved matching. | N20: Attribute classifiers on shared images. | O20: Identity matching and chosen attributes. | P20: Attribute recovery by adaptive attackers. | Q20: multi-attribute, GAN, selective | R20: No | T20: https://arxiv.org/abs/2001.00561 | U20: Search
A21: 17 | B21: hill2020 | C21: The Secretive Company That Might End Privacy as We Know It | D21: Kashmir Hill | E21: 2020 | F21: The New York Times (investigative journalism) | G21: Other | H21: Surveys, audits & society | I21: Surveys & society | J21: None | K21: Clearview AI | L21: Investigation revealing Clearview AI's face search engine built from more than three billion scraped photos and sold to police. | M21: Triggered lawsuits, regulator fines on three continents, platform cease-and-desist letters and much of the anti-scraping research that followed. | N21: Mass scraping for identification. | O21: Not applicable. | P21: Journalism, not peer review. | Q21: Clearview AI, scraping, journalism | R21: No | T21: https://www.nytimes.com/2020/01/18/technology/clearview-privacy-facial-recognition.html | U21: Search
A22: 18 | B22: terhorst2020neg | C22: Unsupervised Enhancement of Soft-Biometric Privacy with Negative Face Recognition | D22: Philipp Terhörst, Marco Huber, Naser Damer, Florian Kirchbuchner, Arjan Kuijper | E22: 2020 | F22: arXiv preprint | G22: Preprint | H22: Soft-biometric privacy | I22: Soft-biometric privacy | J22: ColorFeret, Adience, LFW | K22: FaceNet templates | L22: Stores what a face is not (a negative template) so matching works via dissimilarity while attribute classifiers lose their signal. | M22: Attribute suppression without attribute labels at small recognition cost. | N22: Attribute inference from templates. | O22: Recognition. | P22: Preprint; attacked by Osorio-Roig et al. | Q22: negative recognition, template, unsupervised | R22: No | T22: https://arxiv.org/abs/2002.09181 | U22: Search
A23: 19 | B23: duong2020 | C23: Vec2Face: Unveil Human Faces from their Blackbox Features in Face Recognition | D23: Chi Nhan Duong, Thanh-Dat Truong, Khoa Luu, Kha Gia Quach, Hung Bui, Kaushik Roy | E23: 2020 | F23: CVPR | G23: Vision | H23: Attacks & evaluations | I23: Attacks & evaluations | J23: CASIA-WebFace; LFW, CFP-FP, AgeDB | K23: ArcFace (black-box); DiBiGAN | L23: DiBiGAN: a bijection-based generative model that reconstructs faces from black-box features using distillation. | M23: Realistic, recognisable reconstructions from black-box embeddings without model access. | N23: Attacker with embeddings and only API access to the extractor. | O23: Not applicable. | P23: Quality depends on distillation data. | Q23: template inversion, black-box, GAN | R23: No | T23: https://arxiv.org/abs/2003.06958 | U23: Search

Sheet 2021
A1: 2021
A2: 27 entries published or first released in 2021.
A4: # | B4: ID | C4: Paper title | D4: Authors | E4: Year | F4: Venue | G4: Venue type | H4: Family | I4: Chart group | J4: Datasets | K4: Models / backbones | L4: Approach | M4: Key findings | N4: Threat model / protects against | O4: Utility preserved | P4: Limitations & known attacks | Q4: Tags | R4: Code available | S4: GitHub / code link | T4: Paper link | U4: Google Scholar
A5: 1 | B5: raji2021 | C5: About Face: A Survey of Facial Recognition Evaluation | D5: Inioluwa Deborah Raji, Genevieve Fried | E5: 2021 | F5: arXiv preprint (AAAI 2020 workshop) | G5: Preprint | H5: Surveys, audits & society | I5: Surveys & society | J5: 130+ face datasets reviewed | K5: None | L5: Reviews over 100 face datasets from 1976 to 2019 and how evaluation practice shifted from consented lab data to scraped web data. | M5: Traced the move to web scraping to the demands of deep learning, and the collapse of consent as a norm. | N5: Not applicable. | O5: Not applicable. | P5: Descriptive. | Q5: datasets, evaluation, history | R5: No | T5: https://arxiv.org/abs/2102.00813 | U5: Search
A6: 2 | B6: yin2021 | C6: Adv-Makeup: A New Imperceptible and Transferable Attack on Face Recognition | D6: Bangjie Yin, Wenxuan Wang, Taiping Yao, Junfeng Guo, Zelun Kong, Shouhong Ding, Jilin Li, Cong Liu | E6: 2021 | F6: IJCAI | G6: ML | H6: Adversarial privacy | I6: Adversarial & unlearnable | J6: LFW, CelebA-HQ | K6: IR152, IRSE50, FaceNet, MobileFace | L6: Synthesises adversarial eye-shadow makeup with a blending module and meta-learning across models for transferability. | M6: Impersonation transferred to unseen models and worked when physically applied. | N6: Black-box recognisers, physical and digital. | O6: Looks like makeup. | P6: Region-limited; impersonation framing rather than privacy. | Q6: makeup, eye shadow, physical | R6: Yes | S6: https://github.com/TencentYoutuResearch/Adv-Makeup | T6: https://arxiv.org/abs/2105.03162 | U6: Search
A7: 3 | B7: fowl2021 | C7: Adversarial Examples Make Strong Poisons | D7: Liam Fowl, Micah Goldblum, Ping-yeh Chiang, Jonas Geiping, Wojciech Czaja, Tom Goldstein | E7: 2021 | F7: NeurIPS | G7: ML | H7: Unlearnable images & anti-customisation | I7: Adversarial & unlearnable | J7: CIFAR-10, ImageNet | K7: ResNet-18, VGG, MobileNet | L7: Shows that ordinary adversarial examples, especially class-targeted ones, are strong availability poisons when used as training data. | M7: Training on adversarially perturbed data reduced clean accuracy more than prior poisoning methods on CIFAR-10 and ImageNet. | N7: Unauthorised training on released data. | O7: Small perturbations. | P7: Same fragility to adversarial training and purification as other availability poisons. | Q7: availability poisoning, adversarial examples, targeted | R7: Yes | S7: https://github.com/lhfowl/adversarial_poisons | T7: https://arxiv.org/abs/2106.10807 | U7: Search
A8: 4 | B8: liu2021dpimage | C8: DP-Image: Differential Privacy for Image Data in Feature Space | D8: Bo Liu, Ming Ding, Hanyu Xue, Tianqing Zhu, Dayong Ye, Li Song, Wanlei Zhou | E8: 2021 | F8: arXiv preprint | G8: Preprint | H8: Differential privacy | I8: Obfuscation & differential privacy | J8: CelebA, LFW | K8: GAN inversion and generator | L8: Defines DP over image feature vectors, perturbs them and reconstructs through a generator so the guarantee applies to semantic content. | M8: Photo-realistic DP images with tunable identity protection, unlike pixel-level DP. | N8: Identity inference from released images. | O8: High visual quality. | P8: Guarantee lives in feature space; preprint. | Q8: feature-space DP, GAN inversion | R8: No | T8: https://arxiv.org/abs/2103.07073 | U8: Search
A9: 5 | B9: harvey2021 | C9: Exposing.ai (MegaPixels): Face Datasets and Their Provenance | D9: Adam Harvey, Jules LaPlace | E9: 2021 | F9: Investigative research project | G9: Other | H9: Surveys, audits & society | I9: Surveys & society | J9: MS-Celeb-1M, MegaFace, Duke MTMC, Brainwash, others | K9: None | L9: Traces the origins and downstream uses of face datasets built from Flickr, CCTV and scraped photos, and lets people check whether their Flickr photos were used. | M9: Led directly to the withdrawal of MS-Celeb-1M, Duke MTMC and Brainwash and to a public debate on consent in face research. | N9: Non-consensual inclusion in training data. | O9: Not applicable. | P9: Coverage limited to datasets with traceable sources. | Q9: datasets, provenance, takedowns | R9: No | T9: https://exposing.ai | U9: Search
A10: 6 | B10: chandrasekaran2021 | C10: Face-Off: Adversarial Face Obfuscation | D10: Varun Chandrasekaran, Chuhan Gao, Brian Tang, Kassem Fawaz, Somesh Jha, Suman Banerjee | E10: 2021 | F10: PoPETs | G10: Security | H10: Adversarial privacy | I10: Adversarial & unlearnable | J10: VGGFace2, LFW | K10: FaceNet, VGG-Face; Azure, Rekognition, Face++ | L10: Metric-space adversarial perturbations against face embeddings, transferred to commercial APIs, with a user study on perceptibility. | M10: Defeated Azure, AWS Rekognition and Face++ matching at perturbation levels users found acceptable. | N10: Commercial face recognition services. | O10: User-rated acceptability. | P10: Static perturbations; subject to the same future-model problem as cloaks. | Q10: commercial APIs, user study, perturbation | R10: Yes | S10: https://github.com/wi-pi/face-off | T10: https://doi.org/10.2478/popets-2021-0032 | U10: Search
A11: 7 | B11: aggarwal2021 | C11: FedFace: Collaborative Learning of Face Recognition Model | D11: Divyansh Aggarwal, Jiayu Zhou, Anil K. Jain | E11: 2021 | F11: IJCB | G11: Biometrics | H11: Training-data privacy & synthetic data | I11: Training data & unlearning | J11: CASIA-WebFace (pretrain); simulated clients; LFW, IJB-A | K11: CosFace/ArcFace ResNet | L11: Federated training where each client holds only its owner's face images; a spread-out regulariser keeps class embeddings separated without sharing them. | M11: Improved a pretrained recogniser using thousands of clients without any face image leaving a device. | N11: Central collection of face images for training. | O11: Recognition accuracy gains. | P11: Gradient leakage not fully analysed; slow convergence. | Q11: federated learning, one identity per client | R11: No | T11: https://arxiv.org/abs/2104.03008 | U11: Search
A12: 8 | B12: evtimov2021 | C12: FoggySight: A Scheme for Facial Lookup Privacy | D12: Ivan Evtimov, Pascal Sturmfels, Tadayoshi Kohno | E12: 2021 | F12: PoPETs | G12: Security | H12: Adversarial privacy | I12: Adversarial & unlearnable | J12: VGGFace2, FaceScrub | K12: FaceNet | L12: Community protection: volunteers upload decoy photos crafted to sit near a protected person's embedding, so lookups return decoys instead of the person. | M12: Protected users even when their own photos were unmodified, by crowding the search space. | N12: Face search engines built from scraped photos. | O12: Users' own photos untouched. | P12: Needs many cooperating protectors; search engines can filter decoys. | Q12: decoys, community, lookup privacy | R12: Yes | S12: https://github.com/evtimovi/foggysight | T12: https://doi.org/10.2478/popets-2021-0044 | U12: Search
A13: 9 | B13: li2021mm | C13: Identity-Preserving Face Anonymization via Adaptively Facial Attributes Obfuscation | D13: Jingzhi Li, Lutong Han, Ruoyu Chen, Hua Zhang, Bing Han, Lili Wang, Xiaochun Cao | E13: 2021 | F13: ACM Multimedia | G13: Vision | H13: De-identification (generative) | I13: Generative de-identification | J13: CelebA, LFW | K13: Attribute-conditioned GAN; ArcFace for evaluation | L13: Adaptively obfuscates the facial attributes most relevant to identity while keeping the visual identity-independent attributes and detectability. | M13: Anonymised faces stayed natural and useful for detection while recognisers failed. | N13: Automated recognition on shared images. | O13: Detectability and non-identity attributes. | P13: Attribute-level control leaks under adaptive recognisers. | Q13: attribute obfuscation, identity-preserving, adaptive | R13: No | T13: https://doi.org/10.1145/3474085.3475367 | U13: Search
A14: 10 | B14: xiao2021 | C14: Improving Transferability of Adversarial Patches on Face Recognition with Generative Models | D14: Zihao Xiao, Xianfeng Gao, Chilin Fu, Yinpeng Dong, Wei Gao, Xiaolu Zhang, Jun Zhou, Jun Zhu | E14: 2021 | F14: CVPR | G14: Vision | H14: Adversarial privacy | I14: Adversarial & unlearnable | J14: LFW, CelebA-HQ | K14: ArcFace, CosFace, FaceNet; commercial APIs | L14: Optimises adversarial eyeglass patches on the manifold of a pretrained generator so they transfer to unseen recognisers. | M14: Higher black-box transfer against commercial APIs than pixel-space patches; physically realisable. | N14: Black-box and physical recognisers. | O14: Eyeglass-shaped patch. | P14: Conspicuous accessory. | Q14: adversarial patch, transferability, GAN manifold | R14: No | T14: https://arxiv.org/abs/2106.15058 | U14: Search
A15: 11 | B15: kim2021ironmask | C15: IronMask: Modular Architecture for Protecting Deep Face Template | D15: Sunpill Kim, Yunseong Jeong, Jinsu Kim, Jungkon Kim, Hyung Tae Lee, Jae Hong Seo | E15: 2021 | F15: CVPR | G15: Vision | H15: Identity protection: templates & encrypted matching | I15: Template protection | J15: LFW, CFP-FP, AgeDB | K15: ArcFace, CosFace | L15: A modular template protection built on a new fuzzy commitment for real-valued vectors on a hypersphere, matching the geometry of angular-margin face embeddings. | M15: Template protection for ArcFace and CosFace with small accuracy loss and formal security analysis. | N15: Template theft. | O15: Verification accuracy near baseline. | P15: A 2024 probabilistic linear-regression attack showed weaknesses under repeated use. | Q15: real-valued templates, secure sketch, hypersphere | R15: No | T15: https://arxiv.org/abs/2104.02239 | U15: Search
A16: 12 | B16: carlini2021 | C16: Is Private Learning Possible with Instance Encoding? | D16: Nicholas Carlini, Samuel Deng, Sanjam Garg, Somesh Jha, Saeed Mahloujifar, Mohammad Mahmoody, Abhradeep Thakurta, Florian Tramèr | E16: 2021 | F16: IEEE Symposium on Security and Privacy | G16: Security | H16: Attacks & evaluations | I16: Attacks & evaluations | J16: InstaHide challenge set (CIFAR-derived) | K16: InstaHide encodings | L16: Formal and practical attacks on instance-encoding schemes; recovers images from InstaHide's encoded challenge set. | M16: Recovered recognisable images from the InstaHide challenge; argued instance encoding cannot give meaningful privacy without accuracy loss. | N16: Anyone with encoded training data. | O16: Not applicable. | P16: Specific to encoding schemes, not to cryptographic protection. | Q16: InstaHide, instance encoding, break | R16: No | T16: https://arxiv.org/abs/2011.05315 | U16: Search
A17: 13 | B17: prabhu2021 | C17: Large Image Datasets: A Pyrrhic Win for Computer Vision? | D17: Vinay Uday Prabhu, Abeba Birhane | E17: 2021 | F17: WACV | G17: Vision | H17: Surveys, audits & society | I17: Surveys & society | J17: ImageNet, 80 Million Tiny Images | K17: None | L17: Audits ImageNet and related datasets for non-consensual, offensive and identifying content. | M17: Documented identifiable people and harmful labels; contributed to the blurring of faces in ImageNet and the withdrawal of several face datasets. | N17: Non-consensual inclusion in training data. | O17: Not applicable. | P17: Audit of a few datasets. | Q17: datasets, consent, ethics | R17: No | T17: https://arxiv.org/abs/2006.16923 | U17: Search
A18: 14 | B18: hinojosa2021 | C18: Learning Privacy-Preserving Optics for Human Pose Estimation | D18: Carlos Hinojosa, Juan Carlos Niebles, Henry Arguello | E18: 2021 | F18: ICCV | G18: Vision | H18: Blur, pixelation & obfuscation | I18: Obfuscation & differential privacy | J18: COCO, LSP (pose) | K18: Learned PSF + pose network | L18: Jointly optimises a lens's point spread function and a pose network so the captured image is unrecognisable but pose is recoverable. | M18: Pose estimation close to clean-image accuracy from images where face recognition and human identification fail; validated with a fabricated lens. | N18: Identification from captured images, including sensor compromise. | O18: Human pose. | P18: Task-specific optics; deblurring attacks partially recover images. | Q18: optics, end-to-end, pose estimation | R18: Yes | S18: https://github.com/carlosh93/privacy-optics-hpe | T18: https://openaccess.thecvf.com/content/ICCV2021/html/Hinojosa_Learning_Privacy-Preserving_Optics_for_Human_Pose_Estimation_ICCV_2021_paper.html | U18: Search
A19: 15 | B19: cherepanova2021 | C19: LowKey: Leveraging Adversarial Attacks to Protect Social Media Users from Facial Recognition | D19: Valeriia Cherepanova, Micah Goldblum, Harrison Foley, Shiyuan Duan, John Dickerson, Gavin Taylor, Tom Goldstein | E19: 2021 | F19: ICLR | G19: ML | H19: Adversarial privacy | I19: Adversarial & unlearnable | J19: FaceScrub, UMDFaces | K19: ArcFace/IR-152 ensemble; Amazon Rekognition, Microsoft Azure Face | L19: Feature-space adversarial perturbations optimised over an ensemble of recognisers with Gaussian smoothing so that gallery images fail to match probes. | M19: Sharply reduced identification by Amazon Rekognition and Microsoft Azure Face on protected galleries; released as a web tool. | N19: Commercial recognisers with the user's protected photos in their gallery. | O19: Small but visible perturbation at strong settings. | P19: Also broken by Radiya-Dixit et al.; perturbations are larger than Fawkes'. | Q19: cloaking, evasion, commercial APIs | R19: Yes | S19: https://lowkey.umiacs.umd.edu | T19: https://arxiv.org/abs/2101.07922 | U19: Search
A20: 16 | B20: bourtoule2021 | C20: Machine Unlearning | D20: Lucas Bourtoule, Varun Chandrasekaran, Christopher A. Choquette-Choo, Hengrui Jia, Adelin Travers, Baiwu Zhang, David Lie, Nicolas Papernot | E20: 2021 | F20: IEEE Symposium on Security and Privacy | G20: Security | H20: Machine unlearning & auditing | I20: Training data & unlearning | J20: Purchase, SVHN, MNIST, ImageNet, mini-ImageNet | K20: ResNet, small CNNs | L20: SISA training: shard and slice data, train constituent models, and retrain only the affected shard on a deletion request. | M20: Exact unlearning with large retraining savings; framed unlearning as a systems problem. | N20: Deletion requests against trained models. | O20: Accuracy cost from sharding. | P20: Storage and accuracy overhead; not applicable to already-trained monoliths. | Q20: SISA, exact unlearning, sharding | R20: Yes | S20: https://github.com/cleverhans-lab/machine-unlearning | T20: https://arxiv.org/abs/1912.03817 | U20: Search
A21: 17 | B21: croft2021 | C21: Obfuscation of Images via Differential Privacy: From Facial Images to General Images | D21: William Croft, Jörg-Rüdiger Sack, Wei Shi | E21: 2021 | F21: Peer-to-Peer Networking and Applications | G21: Journal | H21: Differential privacy | I21: Obfuscation & differential privacy | J21: LFW, general image sets | K21: Feature-space DP mechanism | L21: Generalises the metric-DP face obfuscation to arbitrary images with feature-space noise. | M21: A single DP mechanism usable across image types with a utility analysis. | N21: Inference from released images. | O21: Moderate. | P21: Utility degrades quickly at strong budgets. | Q21: differential privacy, general images | R21: No | T21: https://doi.org/10.1007/s12083-021-01091-9 | U21: Search
A22: 18 | B22: rajabi2021 | C22: On the (Im)Practicality of Adversarial Perturbation for Image Privacy | D22: Arezoo Rajabi, Rakesh B. Bobba, Mike Rosulek, Charles V. Wright, Wu-chi Feng | E22: 2021 | F22: PoPETs | G22: Security | H22: Adversarial privacy | I22: Adversarial & unlearnable | J22: VGGFace2, LFW | K22: VGG-Face, FaceNet ensembles | L22: Universal ensemble perturbations and k-randomised transparent image overlays, tested for robustness to compression and to adaptive recognisers. | M22: Perturbations robust enough to survive real pipelines become visible; small ones are removed by compression or adaptation. | N22: Automated recognition of uploaded photos. | O22: Trade-off measured explicitly. | P22: Argues that pixel-level privacy perturbation is impractical at scale. | Q22: universal perturbation, overlays, practicality | R22: No | T22: https://doi.org/10.2478/popets-2021-0006 | U22: Search
A23: 19 | B23: chen2021oriole | C23: Oriole: Thwarting Privacy Against Trustworthy Deep Learning Models | D23: Liuqiao Chen, Hu Wang, Benjamin Zi Hao Zhao, Minhui Xue, Haifeng Qian | E23: 2021 | F23: ACISP | G23: Security | H23: Attacks & evaluations | I23: Attacks & evaluations | J23: PubFig, FaceScrub | K23: Fawkes; VGG-Face-based extractors | L23: Trains a recogniser on multiple cloaked versions of the same images so the cloak's feature shift is learned and cancelled. | M23: Recognition of Fawkes-protected users restored, an early demonstration that cloaks fail against an aware trainer. | N23: Cloaked photos on the web. | O23: Not applicable. | P23: Needs multiple cloaked versions. | Q23: Fawkes, multi-cloak, break | R23: No | T23: https://arxiv.org/abs/2102.11502 | U23: Search
A24: 20 | B24: dhar2021 | C24: PASS: Protected Attribute Suppression System for Mitigating Bias in Face Recognition | D24: Prithviraj Dhar, Joshua Gleason, Aniket Roy, Carlos D. Castillo, Rama Chellappa | E24: 2021 | F24: ICCV | G24: Vision | H24: Soft-biometric privacy | I24: Soft-biometric privacy | J24: IJB-C, MORPH, CelebA | K24: ArcFace, Crystalface descriptors | L24: Trains a lightweight network on top of frozen face descriptors to remove gender or skin-tone information while keeping identity. | M24: Reduced attribute predictability from descriptors and narrowed demographic accuracy gaps. | N24: Attribute inference and biased use of descriptors. | O24: Recognition. | P24: Suppression measured against specific classifiers. | Q24: attribute suppression, fairness, descriptor | R24: No | T24: https://arxiv.org/abs/2108.03764 | U24: Search
A25: 21 | B25: cao2021 | C25: Personalized and Invertible Face De-identification by Disentangled Identity Information Manipulation | D25: Jingyi Cao, Bo Liu, Yunqian Wen, Rong Xie, Li Song | E25: 2021 | F25: ICCV | G25: Vision | H25: De-identification (generative) | I25: Generative de-identification | J25: CelebA-HQ, LFW | K25: Disentangled identity encoder; ArcFace for evaluation | L25: Disentangles identity from attributes, perturbs the identity vector with a user-specific key and reconstructs; inverse manipulation restores the face. | M25: Controllable degree of de-identification and exact recovery with the key, at higher visual quality than earlier reversible methods. | N25: Unauthorised recognition of stored or shared images. | O25: Attributes and expression; recovery for key holder. | P25: Key management outside the model; not cryptographically analysed. | Q25: reversible, disentanglement, controllable | R25: No | T25: https://openaccess.thecvf.com/content/ICCV2021/html/Cao_Personalized_and_Invertible_Face_De-Identification_by_Disentangled_Identity_Information_Manipulation_ICCV_2021_paper.html | U25: Search
A26: 22 | B26: meden2021 | C26: Privacy-Enhancing Face Biometrics: A Comprehensive Survey | D26: Blaž Meden, Peter Rot, Philipp Terhörst, Naser Damer, Arjan Kuijper, Walter J. Scheirer, Arun Ross, Peter Peer, Vitomir Štruc | E26: 2021 | F26: IEEE TIFS | G26: Journal | H26: Surveys, audits & society | I26: Surveys & society | J26: Survey (200+ references) | K26: Survey | L26: Taxonomy of privacy-enhancing face techniques by what is protected (identity, soft biometrics) and where (image, representation, inference level), over more than 200 references. | M26: The standard reference survey; also catalogued the lack of shared evaluation protocols. | N26: Not applicable. | O26: Not applicable. | P26: Pre-diffusion. | Q26: survey, taxonomy, 200+ references | R26: No | T26: https://doi.org/10.1109/TIFS.2021.3096024 | U26: Search
A27: 23 | B27: morales2021 | C27: SensitiveNets: Learning Agnostic Representations with Application to Face Images | D27: Aythami Morales, Julian Fierrez, Ruben Vera-Rodriguez, Ruben Tolosana | E27: 2021 | F27: IEEE TPAMI | G27: Journal | H27: Soft-biometric privacy | I27: Soft-biometric privacy | J27: CelebA, LFW, DiveFace | K27: ResNet-50, VGG-Face | L27: Adds a sensitive-information removal term to representation learning so the embedding is agnostic to gender and ethnicity. | M27: Kept recognition accuracy while sharply reducing attribute predictability; also framed as a fairness tool. | N27: Attribute inference and discriminatory use of embeddings. | O27: Recognition. | P27: Agnosticism measured against specific classifiers. | Q27: agnostic representation, triplet loss, fairness | R27: No | T27: https://arxiv.org/abs/1902.00334 | U27: Search
A28: 24 | B28: qiu2021 | C28: SynFace: Face Recognition with Synthetic Data | D28: Haibo Qiu, Baosheng Yu, Dihong Gong, Zhifeng Li, Wei Liu, Dacheng Tao | E28: 2021 | F28: ICCV | G28: Vision | H28: Training-data privacy & synthetic data | I28: Training data & unlearning | J28: Synthetic (DiscoFaceGAN); LFW, CFP-FP, AgeDB, CALFW, CPLFW | K28: ResNet-50 ArcFace | L28: Trains recognisers on faces from a disentangled face GAN with identity mixup and domain mixup to close the gap to real data. | M28: Demonstrated viable recognition from synthetic-only training and diagnosed the intra-class diversity gap. | N28: Consent and scraping risks of real training sets. | O28: Recognition accuracy (lower than real data). | P28: Generator itself trained on real faces; identity leakage from generator possible. | Q28: synthetic data, GAN, identity mixup | R28: Yes | S28: https://github.com/haibo-qiu/SynFace | T28: https://arxiv.org/abs/2108.07960 | U28: Search
A29: 25 | B29: yang2021 | C29: Towards Face Encryption by Generating Adversarial Identity Masks | D29: Xiao Yang, Yinpeng Dong, Tianyu Pang, Hang Su, Jun Zhu, Yuefeng Chen, Hui Xue | E29: 2021 | F29: ICCV | G29: Vision | H29: Adversarial privacy | I29: Adversarial & unlearnable | J29: LFW, MegaFace | K29: ArcFace, CosFace, FaceNet, SphereFace, MobileFace, ResNet-50 | L29: Targeted Identity-Protection Iterative Method: optimises masks toward a set of target identities with an MMD naturalness loss for imperceptibility and transfer. | M29: Over 95% protection success against several state-of-the-art recognisers in open-set tests. | N29: Unknown black-box recognisers. | O29: Natural-looking images. | P29: Evaluated against fixed models; adaptive retraining not covered. | Q29: TIP-IM, identity mask, transferability | R29: Yes | S29: https://github.com/ShawnXYang/TIP-IM | T29: https://arxiv.org/abs/2003.06814 | U29: Search
A30: 26 | B30: hazirbas2021 | C30: Towards Measuring Fairness in AI: The Casual Conversations Dataset | D30: Caner Hazirbas, Joanna Bitton, Brian Dolhansky, Jacqueline Pan, Albert Gordo, Cristian Canton Ferrer | E30: 2021 | F30: IEEE TBIOM (CVPR Workshops 2021) | G30: Biometrics | H30: Training-data privacy & synthetic data | I30: Training data & unlearning | J30: Casual Conversations (45,186 videos) | K30: Benchmark for deepfake detection and attribute models | L30: A dataset of 3,011 paid, consenting participants with self-reported age and gender and annotated skin tone, licensed for evaluation only. | M30: Demonstrated that a consented, compensated face dataset for fairness evaluation is feasible at scale. | N30: Consent and compensation in face data. | O30: Fairness evaluation. | P30: Evaluation-only licence; US participants. | Q30: consented dataset, fairness, paid participants | R30: No | T30: https://arxiv.org/abs/2104.02821 | U30: Search
A31: 27 | B31: huang2021ue | C31: Unlearnable Examples: Making Personal Data Unexploitable | D31: Hanxun Huang, Xingjun Ma, Sarah Monazam Erfani, James Bailey, Yisen Wang | E31: 2021 | F31: ICLR (spotlight) | G31: ML | H31: Unlearnable images & anti-customisation | I31: Adversarial & unlearnable | J31: CIFAR-10, CIFAR-100, SVHN, ImageNet subset, WebFace subset | K31: ResNet-18, ResNet-50, VGG-11, DenseNet-121 | L31: Error-minimising noise: a bi-level optimisation finds small perturbations that make training loss vanish so a model learns the noise instead of the content, sample-wise or class-wise. | M31: Models trained on unlearnable CIFAR and ImageNet subsets fell to near-chance test accuracy; a face case study on WebFace identities showed personal photos could be made unlearnable. | N31: Unauthorised training on scraped personal images. | O31: Images look unchanged. | P31: Adversarial training largely restores learnability (Fu et al. 2022); JPEG or grayscale compression removes the noise (Liu et al. 2023); diffusion purification too. | Q31: unlearnable examples, error-minimizing noise, availability poisoning | R31: Yes | S31: https://github.com/HanxunH/Unlearnable-Examples | T31: https://arxiv.org/abs/2101.04898 | U31: Search

Sheet 2022
A1: 2022
A2: 24 entries published or first released in 2022.
A4: # | B4: ID | C4: Paper title | D4: Authors | E4: Year | F4: Venue | G4: Venue type | H4: Family | I4: Chart group | J4: Datasets | K4: Models / backbones | L4: Approach | M4: Key findings | N4: Threat model / protects against | O4: Utility preserved | P4: Limitations & known attacks | Q4: Tags | R4: Code available | S4: GitHub / code link | T4: Paper link | U4: Google Scholar
A5: 1 | B5: nguyen2022 | C5: A Survey of Machine Unlearning | D5: Thanh Tam Nguyen, Thanh Trung Huynh, Phi Le Nguyen, Alan Wee-Chung Liew, Hongzhi Yin, Quoc Viet Hung Nguyen | E5: 2022 | F5: arXiv preprint | G5: Preprint | H5: Machine unlearning & auditing | I5: Training data & unlearning | J5: Survey | K5: Survey | L5: Survey of unlearning definitions, exact and approximate methods, verification and datasets. | M5: The most-cited map of the field; documents the lack of standard verification. | N5: Not applicable. | O5: Not applicable. | P5: Fast-moving field. | Q5: survey, machine unlearning | R5: Yes | S5: https://github.com/tamlhp/awesome-machine-unlearning | T5: https://arxiv.org/abs/2209.02299 | U5: Search
A6: 2 | B6: zolfi2022 | C6: Adversarial Mask: Real-World Universal Adversarial Attack on Face Recognition Models | D6: Alon Zolfi, Shai Avidan, Yuval Elovici, Asaf Shabtai | E6: 2022 | F6: ECML PKDD | G6: ML | H6: Adversarial privacy | I6: Adversarial & unlearnable | J6: Own collected videos; CASIA-WebFace | K6: ArcFace, CosFace, FaceNet, MagFace | L6: A single printed fabric mask pattern that makes many wearers unrecognisable to face recognition models. | M6: Universal dodging in physical tests; transferable to unseen models. | N6: Physical recognition in masked settings. | O6: A patterned face mask. | P6: Mask-aware retraining reduces effect. | Q6: universal, fabric mask, physical | R6: Yes | S6: https://github.com/AlonZolfi/AdversarialMask | T6: https://arxiv.org/abs/2111.10759 | U6: Search
A7: 3 | B7: wei2022 | C7: Adversarial Sticker: A Stealthy Attack Method in the Physical World | D7: Xingxing Wei, Ying Guo, Jie Yu | E7: 2022 | F7: IEEE TPAMI | G7: Journal | H7: Adversarial privacy | I7: Adversarial & unlearnable | J7: LFW, CelebA | K7: FaceNet, ArcFace, CosFace | L7: Places ordinary-looking stickers (cartoons, logos) on the face and optimises only their position and rotation for dodging or impersonation. | M7: Stealthy physical attacks without odd-looking patterns, transferable across recognisers. | N7: Physical recognition systems. | O7: Looks like a decorative sticker. | P7: Success depends on sticker inventory and camera geometry. | Q7: physical, sticker, meaningful patterns | R7: Yes | S7: https://github.com/jinyugy21/Adv-Stickers_RHDE | T7: https://arxiv.org/abs/2104.06728 | U7: Search
A8: 4 | B8: osorio2022 | C8: An Attack on Facial Soft-Biometric Privacy Enhancement | D8: Dailé Osorio-Roig, Christian Rathgeb, Pawel Drozdowski, Philipp Terhörst, Vitomir Štruc, Christoph Busch | E8: 2022 | F8: IEEE TBIOM | G8: Biometrics | H8: Attacks & evaluations | I8: Attacks & evaluations | J8: LFW, CelebA | K8: ArcFace; PE-MIU, IVE and other privacy enhancers | L8: Recovers suppressed attributes from privacy-enhanced templates by comparing them with a small annotated database, exploiting that similar templates share attributes. | M8: Attribute prediction well above chance against several soft-biometric privacy methods, using only black-box access. | N8: Attacker with privacy-enhanced templates. | O8: Not applicable. | P8: Needs an annotated reference set. | Q8: soft biometrics, attribute recovery, black-box | R8: No | T8: https://arxiv.org/abs/2111.12405 | U8: Search
A9: 5 | B9: sandoval2022 | C9: Autoregressive Perturbations for Data Poisoning | D9: Pedro Sandoval-Segura, Vasu Singla, Jonas Geiping, Micah Goldblum, Tom Goldstein, David W. Jacobs | E9: 2022 | F9: NeurIPS | G9: ML | H9: Unlearnable images & anti-customisation | I9: Adversarial & unlearnable | J9: CIFAR-10, CIFAR-100, SVHN, STL-10 | K9: ResNet-18, VGG, DenseNet | L9: Generates poisoning perturbations from autoregressive processes without access to any model or the rest of the dataset. | M9: Model-free noise transferred across architectures and matched optimisation-based poisons. | N9: Unauthorised training on released data. | O9: Small perturbations. | P9: Removed by the same squeezing and purification defenses. | Q9: availability poisoning, model-free, autoregressive | R9: Yes | S9: https://github.com/psandovalsegura/autoregressive-poisoning | T9: https://arxiv.org/abs/2206.03693 | U9: Search
A10: 6 | B10: yu2022 | C10: Availability Attacks Create Shortcuts | D10: Da Yu, Huishuai Zhang, Wei Chen, Jian Yin, Tie-Yan Liu | E10: 2022 | F10: ACM KDD | G10: ML | H10: Unlearnable images & anti-customisation | I10: Adversarial & unlearnable | J10: CIFAR-10, CIFAR-100, ImageNet subset | K10: ResNet-18, VGG | L10: Explains availability poisons as learnable shortcuts and shows that simple synthetic, linearly separable noise works as well as optimised noise. | M10: Random linearly separable perturbations made data unlearnable without any model in the loop, revealing why such attacks are also easy to remove. | N10: Unauthorised training on released data. | O10: Small perturbations. | P10: Shortcuts are removed by augmentation or compression. | Q10: shortcut learning, synthetic noise, analysis | R10: Yes | S10: https://github.com/dayu11/Availability-Attacks-Create-Shortcuts | T10: https://arxiv.org/abs/2111.00898 | U10: Search
A11: 7 | B11: radiya2022 | C11: Data Poisoning Won't Save You From Facial Recognition | D11: Evani Radiya-Dixit, Sanghyun Hong, Nicholas Carlini, Florian Tramèr | E11: 2022 | F11: ICLR | G11: ML | H11: Attacks & evaluations | I11: Attacks & evaluations | J11: FaceScrub, PubFig | K11: Fawkes and LowKey; ArcFace, MagFace, CLIP-era extractors | L11: Evaluates cloaking as a defense under two attackers: an adaptive one that trains against the cloak, and an oblivious one that simply waits for better models. | M11: Both attackers defeated Fawkes and LowKey; pictures perturbed once must fool every future model, an asymmetry the defender cannot win. Called cloaking a false sense of security. | N11: Recognisers trained on scraped, cloaked photos. | O11: Not applicable. | P11: Does not address physical or per-query protection. | Q11: Fawkes, LowKey, adaptive, oblivious | R11: Yes | S11: https://github.com/ftramer/FaceCure | T11: https://arxiv.org/abs/2106.14851 | U11: Search
A12: 8 | B12: rathgeb2022 | C12: Deep Face Fuzzy Vault: Implementation and Performance | D12: Christian Rathgeb, Johannes Merkle, Johanna Scholz, Benjamin Tams, Vanessa Nesterowicz | E12: 2022 | F12: Computers & Security | G12: Journal | H12: Identity protection: templates & encrypted matching | I12: Template protection | J12: FERET, FRGCv2 | K12: ArcFace; improved fuzzy vault | L12: Maps real-valued deep features to integer sets and protects them with the improved fuzzy vault scheme. | M12: FNMR below 1% at FMR 0.01% in cross-database tests on FERET and FRGCv2, with unlinkability. | N12: Template theft. | O12: Verification accuracy close to unprotected. | P12: Security depends on feature entropy; attacks on fuzzy vaults with auxiliary data remain. | Q12: fuzzy vault, ArcFace, unlinkable | R12: No | T12: https://arxiv.org/abs/2102.02458 | U12: Search
A13: 9 | B13: croft2022 | C13: Differentially Private Facial Obfuscation via Generative Adversarial Networks | D13: William Croft, Jörg-Rüdiger Sack, Wei Shi | E13: 2022 | F13: Future Generation Computer Systems | G13: Journal | H13: Differential privacy | I13: Obfuscation & differential privacy | J13: CelebA | K13: GAN with PCA-steered latent noise | L13: Applies differential privacy to the latent encoding of a GAN, using PCA to steer noise into identity-relevant directions. | M13: Photo-realistic obfuscated faces with a formal privacy budget and measurable utility trade-off. | N13: Identity inference from the released image. | O13: Visual realism and downstream attribute utility. | P13: Privacy is defined over encodings, not faces; interpretation of epsilon remains hard. | Q13: differential privacy, GAN, obfuscation | R13: No | T13: https://doi.org/10.1016/j.future.2021.11.032 | U13: Search
A14: 10 | B14: mi2022 | C14: DuetFace: Collaborative Privacy-Preserving Face Recognition via Channel Splitting in the Frequency Domain | D14: Yuxi Mi, Yuge Huang, Jiazhen Ji, Hongquan Liu, Xingkun Xu, Shouhong Ding, Shuigeng Zhou | E14: 2022 | F14: ACM Multimedia | G14: Vision | H14: Identity protection: templates & encrypted matching | I14: Template protection | J14: CASIA-WebFace, MS1M (train); LFW, CFP-FP, AgeDB, IJB-B, IJB-C | K14: Split ResNet client/server | L14: Splits frequency channels by energy: the client keeps the visually crucial low-frequency part, the server runs on the rest, with an attention-transfer block between them. | M14: Recognition close to baseline with the server seeing only visually indistinguishable high-frequency channels. | N14: Untrusted inference server. | O14: Recognition accuracy. | P14: Client compute required; partial reconstruction risk. | Q14: split inference, frequency, client-server | R14: Yes | S14: https://github.com/Tencent/TFace | T14: https://arxiv.org/abs/2207.07340 | U14: Search
A15: 11 | B15: liu2022fedfr | C15: FedFR: Joint Optimization Federated Framework for Generic and Personalized Face Recognition | D15: Chih-Ting Liu, Chien-Yi Wang, Shao-Yi Chien, Shang-Hong Lai | E15: 2022 | F15: AAAI | G15: ML | H15: Training-data privacy & synthetic data | I15: Training data & unlearning | J15: MS1M-RetinaFace (pretrain); VGGFace2 clients; IJB-C | K15: ResNet-50 | L15: Jointly improves a generic model and per-client personalised models with a decoupled feature customisation module. | M15: Outperformed prior federated face recognition on generic and personalised benchmarks; released a benchmark. | N15: Central collection of face data. | O15: Recognition accuracy. | P15: Server still sees model updates. | Q15: federated learning, personalisation | R15: Yes | S15: https://github.com/jackie840129/FedFR | T15: https://arxiv.org/abs/2112.12496 | U15: Search
A16: 12 | B16: niu2022 | C16: Federated Learning for Face Recognition with Gradient Correction | D16: Yifan Niu, Weihong Deng | E16: 2022 | F16: AAAI | G16: ML | H16: Training-data privacy & synthetic data | I16: Training data & unlearning | J16: MS1M, CASIA-WebFace; LFW, CFP, AgeDB, IJB | K16: ResNet-50 | L16: FedGC corrects class-embedding gradients so that softmax-based training works when classes are split across clients. | M16: Closed much of the gap to centralised training in the federated face setting. | N16: Central collection of face data. | O16: Recognition accuracy. | P16: Model updates can leak; no DP. | Q16: federated learning, gradient correction | R16: No | T16: https://arxiv.org/abs/2112.07246 | U16: Search
A17: 13 | B17: engelsma2022 | C17: HERS: Homomorphically Encrypted Representation Search | D17: Joshua J. Engelsma, Anil K. Jain, Vishnu Naresh Boddeti | E17: 2022 | F17: IEEE TBIOM | G17: Biometrics | H17: Identity protection: templates & encrypted matching | I17: Template protection | J17: LFW, IJB-C, MegaFace-scale gallery, ImageNet | K17: ArcFace features; FHE search | L17: Compresses representations toward their intrinsic dimensionality, encrypts them with FHE, and searches a gallery in the encrypted domain. | M17: Search against a 100 million gallery in about 500 seconds, a 275× speed-up over prior encrypted search, with little accuracy loss. | N17: Server learning probes or gallery. | O17: Identification accuracy preserved. | P17: Still far slower than plaintext search; key management. | Q17: FHE, 1:N search, compression | R17: Yes | S17: https://github.com/human-analysis/hers-encrypted-image-search | T17: https://arxiv.org/abs/2003.12197 | U17: Search
A18: 14 | B18: shahreza2022hybrid | C18: Hybrid Protection of Biometric Templates by Combining Homomorphic Encryption and Cancelable Biometrics | D18: Hatef Otroshi Shahreza, Vedrana Krivokuća Hahn, Sébastien Marcel | E18: 2022 | F18: IJCB | G18: Biometrics | H18: Identity protection: templates & encrypted matching | I18: Template protection | J18: MOBIO, LFW | K18: ArcFace; PolyProtect; CKKS HE | L18: Applies a cancelable transform and then homomorphic encryption so a compromised key or a decrypted template each remains protected by the other layer. | M18: Defense in depth with recognition accuracy preserved and revocability retained. | N18: Template theft and key compromise. | O18: Verification accuracy. | P18: Combined computational cost. | Q18: hybrid, homomorphic encryption, cancelable | R18: No | T18: https://doi.org/10.1109/IJCB54206.2022.10007960 | U18: Search
A19: 15 | B19: iso24745 | C19: ISO/IEC 24745:2022 Information security, cybersecurity and privacy protection: Biometric information protection | D19: ISO/IEC JTC 1/SC 27 | E19: 2022 | F19: International standard | G19: Other | H19: Identity protection: templates & encrypted matching | I19: Template protection | J19: None (standard) | K19: None | L19: Specifies requirements for protected biometric references: irreversibility, unlinkability and renewability, plus architectures for storage and comparison. | M19: The reference definitions used by template protection papers and by regulators assessing biometric systems. | N19: Compromise of stored references. | O19: Not applicable. | P19: Sets requirements, not methods; compliance testing is immature. | Q19: standard, irreversibility, unlinkability, renewability | R19: No | T19: https://www.iso.org/standard/75302.html | U19: Search
A20: 16 | B20: wen2022 | C20: IdentityDP: Differential Private Identification Protection for Face Images | D20: Yunqian Wen, Bo Liu, Ming Ding, Rong Xie, Li Song | E20: 2022 | F20: Neurocomputing | G20: Journal | H20: Differential privacy | I20: Obfuscation & differential privacy | J20: CelebA-HQ, FFHQ, LFW | K20: Disentangled encoder-decoder; ArcFace and FaceNet for evaluation | L20: Disentangles an identity representation, perturbs it with an epsilon-calibrated mechanism, and reconstructs the image. | M20: Privacy budget directly tunes the identity change; high visual similarity and utility for identity-agnostic tasks. | N20: Identity inference from released images. | O20: Attributes, expression, image quality. | P20: DP applies to the latent, so the guarantee on the image is indirect. | Q20: differential privacy, disentanglement, GAN | R20: No | T20: https://arxiv.org/abs/2103.01745 | U20: Search
A21: 17 | B21: zhong2022 | C21: OPOM: Customized Invisible Cloak towards Face Privacy Protection | D21: Yaoyao Zhong, Weihong Deng | E21: 2022 | F21: IEEE TPAMI | G21: Journal | H21: Adversarial privacy | I21: Adversarial & unlearnable | J21: Privacy-Commons (released), LFW, CelebA | K21: ArcFace, CosFace, SphereFace, MobileFace and others | L21: One Person One Mask: a single universal perturbation per person, optimised away from that person's feature subspace modelled by affine hulls, class centres or convex hulls. | M21: One mask protected all of a user's images against multiple recognisers; released the Privacy-Commons dataset. | N21: Unauthorised recognisers on a user's photo collection. | O21: Small perturbation reused across photos. | P21: Static perturbation; vulnerable to adaptive models like other cloaks. | Q21: universal mask, person-specific, feature subspace | R21: Yes | S21: https://github.com/zhongyy/OPOM | T21: https://arxiv.org/abs/2205.11981 | U21: Search
